Workbook

Sheet Cover Sheet
A1: Energy Prices Road Fuels and Other Petroleum Products
A2: Typical retail prices of petroleum products and crude oil price index
A3: Publication date: 26/02/2026
A4: Data period: New monthly road fuels data for February 2026 and crude oil data for January 2026
A5: Next update: 31/03/2026
A6: About this data
A7: Data in these tables show monthly, quarterly and annual road fuel prices, heating oil prices and a crude oil price index.
A8: Data are shown in current (cash) terms with and without tax.
A9: Monthly and quarterly data are available back to 1989 and annual data back to 1977 on the historic data sheets.
A10: Table 4.1.1 shows mid-month monthly figures of this series in the original units used for each fuel type (data is available back to 1989)
A11: Table 4.1.1 (Quarterly) shows quarterly figures of this series in a comparable unit of measurement across fuel types (pence per kilowatt hour) (data is available back to 1989)
A12: Table 4.1.2 shows the annual typical retail prices of petroleum products and a crude oil price index (data is available back to 1977)
... A26: newsdesk@energysecurity.gov.uk

Sheet Contents
A1: Contents
A2: Tables
A3: Table 4.1.1: Monthly retail prices of petroleum products and a crude oil price index
A4: Table 4.1.1: Typical retail prices of petroleum products and a crude oil price index (quarterly)
A5: Table 4.1.2: Annual retail prices of petroleum products and a crude oil price index
A6: Table 4.1.2: Typical retail prices of petroleum products excluding VAT and duty
A7: Table 4.1.3: Typical January retail prices of petroleum products and a crude oil price index
A8: Charts
A9: Charts
A10: Methodology
A11: Methodology notes

Sheet 4.1.1
A1: Table 4.1.1 Typical retail prices of petroleum products and a crude oil price index (monthly)
A2: Note 1. These estimates are generally representative of prices paid on or about the 15th of the month. Estimates are based on information provided by oil marketing companies until December 1994. From January 1995, data from super/hypermarket chains have been included. The very latest data for motor spirit and diesel are provisional, based on a smaller sample than used for preceding months.
A3: Note 2. Data for Premium Unleaded and Diesel are sourced from a larger sample than the Weekly Prices statistics. As such they will be slightly different than the weekly published figures.
A4: Note 3. These estimates are for deliveries of 2,000 to 5,000 litres; such deliveries attracted 8 per cent VAT from 1 April 1994. With effect from 1 September 1997 the rate of VAT was reduced to 5 per cent.
A5: Note 4. Price index for supplies received by refineries in the UK from both indigenous and imported sources. It represents the average for the month calculated in sterling on a cif basis.
A6: Blank cells in this table represent months where data were not reported or avaliable
A7: An r indicates revised data. An r in the date column indicates all data in the row has been revised. An r in a cell indicates that just that cell has been revised.
A8: Freeze panes are turned on. To turn off freeze panes select the 'View' ribbon then 'Freeze Panes' then 'Unfreeze Panes' or use [Alt,W,F]
A9: Source: Department for Energy Security and Net Zero
A10: Year | B10: Month | C10: Motor spirit: 4 star / LRP (Pence per litre) [Note 1] | D10: Motor spirit: Super unleaded (Pence per litre) [Note 1] | E10: Motor spirit: Premium unleaded / ULSP (Pence per litre) [Note 1, 2] | F10: Derv: Diesel / ULSD (Pence per litre) [Note 1, 2] | G10: Standard grade burning oil (Pence per litre) [Note 1] | H10: Gas oil (Pence per litre) [Note 1, 3] | I10: Crude oil acquired by refineries 2010 = 100 [Note 4] | J10: ULSP to ULSD Differential (Pence per litre) | K10: Historic Indices: Crude oil acquired by refineries 2005 = 100 | L10: Historic Indices: Crude oil acquired by refineries 2000 = 100 | M10: Historic Indices: Crude oil acquired by refineries 1995 = 100 | N10: Month / Year
A11: 1989 | B11: January | C11: 37.14 | E11: 36.02 | F11: 34.17 | G11: 11.41 | H11: 11.15 | N11: =(Typical_retail_prices_of_petroleum_products_and_a_crude_oil_price_index_monthly[[#This Row],[Month]]&" "&Typical_retail_prices_of_petroleum_products_and_a_crude_oil_price_index_monthly[[#This Row],[Year]])*1 -> 32509
A12: 1989 | B12: February | C12: 38.3 | E12: 36.88 | F12: 35.03 | G12: 10.83 | H12: 10.49 | N12: =(Typical_retail_prices_of_petroleum_products_and_a_crude_oil_price_index_monthly[[#This Row],[Month]]&" "&Typical_retail_prices_of_petroleum_products_and_a_crude_oil_price_index_monthly[[#This Row],[Year]])*1 -> 32540
A13: 1989 | B13: March | C13: 38.85 | E13: 37.3 | F13: 35.09 | G13: 11.4 | H13: 10.9 | N13: =(Typical_retail_prices_of_petroleum_products_and_a_crude_oil_price_index_monthly[[#This Row],[Month]]&" "&Typical_retail_prices_of_petroleum_products_and_a_crude_oil_price_index_monthly[[#This Row],[Year]])*1 -> 32568
A14: 1989 | B14: April | C14: 41.14 | E14: 39.09 | F14: 36.08 | G14: 11.45 | H14: 10.83 | N14: =(Typical_retail_prices_of_petroleum_products_and_a_crude_oil_price_index_monthly[[#This Row],[Month]]&" "&Typical_retail_prices_of_petroleum_products_and_a_crude_oil_price_index_monthly[[#This Row],[Year]])*1 -> 32599
A15: 1989 | B15: May | C15: 42.83 | E15: 40.81 | F15: 36.06 | G15: 11.41 | H15: 10.81 | N15: =(Typical_retail_prices_of_petroleum_products_and_a_crude_oil_price_index_monthly[[#This Row],[Month]]&" "&Typical_retail_prices_of_petroleum_products_and_a_crude_oil_price_index_monthly[[#This Row],[Year]])*1 -> 32629
A16: 1989 | B16: June | C16: 42.7 | E16: 40.74 | F16: 35.93 | G16: 11.48 | H16: 11.26 | N16: =(Typical_retail_prices_of_petroleum_products_and_a_crude_oil_price_index_monthly[[#This Row],[Month]]&" "&Typical_retail_prices_of_petroleum_products_and_a_crude_oil_price_index_monthly[[#This Row],[Year]])*1 -> 32660
A17: 1989 | B17: July | C17: 41.49 | E17: 39.26 | F17: 35.87 | G17: 11 | H17: 10.91 | N17: =(Typical_retail_prices_of_petroleum_products_and_a_crude_oil_price_index_monthly[[#This Row],[Month]]&" "&Typical_retail_prices_of_petroleum_products_and_a_crude_oil_price_index_monthly[[#This Row],[Year]])*1 -> 32690
A18: 1989 | B18: August | C18: 39.92 | E18: 37.4 | F18: 35.7 | G18: 11.48 | H18: 11.19 | N18: =(Typical_retail_prices_of_petroleum_products_and_a_crude_oil_price_index_monthly[[#This Row],[Month]]&" "&Typical_retail_prices_of_petroleum_products_and_a_crude_oil_price_index_monthly[[#This Row],[Year]])*1 -> 32721
A19: 1989 | B19: September | C19: 40.79 | E19: 38.19 | F19: 36 | G19: 12.33 | H19: 11.89 | N19: =(Typical_retail_prices_of_petroleum_products_and_a_crude_oil_price_index_monthly[[#This Row],[Month]]&" "&Typical_retail_prices_of_petroleum_products_and_a_crude_oil_price_index_monthly[[#This Row],[Year]])*1 -> 32752
A20: 1989 | B20: October | C20: 40.89 | E20: 38.3 | F20: 37.33 | G20: 13.13 | H20: 12.5 | N20: =(Typical_retail_prices_of_petroleum_products_and_a_crude_oil_price_index_monthly[[#This Row],[Month]]&" "&Typical_retail_prices_of_petroleum_products_and_a_crude_oil_price_index_monthly[[#This Row],[Year]])*1 -> 32782
A21: 1989 | B21: November | C21: 40.68 | E21: 38.08 | F21: 37.76 | G21: 13.79 | H21: 13.28 | N21: =(Typical_retail_prices_of_petroleum_products_and_a_crude_oil_price_index_monthly[[#This Row],[Month]]&" "&Typical_retail_prices_of_petroleum_products_and_a_crude_oil_price_index_monthly[[#This Row],[Year]])*1 -> 32813
A22: 1989 | B22: December | C22: 39.97 | E22: 37.38 | F22: 39.16 | G22: 14.71 | H22: 14.44 | N22: =(Typical_retail_prices_of_petroleum_products_and_a_crude_oil_price_index_monthly[[#This Row],[Month]]&" "&Typical_retail_prices_of_petroleum_products_and_a_crude_oil_price_index_monthly[[#This Row],[Year]])*1 -> 32843
... A34: 1990 | B34: December | C34: 44.28 | E34: 41.29 | F34: 43.7 | G34: 17.67 | H34: 17.35 | N34: =(Typical_retail_prices_of_petroleum_products_and_a_crude_oil_price_index_monthly[[#This Row],[Month]]&" "&Typical_retail_prices_of_petroleum_products_and_a_crude_oil_price_index_monthly[[#This Row],[Year]])*1 -> 33208
A35: 1991 | B35: January | C35: 45.13 | D35: 44.38 | E35: 42.14 | F35: 43.31 | G35: 17.52 | H35: 17.13 | J35: =F35-E35 -> 1.17 | K35: 44.816254 | L35: 70.279371 | M35: 121.4 | N35: =(Typical_retail_prices_of_petroleum_products_and_a_crude_oil_price_index_monthly[[#This Row],[Month]]&" "&Typical_retail_prices_of_petroleum_products_and_a_crude_oil_price_index_monthly[[#This Row],[Year]])*1 -> 33239
A36: 1991 | B36: February | C36: 43.62 | D36: 42.91 | E36: 40.61 | F36: 43.19 | G36: 16.68 | H36: 15.39 | J36: =F36-E36 -> 2.58 | K36: 35.712722 | L36: 56.003512 | M36: 96.74 | N36: =(Typical_retail_prices_of_petroleum_products_and_a_crude_oil_price_index_monthly[[#This Row],[Month]]&" "&Typical_retail_prices_of_petroleum_products_and_a_crude_oil_price_index_monthly[[#This Row],[Year]])*1 -> 33270
A37: 1991 | B37: March | C37: 44.74 | D37: 43.8 | E37: 41.66 | F37: 40.31 | G37: 13.54 | H37: 13.4 | J37: =F37-E37 -> -1.35 | K37: 35.465383 | L37: 55.615644 | M37: 96.07 | N37: =(Typical_retail_prices_of_petroleum_products_and_a_crude_oil_price_index_monthly[[#This Row],[Month]]&" "&Typical_retail_prices_of_petroleum_products_and_a_crude_oil_price_index_monthly[[#This Row],[Year]])*1 -> 33298
A38: 1991 | B38: April | C38: 49.03 | D38: 47.52 | E38: 45.41 | F38: 43.41 | G38: 12.49 | H38: 12.16 | J38: =F38-E38 -> -2 | K38: 36.993714 | L38: 58.012321 | M38: 100.21 | N38: =(Typical_retail_prices_of_petroleum_products_and_a_crude_oil_price_index_monthly[[#This Row],[Month]]&" "&Typical_retail_prices_of_petroleum_products_and_a_crude_oil_price_index_monthly[[#This Row],[Year]])*1 -> 33329
A39: 1991 | B39: May | C39: 50.16 | D39: 48.94 | E39: 46.64 | F39: 43.64 | G39: 13.15 | H39: 12.91 | J39: =F39-E39 -> -3 | K39: 37.444091 | L39: 58.718588 | M39: 101.43 | N39: =(Typical_retail_prices_of_petroleum_products_and_a_crude_oil_price_index_monthly[[#This Row],[Month]]&" "&Typical_retail_prices_of_petroleum_products_and_a_crude_oil_price_index_monthly[[#This Row],[Year]])*1 -> 33359
A40: 1991 | B40: June | C40: 50.04 | D40: 48.76 | E40: 46.53 | F40: 43.64 | G40: 13.38 | H40: 13.05 | J40: =F40-E40 -> -2.89 | K40: 37.421942 | L40: 58.683854 | M40: 101.37 | N40: =(Typical_retail_prices_of_petroleum_products_and_a_crude_oil_price_index_monthly[[#This Row],[Month]]&" "&Typical_retail_prices_of_petroleum_products_and_a_crude_oil_price_index_monthly[[#This Row],[Year]])*1 -> 33390
A41: 1991 | B41: July | C41: 50.65 | D41: 49.35 | E41: 47.08 | F41: 44.26 | G41: 13.67 | H41: 12.97 | J41: =F41-E41 -> -2.82 | K41: 38.776766 | L41: 60.808444 | M41: 105.04 | N41: =(Typical_retail_prices_of_petroleum_products_and_a_crude_oil_price_index_monthly[[#This Row],[Month]]&" "&Typical_retail_prices_of_petroleum_products_and_a_crude_oil_price_index_monthly[[#This Row],[Year]])*1 -> 33420
A42: 1991 | B42: August | C42: 50.23 | D42: 48.9 | E42: 46.71 | F42: 44.17 | G42: 13.33 | H42: 12.71 | J42: =F42-E42 -> -2.54 | K42: 39.415416 | L42: 61.809954 | M42: 106.77 | N42: =(Typical_retail_prices_of_petroleum_products_and_a_crude_oil_price_index_monthly[[#This Row],[Month]]&" "&Typical_retail_prices_of_petroleum_products_and_a_crude_oil_price_index_monthly[[#This Row],[Year]])*1 -> 33451
A43: 1991 | B43: September | C43: 50.11 | D43: 48.85 | E43: 46.58 | F43: 44.24 | G43: 13.64 | H43: 13.01 | J43: =F43-E43 -> -2.34 | K43: 40.039299 | L43: 62.788308 | M43: 108.46 | N43: =(Typical_retail_prices_of_petroleum_products_and_a_crude_oil_price_index_monthly[[#This Row],[Month]]&" "&Typical_retail_prices_of_petroleum_products_and_a_crude_oil_price_index_monthly[[#This Row],[Year]])*1 -> 33482
A44: 1991 | B44: October | C44: 49.99 | D44: 48.7 | E44: 46.48 | F44: 45.1 | G44: 14.18 | H44: 13.66 | J44: =F44-E44 -> -1.38 | K44: 42.029082 | L44: 65.908619 | M44: 113.85 | N44: =(Typical_retail_prices_of_petroleum_products_and_a_crude_oil_price_index_monthly[[#This Row],[Month]]&" "&Typical_retail_prices_of_petroleum_products_and_a_crude_oil_price_index_monthly[[#This Row],[Year]])*1 -> 33512
A45: 1991 | B45: November | C45: 49.69 | D45: 48.44 | E45: 46.18 | F45: 46.05 | G45: 14.33 | H45: 14.25 | J45: =F45-E45 -> -0.13 | K45: 42.442543 | L45: 66.556996 | M45: 114.97 | N45: =(Typical_retail_prices_of_petroleum_products_and_a_crude_oil_price_index_monthly[[#This Row],[Month]]&" "&Typical_retail_prices_of_petroleum_products_and_a_crude_oil_price_index_monthly[[#This Row],[Year]])*1 -> 33543
A46: 1991 | B46: December | C46: 48.39 | D46: 47.12 | E46: 44.86 | F46: 44.5 | G46: 13.43 | H46: 13.16 | J46: =F46-E46 -> -0.36 | K46: 36.517495 | L46: 57.26553 | M46: 98.92 | N46: =(Typical_retail_prices_of_petroleum_products_and_a_crude_oil_price_index_monthly[[#This Row],[Month]]&" "&Typical_retail_prices_of_petroleum_products_and_a_crude_oil_price_index_monthly[[#This Row],[Year]])*1 -> 33573
... A94: 1995 | B94: December | C94: 61.83 | D94: 60.74 | E94: 55.7 | F94: 56.8 | G94: 14.69 | H94: 14.92 | J94: =F94-E94 -> 1.1 | K94: 39.463407 | L94: 61.885212 | M94: 106.9 | N94: =(Typical_retail_prices_of_petroleum_products_and_a_crude_oil_price_index_monthly[[#This Row],[Month]]&" "&Typical_retail_prices_of_petroleum_products_and_a_crude_oil_price_index_monthly[[#This Row],[Year]])*1 -> 35034
A95: 1996 | B95: January | C95: 61.97 | D95: 61.26 | E95: 55.93 | F95: 57.43 | G95: 15.38 | H95: 15.86 | I95: 23.342423 | J95: =F95-E95 -> 1.5 | K95: 40.904203 | L95: 64.144621 | M95: 110.9 | N95: =(Typical_retail_prices_of_petroleum_products_and_a_crude_oil_price_index_monthly[[#This Row],[Month]]&" "&Typical_retail_prices_of_petroleum_products_and_a_crude_oil_price_index_monthly[[#This Row],[Year]])*1 -> 35065
A96: 1996 | B96: February | C96: 59.72 | D96: 59.22 | E96: 54.45 | F96: 55.65 | G96: 15.08 | H96: 15.61 | I96: 22.889426 | J96: =F96-E96 -> 1.2 | K96: 40.074773 | L96: 62.843936 | M96: 108.54 | N96: =(Typical_retail_prices_of_petroleum_products_and_a_crude_oil_price_index_monthly[[#This Row],[Month]]&" "&Typical_retail_prices_of_petroleum_products_and_a_crude_oil_price_index_monthly[[#This Row],[Year]])*1 -> 35096
A97: 1996 | B97: March | C97: 59.28 | D97: 59.12 | E97: 54.2 | F97: 55.4 | G97: 16.03 | H97: 16.33 | I97: 25.607715 | J97: =F97-E97 -> 1.2 | K97: 44.652326 | L97: 70.022305 | M97: 120.58 | N97: =(Typical_retail_prices_of_petroleum_products_and_a_crude_oil_price_index_monthly[[#This Row],[Month]]&" "&Typical_retail_prices_of_petroleum_products_and_a_crude_oil_price_index_monthly[[#This Row],[Year]])*1 -> 35125
A98: 1996 | B98: April | C98: 60.35 | D98: 60.19 | E98: 55.24 | F98: 56.42 | G98: 16.57 | H98: 17.05 | I98: 27.415084 | J98: =F98-E98 -> 1.18 | K98: 47.905135 | L98: 75.123252 | M98: 129.58 | N98: =(Typical_retail_prices_of_petroleum_products_and_a_crude_oil_price_index_monthly[[#This Row],[Month]]&" "&Typical_retail_prices_of_petroleum_products_and_a_crude_oil_price_index_monthly[[#This Row],[Year]])*1 -> 35156
A99: 1996 | B99: May | C99: 60.28 | D99: 62.92 | E99: 55.13 | F99: 56.23 | G99: 15.26 | H99: 15.78 | I99: 25.160352 | J99: =F99-E99 -> 1.1 | K99: 44.164004 | L99: 69.256534 | M99: 119.69 | N99: =(Typical_retail_prices_of_petroleum_products_and_a_crude_oil_price_index_monthly[[#This Row],[Month]]&" "&Typical_retail_prices_of_petroleum_products_and_a_crude_oil_price_index_monthly[[#This Row],[Year]])*1 -> 35186
A100: 1996 | B100: June | C100: 59.64 | D100: 62.89 | E100: 54.67 | F100: 55.6 | G100: 14.45 | H100: 15.05 | I100: 23.659403 | J100: =F100-E100 -> 0.93 | K100: 41.461884 | L100: 65.019158 | M100: 112.37 | N100: =(Typical_retail_prices_of_petroleum_products_and_a_crude_oil_price_index_monthly[[#This Row],[Month]]&" "&Typical_retail_prices_of_petroleum_products_and_a_crude_oil_price_index_monthly[[#This Row],[Year]])*1 -> 35217
A101: 1996 | B101: July | C101: 59.49 | D101: 62.89 | E101: 54.34 | F101: 55.22 | G101: 14.63 | H101: 15.43 | I101: 24.776133 | J101: =F101-E101 -> 0.88 | K101: 43.221876 | L101: 67.77912 | M101: 116.81 | N101: =(Typical_retail_prices_of_petroleum_products_and_a_crude_oil_price_index_monthly[[#This Row],[Month]]&" "&Typical_retail_prices_of_petroleum_products_and_a_crude_oil_price_index_monthly[[#This Row],[Year]])*1 -> 35247
A102: 1996 | B102: August | C102: 61.51 | D102: 65.26 | E102: 56.77 | F102: 57.62 | G102: 14.93 | H102: 15.52 | I102: 25.756688 | J102: =F102-E102 -> 0.85 | K102: 45.056649 | L102: 70.65635 | M102: 121.96 | N102: =(Typical_retail_prices_of_petroleum_products_and_a_crude_oil_price_index_monthly[[#This Row],[Month]]&" "&Typical_retail_prices_of_petroleum_products_and_a_crude_oil_price_index_monthly[[#This Row],[Year]])*1 -> 35278
A103: 1996 | B103: September | C103: 63.04 | D103: 66.64 | E103: 58.24 | F103: 58.79 | G103: 17.05 | H103: 17.51 | I103: 27.738946 | J103: =F103-E103 -> 0.55 | K103: 48.486942 | L103: 76.035622 | M103: 131.07 | N103: =(Typical_retail_prices_of_petroleum_products_and_a_crude_oil_price_index_monthly[[#This Row],[Month]]&" "&Typical_retail_prices_of_petroleum_products_and_a_crude_oil_price_index_monthly[[#This Row],[Year]])*1 -> 35309
A104: 1996 | B104: October | C104: 63.71 | D104: 66.78 | E104: 58.78 | F104: 60.67 | G104: 17.99 | H104: 18.71 | I104: 29.481854 | J104: =F104-E104 -> 1.89 | K104: 51.454781 | L104: 80.68969 | M104: 138.84 | N104: =(Typical_retail_prices_of_petroleum_products_and_a_crude_oil_price_index_monthly[[#This Row],[Month]]&" "&Typical_retail_prices_of_petroleum_products_and_a_crude_oil_price_index_monthly[[#This Row],[Year]])*1 -> 35339
A105: 1996 | B105: November | C105: 64.26 | D105: 67.34 | E105: 59.25 | F105: 60.85 | G105: 16.79 | H105: 17.62 | I105: 26.72295 | J105: =F105-E105 -> 1.6 | K105: 46.818255 | L105: 73.418842 | M105: 126.89 | N105: =(Typical_retail_prices_of_petroleum_products_and_a_crude_oil_price_index_monthly[[#This Row],[Month]]&" "&Typical_retail_prices_of_petroleum_products_and_a_crude_oil_price_index_monthly[[#This Row],[Year]])*1 -> 35370
A106: 1996 | B106: December | C106: 66.33 | D106: 69.58 | E106: 61.25 | F106: 62.59 | G106: 17.02 | H106: 17.88 | I106: 27.984003 | J106: =F106-E106 -> 1.34 | K106: 48.903144 | L106: 76.688297 | M106: 132.26 | N106: =(Typical_retail_prices_of_petroleum_products_and_a_crude_oil_price_index_monthly[[#This Row],[Month]]&" "&Typical_retail_prices_of_petroleum_products_and_a_crude_oil_price_index_monthly[[#This Row],[Year]])*1 -> 35400
... A186: 2003 | B186: August | C186: 79.77 | D186: 81.26 | E186: 75.73 | F186: 77.32 | G186: 17.32 | H186: 18.51 | I186: 35.757914 | J186: =F186-E186 -> 1.59 | K186: 62.576832 | L186: 98.14808 | M186: 170.3 | N186: =(Typical_retail_prices_of_petroleum_products_and_a_crude_oil_price_index_monthly[[#This Row],[Month]]&" "&Typical_retail_prices_of_petroleum_products_and_a_crude_oil_price_index_monthly[[#This Row],[Year]])*1 -> 37834
A187: 2003 | B187: September | C187: 79.81 | D187: 81.17 | E187: 76.1 | F187: 77.55 | G187: 16.81 | H187: 17.94 | I187: 32.158924 | J187: =F187-E187 -> 1.45 | K187: 56.280487 | L187: 88.07219 | M187: .. | N187: =(Typical_retail_prices_of_petroleum_products_and_a_crude_oil_price_index_monthly[[#This Row],[Month]]&" "&Typical_retail_prices_of_petroleum_products_and_a_crude_oil_price_index_monthly[[#This Row],[Year]])*1 -> 37865
A188: 2003 | B188: October | C188: 80.05 | D188: 81.31 | E188: 75.84 | F188: 77.38 | G188: 17.07 | H188: 18.6 | I188: 33.976689 | J188: =F188-E188 -> 1.54 | K188: 59.465651 | L188: 93.345352 | N188: =(Typical_retail_prices_of_petroleum_products_and_a_crude_oil_price_index_monthly[[#This Row],[Month]]&" "&Typical_retail_prices_of_petroleum_products_and_a_crude_oil_price_index_monthly[[#This Row],[Year]])*1 -> 37895
A189: 2003 | B189: November | C189: 80.19 | D189: 81.4 | E189: 75.86 | F189: 77.45 | G189: 17.55 | H189: 18.74 | I189: 33.02077 | J189: =F189-E189 -> 1.59 | K189: 57.808322 | L189: 90.633255 | N189: =(Typical_retail_prices_of_petroleum_products_and_a_crude_oil_price_index_monthly[[#This Row],[Month]]&" "&Typical_retail_prices_of_petroleum_products_and_a_crude_oil_price_index_monthly[[#This Row],[Year]])*1 -> 37926
A190: 2003 | B190: December | C190: 80.25 | D190: 81.32 | E190: 75.88 | F190: 77.56 | G190: 18.2 | H190: 18.47 | I190: 33.104507 | J190: =F190-E190 -> 1.68 | K190: 57.940185 | L190: 90.909291 | N190: =(Typical_retail_prices_of_petroleum_products_and_a_crude_oil_price_index_monthly[[#This Row],[Month]]&" "&Typical_retail_prices_of_petroleum_products_and_a_crude_oil_price_index_monthly[[#This Row],[Year]])*1 -> 37956
A191: 2004 | B191: January | C191: 80.04 | D191: 81.49 | E191: 76.2 | F191: 77.92 | G191: 18.33 | H191: 18.95 | I191: 32.168737 | J191: =F191-E191 -> 1.72 | K191: 56.391294 | L191: 88.3 | N191: =(Typical_retail_prices_of_petroleum_products_and_a_crude_oil_price_index_monthly[[#This Row],[Month]]&" "&Typical_retail_prices_of_petroleum_products_and_a_crude_oil_price_index_monthly[[#This Row],[Year]])*1 -> 37987
A192: 2004 | B192: February | C192: 79.89 | D192: 81.42 | E192: 76.36 | F192: 77.93 | G192: 17.73 | H192: 17.58 | I192: 31.824831 | J192: =F192-E192 -> 1.57 | K192: 55.69972 | L192: 87.4 | N192: =(Typical_retail_prices_of_petroleum_products_and_a_crude_oil_price_index_monthly[[#This Row],[Month]]&" "&Typical_retail_prices_of_petroleum_products_and_a_crude_oil_price_index_monthly[[#This Row],[Year]])*1 -> 38018
A193: 2004 | B193: March | C193: 80.96 | D193: 82.36 | E193: 77.15 | F193: 78.6 | G193: 17.97 | H193: 18.71 | I193: 35.283605 | J193: =F193-E193 -> 1.45 | K193: 61.740841 | L193: 96.9 | N193: =(Typical_retail_prices_of_petroleum_products_and_a_crude_oil_price_index_monthly[[#This Row],[Month]]&" "&Typical_retail_prices_of_petroleum_products_and_a_crude_oil_price_index_monthly[[#This Row],[Year]])*1 -> 38047
A194: 2004 | B194: April | C194: 81.25 | D194: 82.53 | E194: 77.81 | F194: 79.21 | G194: 18.31 | H194: 19.5 | I194: 35.229265 | J194: =F194-E194 -> 1.4 | K194: 61.600769 | L194: 96.7 | N194: =(Typical_retail_prices_of_petroleum_products_and_a_crude_oil_price_index_monthly[[#This Row],[Month]]&" "&Typical_retail_prices_of_petroleum_products_and_a_crude_oil_price_index_monthly[[#This Row],[Year]])*1 -> 38078
A195: 2004 | B195: May | C195: 84.32 | D195: 86.24 | E195: 81.02 | F195: 82.32 | G195: 21.12 | H195: 20.89 | I195: 40.253177 | J195: =F195-E195 -> 1.3 | K195: 70.44249 | L195: 110.5 | N195: =(Typical_retail_prices_of_petroleum_products_and_a_crude_oil_price_index_monthly[[#This Row],[Month]]&" "&Typical_retail_prices_of_petroleum_products_and_a_crude_oil_price_index_monthly[[#This Row],[Year]])*1 -> 38108
A196: 2004 | B196: June | C196: 85.01 | D196: 87.06 | E196: 81.7 | F196: 82.86 | G196: 19.77 | H196: 20.56 | I196: 37.043386 | J196: =F196-E196 -> 1.16 | K196: 64.905667 | L196: 101.7 | N196: =(Typical_retail_prices_of_petroleum_products_and_a_crude_oil_price_index_monthly[[#This Row],[Month]]&" "&Typical_retail_prices_of_petroleum_products_and_a_crude_oil_price_index_monthly[[#This Row],[Year]])*1 -> 38139
A197: 2004 | B197: July | C197: 84.77 | D197: 86.23 | E197: 80.35 | F197: 81.17 | G197: 20.69 | H197: 21.42 | I197: 38.922931 | J197: =F197-E197 -> 0.82 | K197: 68.252814 | L197: 106.9 | N197: =(Typical_retail_prices_of_petroleum_products_and_a_crude_oil_price_index_monthly[[#This Row],[Month]]&" "&Typical_retail_prices_of_petroleum_products_and_a_crude_oil_price_index_monthly[[#This Row],[Year]])*1 -> 38169
A198: 2004 | B198: August | C198: 85.29 | D198: 86.64 | E198: 81.14 | F198: 82.28 | G198: 22.84 | H198: 23.58 | I198: 45.487383 | J198: =F198-E198 -> 1.14 | K198: 79.614644 | L198: 124.9 | N198: =(Typical_retail_prices_of_petroleum_products_and_a_crude_oil_price_index_monthly[[#This Row],[Month]]&" "&Typical_retail_prices_of_petroleum_products_and_a_crude_oil_price_index_monthly[[#This Row],[Year]])*1 -> 38200
A199: 2004 | B199: September | C199: 86.15 | D199: 86.74 | E199: 81.25 | F199: 82.94 | G199: 23.58 | H199: 23.96 | I199: 46.317146 | J199: =F199-E199 -> 1.69 | K199: 81.078529 | L199: 127.2 | N199: =(Typical_retail_prices_of_petroleum_products_and_a_crude_oil_price_index_monthly[[#This Row],[Month]]&" "&Typical_retail_prices_of_petroleum_products_and_a_crude_oil_price_index_monthly[[#This Row],[Year]])*1 -> 38231
... A210: 2005 | B210: August | C210: 91.99 | D210: 96.59 | E210: 90.4 | F210: 94.33 | G210: 32.11 | H210: 33.47 | I210: 68.211611 | J210: =F210-E210 -> 3.93 | K210: 119.39025 | L210: 187.3 | N210: =(Typical_retail_prices_of_petroleum_products_and_a_crude_oil_price_index_monthly[[#This Row],[Month]]&" "&Typical_retail_prices_of_petroleum_products_and_a_crude_oil_price_index_monthly[[#This Row],[Year]])*1 -> 38565
A211: 2005 | B211: September | D211: 99.48 | E211: 94.77 | F211: 97.58 | G211: 33.57 | H211: 35.54 | I211: 66.271073 | J211: =F211-E211 -> 2.81 | K211: 115.99747 | L211: 182 | N211: =(Typical_retail_prices_of_petroleum_products_and_a_crude_oil_price_index_monthly[[#This Row],[Month]]&" "&Typical_retail_prices_of_petroleum_products_and_a_crude_oil_price_index_monthly[[#This Row],[Year]])*1 -> 38596
A212: 2005 | B212: October | D212: 100.3 | E212: 94 | F212: 96.94 | G212: 34.95 | H212: 36.34 | I212: 63.669871 | J212: =F212-E212 -> 2.94 | K212: 111.43426 | L212: 174.8 | N212: =(Typical_retail_prices_of_petroleum_products_and_a_crude_oil_price_index_monthly[[#This Row],[Month]]&" "&Typical_retail_prices_of_petroleum_products_and_a_crude_oil_price_index_monthly[[#This Row],[Year]])*1 -> 38626
A213: 2005 | B213: November | D213: 97.11 | E213: 90.3 | F213: 94.74 | G213: 31.1 | H213: 33.09 | I213: 62.139886 | J213: =F213-E213 -> 4.44 | K213: 108.80907 | L213: 170.6 | N213: =(Typical_retail_prices_of_petroleum_products_and_a_crude_oil_price_index_monthly[[#This Row],[Month]]&" "&Typical_retail_prices_of_petroleum_products_and_a_crude_oil_price_index_monthly[[#This Row],[Year]])*1 -> 38657
A214: 2005 | B214: December | D214: 95.33 | E214: 87.45 | F214: 91.72 | G214: 30.53 | H214: 33.3 | I214: 62.693403 | J214: =F214-E214 -> 4.27 | K214: 109.72106 | L214: 172.1 | N214: =(Typical_retail_prices_of_petroleum_products_and_a_crude_oil_price_index_monthly[[#This Row],[Month]]&" "&Typical_retail_prices_of_petroleum_products_and_a_crude_oil_price_index_monthly[[#This Row],[Year]])*1 -> 38687
A215: 2006 | B215: January | D215: 94.73 | E215: 88.84 | F215: 93.07 | G215: 31.58 | H215: 33.6 | I215: 67.801238 | J215: =F215-E215 -> 4.23 | K215: 118.6992 | L215: 186.2 | N215: =(Typical_retail_prices_of_petroleum_products_and_a_crude_oil_price_index_monthly[[#This Row],[Month]]&" "&Typical_retail_prices_of_petroleum_products_and_a_crude_oil_price_index_monthly[[#This Row],[Year]])*1 -> 38718
A216: 2006 | B216: February | D216: 96.8 | E216: 89.46 | F216: 93.66 | G216: 32.16 | H216: 33.79 | I216: 66.556468 | J216: =F216-E216 -> 4.2 | K216: 116.49436 | L216: 182.7 | N216: =(Typical_retail_prices_of_petroleum_products_and_a_crude_oil_price_index_monthly[[#This Row],[Month]]&" "&Typical_retail_prices_of_petroleum_products_and_a_crude_oil_price_index_monthly[[#This Row],[Year]])*1 -> 38749
A217: 2006 | B217: March | D217: 96.61 | E217: 89.43 | F217: 93.75 | G217: 32.12 | H217: 34.08 | I217: 67.421517 | J217: =F217-E217 -> 4.32 | K217: 118.14868 | L217: 185.1 | N217: =(Typical_retail_prices_of_petroleum_products_and_a_crude_oil_price_index_monthly[[#This Row],[Month]]&" "&Typical_retail_prices_of_petroleum_products_and_a_crude_oil_price_index_monthly[[#This Row],[Year]])*1 -> 38777
A218: 2006 | B218: April | D218: 99.42 | E218: 94.14 | F218: 97.59 | G218: 33.16 | H218: 35.31 | I218: 75.281295 | J218: =F218-E218 -> 3.45 | K218: 131.72817 | L218: 206.7 | N218: =(Typical_retail_prices_of_petroleum_products_and_a_crude_oil_price_index_monthly[[#This Row],[Month]]&" "&Typical_retail_prices_of_petroleum_products_and_a_crude_oil_price_index_monthly[[#This Row],[Year]])*1 -> 38808
A219: 2006 | B219: May | D219: 102.35 | E219: 96.12 | F219: 98.47 | G219: 34.07 | H219: 36.12 | I219: 71.311651 | J219: =F219-E219 -> 2.35 | K219: 124.98569 | L219: 195.8 | N219: =(Typical_retail_prices_of_petroleum_products_and_a_crude_oil_price_index_monthly[[#This Row],[Month]]&" "&Typical_retail_prices_of_petroleum_products_and_a_crude_oil_price_index_monthly[[#This Row],[Year]])*1 -> 38838
A220: 2006 | B220: June | D220: 101.37 | E220: 95.3 | F220: 97.66 | G220: 33.75 | H220: 36.17 | I220: 70.767906 | J220: =F220-E220 -> 2.36 | K220: 123.86411 | L220: 194.3 | N220: =(Typical_retail_prices_of_petroleum_products_and_a_crude_oil_price_index_monthly[[#This Row],[Month]]&" "&Typical_retail_prices_of_petroleum_products_and_a_crude_oil_price_index_monthly[[#This Row],[Year]])*1 -> 38869
A221: 2006 | B221: July | D221: 102.53 | E221: 96.78 | F221: 98.68 | G221: 37.4 | H221: 40.82 | I221: 76.364832 | J221: =F221-E221 -> 1.9 | K221: 133.78262 | L221: 209.7 | N221: =(Typical_retail_prices_of_petroleum_products_and_a_crude_oil_price_index_monthly[[#This Row],[Month]]&" "&Typical_retail_prices_of_petroleum_products_and_a_crude_oil_price_index_monthly[[#This Row],[Year]])*1 -> 38899
A222: 2006 | B222: August | D222: 103.01 | E222: 97.67 | F222: 99.38 | G222: 37.36 | H222: 41.11 | I222: 74.181852 | J222: =F222-E222 -> 1.71 | K222: 129.76338 | L222: 203.7 | N222: =(Typical_retail_prices_of_petroleum_products_and_a_crude_oil_price_index_monthly[[#This Row],[Month]]&" "&Typical_retail_prices_of_petroleum_products_and_a_crude_oil_price_index_monthly[[#This Row],[Year]])*1 -> 38930
... A263: 2010 | B263: January | D263: 118.52927 | E263: 111.48884 | F263: 113.311 | G263: 42.490196 | H263: 50.639435 | I263: 91.750477 | J263: =F263-E263 -> 1.8221665 | K263: 160.72709 | L263: 257.45042 | N263: =(Typical_retail_prices_of_petroleum_products_and_a_crude_oil_price_index_monthly[[#This Row],[Month]]&" "&Typical_retail_prices_of_petroleum_products_and_a_crude_oil_price_index_monthly[[#This Row],[Year]])*1 -> 40179
A264: 2010 | B264: February | D264: 118.52849 | E264: 111.64594 | F264: 113.38498 | G264: 43.198321 | H264: 50.045117 | I264: 92.717894 | J264: =F264-E264 -> 1.739037 | K264: 162.24124 | N264: =(Typical_retail_prices_of_petroleum_products_and_a_crude_oil_price_index_monthly[[#This Row],[Month]]&" "&Typical_retail_prices_of_petroleum_products_and_a_crude_oil_price_index_monthly[[#This Row],[Year]])*1 -> 40210
A265: 2010 | B265: March | D265: 121.87084 | E265: 115.46876 | F265: 116.20458 | G265: 45.11764 | H265: 52.501819 | I265: 101.82307 | J265: =F265-E265 -> 0.73582304 | K265: 178.22082 | N265: =(Typical_retail_prices_of_petroleum_products_and_a_crude_oil_price_index_monthly[[#This Row],[Month]]&" "&Typical_retail_prices_of_petroleum_products_and_a_crude_oil_price_index_monthly[[#This Row],[Year]])*1 -> 40238
A266: 2010 | B266: April | D266: 126.09781 | E266: 119.80299 | F266: 120.98551 | G266: 46.682493 | H266: 55.155251 | I266: 106.54231 | J266: =F266-E266 -> 1.1825139 | K266: 186.40964 | N266: =(Typical_retail_prices_of_petroleum_products_and_a_crude_oil_price_index_monthly[[#This Row],[Month]]&" "&Typical_retail_prices_of_petroleum_products_and_a_crude_oil_price_index_monthly[[#This Row],[Year]])*1 -> 40269
A267: 2010 | B267: May | D267: 127.08088 | E267: 121.17919 | F267: 122.75372 | G267: 47.413579 | H267: 56.428913 | I267: 99.62629 | J267: =F267-E267 -> 1.5745338 | K267: 174.20931 | N267: =(Typical_retail_prices_of_petroleum_products_and_a_crude_oil_price_index_monthly[[#This Row],[Month]]&" "&Typical_retail_prices_of_petroleum_products_and_a_crude_oil_price_index_monthly[[#This Row],[Year]])*1 -> 40299
A268: 2010 | B268: June | D268: 124.85221 | E268: 117.70088 | F268: 120.11671 | G268: 46.752187 | H268: 55.309938 | I268: 98.161654 | J268: =F268-E268 -> 2.4158349 | K268: 171.75354 | N268: =(Typical_retail_prices_of_petroleum_products_and_a_crude_oil_price_index_monthly[[#This Row],[Month]]&" "&Typical_retail_prices_of_petroleum_products_and_a_crude_oil_price_index_monthly[[#This Row],[Year]])*1 -> 40330
A269: 2010 | B269: July | D269: 124.53616 | E269: 117.22383 | F269: 119.66201 | G269: 44.453818 | H269: 53.323589 | I269: 96.42329 | J269: =F269-E269 -> 2.4381757 | K269: 168.88482 | N269: =(Typical_retail_prices_of_petroleum_products_and_a_crude_oil_price_index_monthly[[#This Row],[Month]]&" "&Typical_retail_prices_of_petroleum_products_and_a_crude_oil_price_index_monthly[[#This Row],[Year]])*1 -> 40360
A270: 2010 | B270: August | D270: 123.1566 | E270: 116.19515 | F270: 118.686 | G270: 44.184439 | H270: 52.888837 | I270: 97.073204 | J270: =F270-E270 -> 2.4908484 | K270: 169.62901 | N270: =(Typical_retail_prices_of_petroleum_products_and_a_crude_oil_price_index_monthly[[#This Row],[Month]]&" "&Typical_retail_prices_of_petroleum_products_and_a_crude_oil_price_index_monthly[[#This Row],[Year]])*1 -> 40391
A271: 2010 | B271: September | D271: 121.87236 | E271: 114.61457 | F271: 117.17971 | G271: 42.926827 | H271: 52.989525 | I271: 97.157281 | J271: =F271-E271 -> 2.5651332 | K271: 169.98388 | N271: =(Typical_retail_prices_of_petroleum_products_and_a_crude_oil_price_index_monthly[[#This Row],[Month]]&" "&Typical_retail_prices_of_petroleum_products_and_a_crude_oil_price_index_monthly[[#This Row],[Year]])*1 -> 40422
A272: 2010 | B272: October | D272: 124.6489 | E272: 117.20211 | F272: 120.58979 | G272: 45.301963 | H272: 54.826932 | I272: 101.56932 | J272: =F272-E272 -> 3.3876872 | K272: 177.70267 | N272: =(Typical_retail_prices_of_petroleum_products_and_a_crude_oil_price_index_monthly[[#This Row],[Month]]&" "&Typical_retail_prices_of_petroleum_products_and_a_crude_oil_price_index_monthly[[#This Row],[Year]])*1 -> 40452
A273: 2010 | B273: November | D273: 125.97259 | E273: 118.70185 | F273: 122.46979 | G273: 46.645437 | H273: 55.786132 | I273: 104.04309 | J273: =F273-E273 -> 3.7679379 | K273: 181.8954 | N273: =(Typical_retail_prices_of_petroleum_products_and_a_crude_oil_price_index_monthly[[#This Row],[Month]]&" "&Typical_retail_prices_of_petroleum_products_and_a_crude_oil_price_index_monthly[[#This Row],[Year]])*1 -> 40483
A274: 2010 | B274: December | D274: 128.85625 | E274: 121.60674 | F274: 125.75973 | G274: 50.24845 | H274: 59.819514 | I274: 113.11212 | J274: =F274-E274 -> 4.1529864 | K274: 197.97122 | N274: =(Typical_retail_prices_of_petroleum_products_and_a_crude_oil_price_index_monthly[[#This Row],[Month]]&" "&Typical_retail_prices_of_petroleum_products_and_a_crude_oil_price_index_monthly[[#This Row],[Year]])*1 -> 40513
A275: 2011 | B275: January | D275: 134.83284 | E275: 127.52572 | F275: 132.07785 | G275: 55.136714 | H275: 61.901548 | I275: 119.78588 | J275: =F275-E275 -> 4.5521381 | K275: 209.88691 | N275: =(Typical_retail_prices_of_petroleum_products_and_a_crude_oil_price_index_monthly[[#This Row],[Month]]&" "&Typical_retail_prices_of_petroleum_products_and_a_crude_oil_price_index_monthly[[#This Row],[Year]])*1 -> 40544
... A311: 2014 | B311: January | D311: 137.77165 | E311: 130.1638 | F311: 138.10669 | G311: 55.668188 | H311: 66.675702 | I311: 129.01003 | J311: =F311-E311 -> 7.942882 | K311: 223.49922 | N311: =(Typical_retail_prices_of_petroleum_products_and_a_crude_oil_price_index_monthly[[#This Row],[Month]]&" "&Typical_retail_prices_of_petroleum_products_and_a_crude_oil_price_index_monthly[[#This Row],[Year]])*1 -> 41640
A312: 2014 | B312: February | D312: 136.33651 | E312: 128.99663 | F312: 136.65356 | G312: 52.867314 | H312: 65.812493 | I312: 128.60719 | J312: =F312-E312 -> 7.656925 | N312: =(Typical_retail_prices_of_petroleum_products_and_a_crude_oil_price_index_monthly[[#This Row],[Month]]&" "&Typical_retail_prices_of_petroleum_products_and_a_crude_oil_price_index_monthly[[#This Row],[Year]])*1 -> 41671
A313: 2014 | B313: March | D313: 136.26155 | E313: 128.61702 | F313: 136.03 | G313: 51.58573 | H313: 65.602233 | I313: 126.3476 | J313: =F313-E313 -> 7.41298 | N313: =(Typical_retail_prices_of_petroleum_products_and_a_crude_oil_price_index_monthly[[#This Row],[Month]]&" "&Typical_retail_prices_of_petroleum_products_and_a_crude_oil_price_index_monthly[[#This Row],[Year]])*1 -> 41699
A314: 2014 | B314: April | D314: 136.34406 | E314: 128.79406 | F314: 135.86774 | G314: 51.357103 | H314: 66.693935 | I314: 125.41925 | J314: =F314-E314 -> 7.073681 | N314: =(Typical_retail_prices_of_petroleum_products_and_a_crude_oil_price_index_monthly[[#This Row],[Month]]&" "&Typical_retail_prices_of_petroleum_products_and_a_crude_oil_price_index_monthly[[#This Row],[Year]])*1 -> 41730
A315: 2014 | B315: May | D315: 137.14782 | E315: 129.31913 | F315: 136.10389 | G315: 50.268751 | H315: 63.744446 | I315: 126.68238 | J315: =F315-E315 -> 6.784756 | N315: =(Typical_retail_prices_of_petroleum_products_and_a_crude_oil_price_index_monthly[[#This Row],[Month]]&" "&Typical_retail_prices_of_petroleum_products_and_a_crude_oil_price_index_monthly[[#This Row],[Year]])*1 -> 41760
A316: 2014 | B316: June | D316: 137.35051 | E316: 129.69879 | F316: 135.4136 | G316: 51.691309 | H316: 63.93364 | I316: 128.34187 | J316: =F316-E316 -> 5.714808 | N316: =(Typical_retail_prices_of_petroleum_products_and_a_crude_oil_price_index_monthly[[#This Row],[Month]]&" "&Typical_retail_prices_of_petroleum_products_and_a_crude_oil_price_index_monthly[[#This Row],[Year]])*1 -> 41791
A317: 2014 | B317: July | D317: 138.66865 | E317: 131.12031 | F317: 136.0077 | G317: 51.334171 | H317: 62.551987 | I317: 123.35639 | J317: =F317-E317 -> 4.8873892 | N317: =(Typical_retail_prices_of_petroleum_products_and_a_crude_oil_price_index_monthly[[#This Row],[Month]]&" "&Typical_retail_prices_of_petroleum_products_and_a_crude_oil_price_index_monthly[[#This Row],[Year]])*1 -> 41821
A318: 2014 | B318: August | D318: 136.84727 | E318: 129.26999 | F318: 133.61398 | G318: 51.147077 | H318: 62.609354 | I318: 119.55031 | J318: =F318-E318 -> 4.3439924 | N318: =(Typical_retail_prices_of_petroleum_products_and_a_crude_oil_price_index_monthly[[#This Row],[Month]]&" "&Typical_retail_prices_of_petroleum_products_and_a_crude_oil_price_index_monthly[[#This Row],[Year]])*1 -> 41852
A319: 2014 | B319: September | D319: 136.12828 | E319: 128.51364 | F319: 133.07132 | G319: 51.023101 | H319: 61.901025 | I319: 116.66264 | J319: =F319-E319 -> 4.5576793 | N319: =(Typical_retail_prices_of_petroleum_products_and_a_crude_oil_price_index_monthly[[#This Row],[Month]]&" "&Typical_retail_prices_of_petroleum_products_and_a_crude_oil_price_index_monthly[[#This Row],[Year]])*1 -> 41883
A320: 2014 | B320: October | D320: 134.23615 | E320: 126.75775 | F320: 131.08198 | G320: 46.725181 | H320: 58.658971 | I320: 107.21554 | J320: =F320-E320 -> 4.3242299 | N320: =(Typical_retail_prices_of_petroleum_products_and_a_crude_oil_price_index_monthly[[#This Row],[Month]]&" "&Typical_retail_prices_of_petroleum_products_and_a_crude_oil_price_index_monthly[[#This Row],[Year]])*1 -> 41913
A321: 2014 | B321: November | D321: 130.02475 | E321: 122.47707 | F321: 127.17998 | G321: 46.322657 | H321: 57.794693 | I321: 99.10816 | J321: =F321-E321 -> 4.7029077 | N321: =(Typical_retail_prices_of_petroleum_products_and_a_crude_oil_price_index_monthly[[#This Row],[Month]]&" "&Typical_retail_prices_of_petroleum_products_and_a_crude_oil_price_index_monthly[[#This Row],[Year]])*1 -> 41944
A322: 2014 | B322: December | D322: 123.70763 | E322: 116.22204 | F322: 122.36556 | G322: 41.7492 | H322: 51.403922 | I322: 81.181465 | J322: =F322-E322 -> 6.1435207 | N322: =(Typical_retail_prices_of_petroleum_products_and_a_crude_oil_price_index_monthly[[#This Row],[Month]]&" "&Typical_retail_prices_of_petroleum_products_and_a_crude_oil_price_index_monthly[[#This Row],[Year]])*1 -> 41974
...

Sheet 4.1.1 (Quarterly)
A1: Table 4.1.1 Typical retail prices of petroleum products and a crude oil price index (quarterly)
A2: Note 1. These estimates are generally representative of prices paid on or about the 15th of the month. Estimates are based on information provided by oil marketing companies until December 1994. From January 1995, data from super/hypermarket chains have been included. The very latest data for motor spirit and diesel are provisional, based on a smaller sample than used for preceding months.
A3: Note 2. Data for Premium Unleaded and Diesel are sourced from a larger sample than the Weekly Prices statistics. As such they will be slightly different than the weekly published figures.
A4: Note 3. These estimates are for deliveries of 2,000 to 5,000 litres; such deliveries attracted 8 per cent VAT from 1 April 1994. With effect from 1 September 1997 the rate of VAT was reduced to 5 per cent.
A5: Note 4. Price index for supplies received by refineries in the UK from both indigenous and imported sources. It represents the average for the month calculated in sterling on a cif basis.
A6: Blank cells in this table represent quarters where data were not reported or avaliable
A7: An r indicates revised data. An r in the date column indicates all data in the row has been revised. An r in a cell indicates that just that cell has been revised.
A8: Freeze panes are turned on. To turn off freeze panes select the 'View' ribbon then 'Freeze Panes' then 'Unfreeze Panes' or use [Alt,W,F]
A9: Source: Department for Energy Security and Net Zero
A10: Year | B10: Quarter | C10: Motor spirit: 4 star / LRP (Pence per litre [Note 1] | D10: Motor spirit: Super unleaded (Pence per litre) [Note 1] | E10: Motor spirit: Premium unleaded / ULSP (Pence per litre) [Note 1, 2] | F10: Derv: Diesel / ULSD (Pence per litre) [Note 1, 2] | G10: Standard grade burning oil (Pence per litre) [Note 1] | H10: Gas oil (Pence per litre) [Note 1, 3] | I10: Crude oil acquired by refineries 2010 = 100 [Note 4] [r] | J10: ULSP to ULSD Differential (Pence per litre) | K10: Historic Indices: Crude oil acquired by refineries 2005 = 100 | L10: Historic Indices: Crude oil acquired by refineries 2000 = 100 | M10: Historic Indices: Crude oil acquired by refineries 1995 = 100
A11: 1989 | B11: Jan to Mar | C11: =SUM('4.1.1'!C11:C13)/3 -> 38.096667 | E11: =SUM('4.1.1'!E11:E13)/3 -> 36.733333 | F11: =SUM('4.1.1'!F11:F13)/3 -> 34.763333 | G11: =SUM('4.1.1'!G11:G13)/3 -> 11.213333 | H11: =SUM('4.1.1'!H11:H13)/3 -> 10.846667
A12: 1989 | B12: Apr to Jun | C12: =SUM('4.1.1'!C14:C16)/3 -> 42.223333 | E12: =SUM('4.1.1'!E14:E16)/3 -> 40.213333 | F12: =SUM('4.1.1'!F14:F16)/3 -> 36.023333 | G12: =SUM('4.1.1'!G14:G16)/3 -> 11.446667 | H12: =SUM('4.1.1'!H14:H16)/3 -> 10.966667
A13: 1989 | B13: Jul to Sep | C13: =SUM('4.1.1'!C17:C19)/3 -> 40.733333 | E13: =SUM('4.1.1'!E17:E19)/3 -> 38.283333 | F13: =SUM('4.1.1'!F17:F19)/3 -> 35.856667 | G13: =SUM('4.1.1'!G17:G19)/3 -> 11.603333 | H13: =SUM('4.1.1'!H17:H19)/3 -> 11.33
A14: 1989 | B14: Oct to Dec | C14: =SUM('4.1.1'!C20:C22)/3 -> 40.513333 | E14: =SUM('4.1.1'!E20:E22)/3 -> 37.92 | F14: =SUM('4.1.1'!F20:F22)/3 -> 38.083333 | G14: =SUM('4.1.1'!G20:G22)/3 -> 13.876667 | H14: =SUM('4.1.1'!H20:H22)/3 -> 13.406667
A15: 1990 | B15: Jan to Mar | C15: =SUM('4.1.1'!C23:C25)/3 -> 40.89 | E15: =SUM('4.1.1'!E23:E25)/3 -> 38.303333 | F15: =SUM('4.1.1'!F23:F25)/3 -> 38.066667 | G15: =SUM('4.1.1'!G23:G25)/3 -> 14.043333 | H15: =SUM('4.1.1'!H23:H25)/3 -> 13.66
A16: 1990 | B16: Apr to Jun | C16: =SUM('4.1.1'!C26:C28)/3 -> 43.946667 | E16: =SUM('4.1.1'!E26:E28)/3 -> 41.06 | F16: =SUM('4.1.1'!F26:F28)/3 -> 39 | G16: =SUM('4.1.1'!G26:G28)/3 -> 12.166667 | H16: =SUM('4.1.1'!H26:H28)/3 -> 11.933333
A17: 1990 | B17: Jul to Sep | C17: =SUM('4.1.1'!C29:C31)/3 -> 46.906667 | E17: =SUM('4.1.1'!E29:E31)/3 -> 43.976667 | F17: =SUM('4.1.1'!F29:F31)/3 -> 40.17 | G17: =SUM('4.1.1'!G29:G31)/3 -> 15.29 | H17: =SUM('4.1.1'!H29:H31)/3 -> 14.59
A18: 1990 | B18: Oct to Dec | C18: =SUM('4.1.1'!C32:C34)/3 -> 47.753333 | E18: =SUM('4.1.1'!E32:E34)/3 -> 44.786667 | F18: =SUM('4.1.1'!F32:F34)/3 -> 44.69 | G18: =SUM('4.1.1'!G32:G34)/3 -> 20.74 | H18: =SUM('4.1.1'!H32:H34)/3 -> 18.373333
A19: 1991 | B19: Jan to Mar | C19: =SUM('4.1.1'!C35:C37)/3 -> 44.496667 | D19: =SUM('4.1.1'!D35:D37)/3 -> 43.696667 | E19: =SUM('4.1.1'!E35:E37)/3 -> 41.47 | F19: =SUM('4.1.1'!F35:F37)/3 -> 42.27 | G19: =SUM('4.1.1'!G35:G37)/3 -> 15.913333 | H19: =SUM('4.1.1'!H35:H37)/3 -> 15.306667 | J19: =F19-E19 -> 0.8 | M19: 104.73667
A20: 1991 | B20: Apr to Jun | C20: =SUM('4.1.1'!C38:C40)/3 -> 49.743333 | D20: =SUM('4.1.1'!D38:D40)/3 -> 48.406667 | E20: =SUM('4.1.1'!E38:E40)/3 -> 46.193333 | F20: =SUM('4.1.1'!F38:F40)/3 -> 43.563333 | G20: =SUM('4.1.1'!G38:G40)/3 -> 13.006667 | H20: =SUM('4.1.1'!H38:H40)/3 -> 12.706667 | J20: =F20-E20 -> -2.63 | M20: 101.00333
A21: 1991 | B21: Jul to Sep | C21: =SUM('4.1.1'!C41:C43)/3 -> 50.33 | D21: =SUM('4.1.1'!D41:D43)/3 -> 49.033333 | E21: =SUM('4.1.1'!E41:E43)/3 -> 46.79 | F21: =SUM('4.1.1'!F41:F43)/3 -> 44.223333 | G21: =SUM('4.1.1'!G41:G43)/3 -> 13.546667 | H21: =SUM('4.1.1'!H41:H43)/3 -> 12.896667 | J21: =F21-E21 -> -2.5666667 | M21: 106.75667
A22: 1991 | B22: Oct to Dec | C22: =SUM('4.1.1'!C44:C46)/3 -> 49.356667 | D22: =SUM('4.1.1'!D44:D46)/3 -> 48.086667 | E22: =SUM('4.1.1'!E44:E46)/3 -> 45.84 | F22: =SUM('4.1.1'!F44:F46)/3 -> 45.216667 | G22: =SUM('4.1.1'!G44:G46)/3 -> 13.98 | H22: =SUM('4.1.1'!H44:H46)/3 -> 13.69 | J22: =F22-E22 -> -0.62333333 | M22: 109.24667
A23: 1992 | B23: Jan to Mar | C23: =SUM('4.1.1'!C47:C49)/3 -> 48.353333 | D23: =SUM('4.1.1'!D47:D49)/3 -> 46.76 | E23: =SUM('4.1.1'!E47:E49)/3 -> 44.56 | F23: =SUM('4.1.1'!F47:F49)/3 -> 43.753333 | G23: =SUM('4.1.1'!G47:G49)/3 -> 13.25 | H23: =SUM('4.1.1'!H47:H49)/3 -> 12.103333 | J23: =F23-E23 -> -0.80666667 | M23: 91.366667
A24: 1992 | B24: Apr to Jun | C24: =SUM('4.1.1'!C50:C52)/3 -> 51.353333 | D24: =SUM('4.1.1'!D50:D52)/3 -> 49.226667 | E24: =SUM('4.1.1'!E50:E52)/3 -> 46.866667 | F24: =SUM('4.1.1'!F50:F52)/3 -> 45.07 | G24: =SUM('4.1.1'!G50:G52)/3 -> 12.64 | H24: =SUM('4.1.1'!H50:H52)/3 -> 12.276667 | J24: =F24-E24 -> -1.7966667 | M24: 101.57333
A25: 1992 | B25: Jul to Sep | C25: =SUM('4.1.1'!C53:C55)/3 -> 49.976667 | D25: =SUM('4.1.1'!D53:D55)/3 -> 47.863333 | E25: =SUM('4.1.1'!E53:E55)/3 -> 45.65 | F25: =SUM('4.1.1'!F53:F55)/3 -> 44.573333 | G25: =SUM('4.1.1'!G53:G55)/3 -> 12.296667 | H25: =SUM('4.1.1'!H53:H55)/3 -> 11.936667 | J25: =F25-E25 -> -1.0766667 | M25: 98.79
A26: 1992 | B26: Oct to Dec | C26: =SUM('4.1.1'!C56:C58)/3 -> 51.436667 | D26: =SUM('4.1.1'!D56:D58)/3 -> 49.653333 | E26: =SUM('4.1.1'!E56:E58)/3 -> 47.206667 | F26: =SUM('4.1.1'!F56:F58)/3 -> 46.646667 | G26: =SUM('4.1.1'!G56:G58)/3 -> 14.033333 | H26: =SUM('4.1.1'!H56:H58)/3 -> 13.653333 | J26: =F26-E26 -> -0.56 | M26: 106.32667
A27: 1993 | B27: Jan to Mar | C27: =SUM('4.1.1'!C59:C61)/3 -> 51.983333 | D27: =SUM('4.1.1'!D59:D61)/3 -> 50.626667 | E27: =SUM('4.1.1'!E59:E61)/3 -> 47.746667 | F27: =SUM('4.1.1'!F59:F61)/3 -> 47.74 | G27: =SUM('4.1.1'!G59:G61)/3 -> 14.346667 | H27: =SUM('4.1.1'!H59:H61)/3 -> 13.79 | J27: =F27-E27 -> -0.0066666667 | M27: 111.32333
A28: 1993 | B28: Apr to Jun | C28: =SUM('4.1.1'!C62:C64)/3 -> 55.173333 | D28: =SUM('4.1.1'!D62:D64)/3 -> 53.856667 | E28: =SUM('4.1.1'!E62:E64)/3 -> 50.316667 | F28: =SUM('4.1.1'!F62:F64)/3 -> 49.45 | G28: =SUM('4.1.1'!G62:G64)/3 -> 13.71 | H28: =SUM('4.1.1'!H62:H64)/3 -> 13.776667 | J28: =F28-E28 -> -0.86666667 | M28: 108.51667
A29: 1993 | B29: Jul to Sep | C29: =SUM('4.1.1'!C65:C67)/3 -> 54.653333 | D29: =SUM('4.1.1'!D65:D67)/3 -> 53.513333 | E29: =SUM('4.1.1'!E65:E67)/3 -> 49.89 | F29: =SUM('4.1.1'!F65:F67)/3 -> 49.296667 | G29: =SUM('4.1.1'!G65:G67)/3 -> 12.936667 | H29: =SUM('4.1.1'!H65:H67)/3 -> 12.753333 | J29: =F29-E29 -> -0.59333333 | M29: 98.65
A30: 1993 | B30: Oct to Dec | C30: =SUM('4.1.1'!C68:C70)/3 -> 54.673333 | D30: =SUM('4.1.1'!D68:D70)/3 -> 53.626667 | E30: =SUM('4.1.1'!E68:E70)/3 -> 49.82 | F30: =SUM('4.1.1'!F68:F70)/3 -> 50.293333 | G30: =SUM('4.1.1'!G68:G70)/3 -> 13.556667 | H30: =SUM('4.1.1'!H68:H70)/3 -> 13.356667 | J30: =F30-E30 -> 0.47333333 | M30: 96.03
A31: 1994 | B31: Jan to Mar | C31: =SUM('4.1.1'!C71:C73)/3 -> 55.713333 | D31: =SUM('4.1.1'!D71:D73)/3 -> 54.47 | E31: =SUM('4.1.1'!E71:E73)/3 -> 50.566667 | F31: =SUM('4.1.1'!F71:F73)/3 -> 51.123333 | G31: =SUM('4.1.1'!G71:G73)/3 -> 12.813333 | H31: =SUM('4.1.1'!H71:H73)/3 -> 12.58 | J31: =F31-E31 -> 0.55666667 | M31: 89.693333
A32: 1994 | B32: Apr to Jun | C32: =SUM('4.1.1'!C74:C76)/3 -> 56.766667 | D32: =SUM('4.1.1'!D74:D76)/3 -> 55.71 | E32: =SUM('4.1.1'!E74:E76)/3 -> 51.456667 | F32: =SUM('4.1.1'!F74:F76)/3 -> 51.476667 | G32: =SUM('4.1.1'!G74:G76)/3 -> 13.483333 | H32: =SUM('4.1.1'!H74:H76)/3 -> 13.55 | J32: =F32-E32 -> 0.02 | M32: 95.243333
A33: 1994 | B33: Jul to Sep | C33: =SUM('4.1.1'!C77:C79)/3 -> 57.656667 | D33: =SUM('4.1.1'!D77:D79)/3 -> 57.053333 | E33: =SUM('4.1.1'!E77:E79)/3 -> 52.346667 | F33: =SUM('4.1.1'!F77:F79)/3 -> 51.786667 | G33: =SUM('4.1.1'!G77:G79)/3 -> 13.483333 | H33: =SUM('4.1.1'!H77:H79)/3 -> 13.236667 | J33: =F33-E33 -> -0.56 | M33: 98.996667
A34: 1994 | B34: Oct to Dec | C34: =SUM('4.1.1'!C80:C82)/3 -> 57.36 | D34: =SUM('4.1.1'!D80:D82)/3 -> 56.683333 | E34: =SUM('4.1.1'!E80:E82)/3 -> 51.94 | F34: =SUM('4.1.1'!F80:F82)/3 -> 51.736667 | G34: =SUM('4.1.1'!G80:G82)/3 -> 13.68 | H34: =SUM('4.1.1'!H80:H82)/3 -> 13.693333 | J34: =F34-E34 -> -0.20333333 | M34: 96.44
A35: 1995 | B35: Jan to Mar | C35: =SUM('4.1.1'!C83:C85)/3 -> 58.896667 | D35: =SUM('4.1.1'!D83:D85)/3 -> 57.76 | E35: =SUM('4.1.1'!E83:E85)/3 -> 53.153333 | F35: =SUM('4.1.1'!F83:F85)/3 -> 53.846667 | G35: =SUM('4.1.1'!G83:G85)/3 -> 13.54 | H35: =SUM('4.1.1'!H83:H85)/3 -> 13.833333 | J35: =F35-E35 -> 0.69333333 | M35: 98.423333
A36: 1995 | B36: Apr to Jun | C36: =SUM('4.1.1'!C86:C88)/3 -> 60.293333 | D36: =SUM('4.1.1'!D86:D88)/3 -> 59.083333 | E36: =SUM('4.1.1'!E86:E88)/3 -> 54.416667 | F36: =SUM('4.1.1'!F86:F88)/3 -> 54.776667 | G36: =SUM('4.1.1'!G86:G88)/3 -> 13.656667 | H36: =SUM('4.1.1'!H86:H88)/3 -> 13.9 | J36: =F36-E36 -> 0.36 | M36: 104.85
A37: 1995 | B37: Jul to Sep | C37: =SUM('4.1.1'!C89:C91)/3 -> 59.983333 | D37: =SUM('4.1.1'!D89:D91)/3 -> 58.88 | E37: =SUM('4.1.1'!E89:E91)/3 -> 54.023333 | F37: =SUM('4.1.1'!F89:F91)/3 -> 54.196667 | G37: =SUM('4.1.1'!G89:G91)/3 -> 13.826667 | H37: =SUM('4.1.1'!H89:H91)/3 -> 13.6 | J37: =F37-E37 -> 0.17333333 | M37: 95.85
A38: 1995 | B38: Oct to Dec | C38: =SUM('4.1.1'!C92:C94)/3 -> 59.62 | D38: =SUM('4.1.1'!D92:D94)/3 -> 58.486667 | E38: =SUM('4.1.1'!E92:E94)/3 -> 53.483333 | F38: =SUM('4.1.1'!F92:F94)/3 -> 54.143333 | G38: =SUM('4.1.1'!G92:G94)/3 -> 14.176667 | H38: =SUM('4.1.1'!H92:H94)/3 -> 14.15 | J38: =F38-E38 -> 0.66 | M38: 100.87667
A39: 1996 | B39: Jan to Mar | C39: =SUM('4.1.1'!C95:C97)/3 -> 60.323333 | D39: =SUM('4.1.1'!D95:D97)/3 -> 59.866667 | E39: =SUM('4.1.1'!E95:E97)/3 -> 54.86 | F39: =SUM('4.1.1'!F95:F97)/3 -> 56.16 | G39: =SUM('4.1.1'!G95:G97)/3 -> 15.496667 | H39: =SUM('4.1.1'!H95:H97)/3 -> 15.933333 | J39: =F39-E39 -> 1.3 | M39: 113.34
A40: 1996 | B40: Apr to Jun | C40: =SUM('4.1.1'!C98:C100)/3 -> 60.09 | D40: =SUM('4.1.1'!D98:D100)/3 -> 62 | E40: =SUM('4.1.1'!E98:E100)/3 -> 55.013333 | F40: =SUM('4.1.1'!F98:F100)/3 -> 56.083333 | G40: =SUM('4.1.1'!G98:G100)/3 -> 15.426667 | H40: =SUM('4.1.1'!H98:H100)/3 -> 15.96 | J40: =F40-E40 -> 1.07 | M40: 120.54667
A41: 1996 | B41: Jul to Sep | C41: =SUM('4.1.1'!C101:C103)/3 -> 61.346667 | D41: =SUM('4.1.1'!D101:D103)/3 -> 64.93 | E41: =SUM('4.1.1'!E101:E103)/3 -> 56.45 | F41: =SUM('4.1.1'!F101:F103)/3 -> 57.21 | G41: =SUM('4.1.1'!G101:G103)/3 -> 15.536667 | H41: =SUM('4.1.1'!H101:H103)/3 -> 16.153333 | J41: =F41-E41 -> 0.76 | M41: 123.28
A42: 1996 | B42: Oct to Dec | C42: =SUM('4.1.1'!C104:C106)/3 -> 64.766667 | D42: =SUM('4.1.1'!D104:D106)/3 -> 67.9 | E42: =SUM('4.1.1'!E104:E106)/3 -> 59.76 | F42: =SUM('4.1.1'!F104:F106)/3 -> 61.37 | G42: =SUM('4.1.1'!G104:G106)/3 -> 17.266667 | H42: =SUM('4.1.1'!H104:H106)/3 -> 18.07 | J42: =F42-E42 -> 1.61 | M42: 132.66333
A43: 1997 | B43: Jan to Mar | C43: =SUM('4.1.1'!C107:C109)/3 -> 65.046667 | D43: =SUM('4.1.1'!D107:D109)/3 -> 68.786667 | E43: =SUM('4.1.1'!E107:E109)/3 -> 60.073333 | F43: =SUM('4.1.1'!F107:F109)/3 -> 61.243333 | G43: =SUM('4.1.1'!G107:G109)/3 -> 15.903333 | H43: =SUM('4.1.1'!H107:H109)/3 -> 16.85 | J43: =F43-E43 -> 1.17 | M43: 121.55333
A44: 1997 | B44: Apr to Jun | C44: =SUM('4.1.1'!C110:C112)/3 -> 64.963333 | D44: =SUM('4.1.1'!D110:D112)/3 -> 69 | E44: =SUM('4.1.1'!E110:E112)/3 -> 59.503333 | F44: =SUM('4.1.1'!F110:F112)/3 -> 60.373333 | G44: =SUM('4.1.1'!G110:G112)/3 -> 13.973333 | H44: =SUM('4.1.1'!H110:H112)/3 -> 15.166667 | J44: =F44-E44 -> 0.87 | M44: 101.47333
A45: 1997 | B45: Jul to Sep | C45: =SUM('4.1.1'!C113:C115)/3 -> 69.33 | D45: =SUM('4.1.1'!D113:D115)/3 -> 73.496667 | E45: =SUM('4.1.1'!E113:E115)/3 -> 63.826667 | F45: =SUM('4.1.1'!F113:F115)/3 -> 64.226667 | G45: =SUM('4.1.1'!G113:G115)/3 -> 13.53 | H45: =SUM('4.1.1'!H113:H115)/3 -> 14.833333 | J45: =F45-E45 -> 0.4 | M45: 104.44
A46: 1997 | B46: Oct to Dec | C46: =SUM('4.1.1'!C116:C118)/3 -> 69.53 | D46: =SUM('4.1.1'!D116:D118)/3 -> 73.943333 | E46: =SUM('4.1.1'!E116:E118)/3 -> 63.876667 | F46: =SUM('4.1.1'!F116:F118)/3 -> 64.043333 | G46: =SUM('4.1.1'!G116:G118)/3 -> 14.016667 | H46: =SUM('4.1.1'!H116:H118)/3 -> 14.953333 | I46: =SUM('4.1.1'!I116:I118)/3 -> 21.893322 | J46: =F46-E46 -> 0.16666667 | K46: 38.36221 | L46: 60.158352 | M46: 103.98333
A47: 1998 | B47: Jan to Mar | C47: =SUM('4.1.1'!C119:C121)/3 -> 68.623333 | D47: =SUM('4.1.1'!D119:D121)/3 -> 73.84 | E47: =SUM('4.1.1'!E119:E121)/3 -> 62.616667 | F47: =SUM('4.1.1'!F119:F121)/3 -> 62.826667 | G47: =SUM('4.1.1'!G119:G121)/3 -> 12.353333 | H47: =SUM('4.1.1'!H119:H121)/3 -> 13.356667 | I47: =SUM('4.1.1'!I119:I121)/3 -> 16.696029 | J47: =F47-E47 -> 0.21 | K47: 29.288976 | L47: 45.930005 | M47: 79.513333
A48: 1998 | B48: Apr to Jun | C48: =SUM('4.1.1'!C122:C124)/3 -> 72.333333 | D48: =SUM('4.1.1'!D122:D124)/3 -> 78.866667 | E48: =SUM('4.1.1'!E122:E124)/3 -> 65.703333 | F48: =SUM('4.1.1'!F122:F124)/3 -> 66.703333 | G48: =SUM('4.1.1'!G122:G124)/3 -> 11.486667 | H48: =SUM('4.1.1'!H122:H124)/3 -> 12.743333 | I48: =SUM('4.1.1'!I122:I124)/3 -> 15.398539 | J48: =F48-E48 -> 1 | K48: 27.006298 | L48: 42.350385 | M48: 73.193333
A49: 1998 | B49: Jul to Sep | C49: =SUM('4.1.1'!C125:C127)/3 -> 72.283333 | D49: =SUM('4.1.1'!D125:D127)/3 -> 79.356667 | E49: =SUM('4.1.1'!E125:E127)/3 -> 65.993333 | F49: =SUM('4.1.1'!F125:F127)/3 -> 66.773333 | G49: =SUM('4.1.1'!G125:G127)/3 -> 10.536667 | H49: =SUM('4.1.1'!H125:H127)/3 -> 11.936667 | I49: =SUM('4.1.1'!I125:I127)/3 -> 14.277576 | J49: =F49-E49 -> 0.78 | K49: 25.027655 | L49: 39.247543 | M49: 67.793333
A50: 1998 | B50: Oct to Dec | C50: =SUM('4.1.1'!C128:C130)/3 -> 71.186667 | D50: =SUM('4.1.1'!D128:D130)/3 -> 79.123333 | E50: =SUM('4.1.1'!E128:E130)/3 -> 64.87 | F50: =SUM('4.1.1'!F128:F130)/3 -> 65.71 | G50: =SUM('4.1.1'!G128:G130)/3 -> 10.613333 | H50: =SUM('4.1.1'!H128:H130)/3 -> 11.836667 | I50: =SUM('4.1.1'!I128:I130)/3 -> 12.819356 | J50: =F50-E50 -> 0.84 | K50: 22.544777 | L50: 35.353976 | M50: 61.433333
A51: 1999 | B51: Jan to Mar | C51: =SUM('4.1.1'!C131:C133)/3 -> 71.08 | D51: =SUM('4.1.1'!D131:D133)/3 -> 79.91 | E51: =SUM('4.1.1'!E131:E133)/3 -> 64.133333 | F51: =SUM('4.1.1'!F131:F133)/3 -> 66.02 | G51: =SUM('4.1.1'!G131:G133)/3 -> 10.21 | H51: =SUM('4.1.1'!H131:H133)/3 -> 11.583333 | I51: =SUM('4.1.1'!I131:I133)/3 -> 13.487776 | J51: =F51-E51 -> 1.8866667 | K51: 23.546055 | L51: 36.924146 | M51: 63.473333
A52: 1999 | B52: Apr to Jun | C52: =SUM('4.1.1'!C134:C136)/3 -> 77.586667 | D52: =SUM('4.1.1'!D134:D136)/3 -> 83.65 | E52: =SUM('4.1.1'!E134:E136)/3 -> 70.013333 | F52: =SUM('4.1.1'!F134:F136)/3 -> 73.033333 | G52: =SUM('4.1.1'!G134:G136)/3 -> 11.81 | H52: =SUM('4.1.1'!H134:H136)/3 -> 12.776667 | I52: =SUM('4.1.1'!I134:I136)/3 -> 18.47212 | J52: =F52-E52 -> 3.02 | K52: 32.290754 | L52: 50.637294 | M52: 87.276667
A53: 1999 | B53: Jul to Sep | C53: =SUM('4.1.1'!C137:C139)/3 -> 79.356667 | D53: =SUM('4.1.1'!D137:D139)/3 -> 84.516667 | E53: =SUM('4.1.1'!E137:E139)/3 -> 72.29 | F53: =SUM('4.1.1'!F137:F139)/3 -> 74.66 | G53: =SUM('4.1.1'!G137:G139)/3 -> 13.453333 | H53: =SUM('4.1.1'!H137:H139)/3 -> 14.63 | I53: =SUM('4.1.1'!I137:I139)/3 -> 24.496281 | J53: =F53-E53 -> 2.37 | K53: 42.915456 | L53: 67.298601 | M53: 116.29
A54: 1999 | B54: Oct to Dec | C54: =SUM('4.1.1'!C140:C142)/3 -> 80.786667 | D54: =SUM('4.1.1'!D140:D142)/3 -> 83.613333 | E54: =SUM('4.1.1'!E140:E142)/3 -> 74.21 | F54: =SUM('4.1.1'!F140:F142)/3 -> 76.23 | G54: =SUM('4.1.1'!G140:G142)/3 -> 15.443333 | H54: =SUM('4.1.1'!H140:H142)/3 -> 16.58 | I54: =SUM('4.1.1'!I140:I142)/3 -> 28.770147 | J54: =F54-E54 -> 2.02 | K54: 50.312148 | L54: 78.897849 | M54: 136.05667
A55: 2000 | B55: Jan to Mar | C55: =SUM('4.1.1'!C143:C145)/3 -> 81.526667 | D55: =SUM('4.1.1'!D143:D145)/3 -> 84.27 | E55: =SUM('4.1.1'!E143:E145)/3 -> 76.28 | F55: =SUM('4.1.1'!F143:F145)/3 -> 78.416667 | G55: =SUM('4.1.1'!G143:G145)/3 -> 18.13 | H55: =SUM('4.1.1'!H143:H145)/3 -> 18.57 | I55: =SUM('4.1.1'!I143:I145)/3 -> 32.639532 | J55: =F55-E55 -> 2.1366667 | K55: 57.121412 | L55: 89.575914 | M55: 154.68667
A56: 2000 | B56: Apr to Jun | C56: =SUM('4.1.1'!C146:C148)/3 -> 85.61 | D56: =SUM('4.1.1'!D146:D148)/3 -> 87.99 | E56: =SUM('4.1.1'!E146:E148)/3 -> 81.26 | F56: =SUM('4.1.1'!F146:F148)/3 -> 81.516667 | G56: =SUM('4.1.1'!G146:G148)/3 -> 18.363333 | H56: =SUM('4.1.1'!H146:H148)/3 -> 19.256667 | I56: =SUM('4.1.1'!I146:I148)/3 -> 34.008285 | J56: =F56-E56 -> 0.25666667 | K56: 59.469914 | L56: 93.258756 | M56: 161.11333
A57: 2000 | B57: Jul to Sep | C57: =SUM('4.1.1'!C149:C151)/3 -> 86.773333 | D57: =SUM('4.1.1'!D149:D151)/3 -> 88.733333 | E57: =SUM('4.1.1'!E149:E151)/3 -> 81.72 | F57: =SUM('4.1.1'!F149:F151)/3 -> 82.063333 | G57: =SUM('4.1.1'!G149:G151)/3 -> 21.82 | H57: =SUM('4.1.1'!H149:H151)/3 -> 22.993333 | I57: =SUM('4.1.1'!I149:I151)/3 -> 39.26711 | J57: =F57-E57 -> 0.34333333 | K57: 68.655988 | L57: 107.66406 | M57: 185.98333
A58: 2000 | B58: Oct to Dec | C58: =SUM('4.1.1'!C152:C154)/3 -> 85.66 | D58: =SUM('4.1.1'!D152:D154)/3 -> 88.27 | E58: =SUM('4.1.1'!E152:E154)/3 -> 80.446667 | F58: =SUM('4.1.1'!F152:F154)/3 -> 83.376667 | G58: =SUM('4.1.1'!G152:G154)/3 -> 23.976667 | H58: =SUM('4.1.1'!H152:H154)/3 -> 25.223333 | I58: =SUM('4.1.1'!I152:I154)/3 -> 39.89953 | J58: =F58-E58 -> 2.93 | K58: 69.822444 | L58: 109.49325 | M58: 189.17333
A59: 2001 | B59: Jan to Mar | C59: =SUM('4.1.1'!C155:C157)/3 -> 80.653333 | D59: =SUM('4.1.1'!D155:D157)/3 -> 83.8 | E59: =SUM('4.1.1'!E155:E157)/3 -> 76.296667 | F59: =SUM('4.1.1'!F155:F157)/3 -> 80.17 | G59: =SUM('4.1.1'!G155:G157)/3 -> 19.756667 | H59: =SUM('4.1.1'!H155:H157)/3 -> 20.403333 | I59: =SUM('4.1.1'!I155:I157)/3 -> 34.114913 | J59: =F59-E59 -> 3.8733333 | K59: 59.772027 | L59: 93.732521 | M59: 161.87333
A60: 2001 | B60: Quarter 2 | C60: =SUM('4.1.1'!C158:C160)/3 -> 80.22 | D60: =SUM('4.1.1'!D158:D160)/3 -> 83.373333 | E60: =SUM('4.1.1'!E158:E160)/3 -> 77.66 | F60: =SUM('4.1.1'!F158:F160)/3 -> 77.763333 | G60: =SUM('4.1.1'!G158:G160)/3 -> 19.32 | H60: =SUM('4.1.1'!H158:H160)/3 -> 20.066667 | I60: =SUM('4.1.1'!I158:I160)/3 -> 37.001418 | J60: =F60-E60 -> 0.10333333 | K60: 64.72705 | L60: 101.50282 | M60: 175.43333
A61: 2001 | B61: Quarter 3 | C61: =SUM('4.1.1'!C161:C163)/3 -> 80.593333 | D61: =SUM('4.1.1'!D161:D163)/3 -> 83.756667 | E61: =SUM('4.1.1'!E161:E163)/3 -> 77.013333 | F61: =SUM('4.1.1'!F161:F163)/3 -> 77.54 | G61: =SUM('4.1.1'!G161:G163)/3 -> 18.42 | H61: =SUM('4.1.1'!H161:H163)/3 -> 19.663333 | I61: =SUM('4.1.1'!I161:I163)/3 -> 33.887931 | J61: =F61-E61 -> 0.52666667 | K61: 59.191175 | L61: 92.821647 | M61: 160.56667
A62: 2001 | B62: Oct to Dec | C62: =SUM('4.1.1'!C164:C166)/3 -> 77.39 | D62: =SUM('4.1.1'!D164:D166)/3 -> 80.036667 | E62: =SUM('4.1.1'!E164:E166)/3 -> 71.896667 | F62: =SUM('4.1.1'!F164:F166)/3 -> 75.87 | G62: =SUM('4.1.1'!G164:G166)/3 -> 15.013333 | H62: =SUM('4.1.1'!H164:H166)/3 -> 16.326667 | I62: =SUM('4.1.1'!I164:I166)/3 -> 26.163148 | J62: =F62-E62 -> 3.9733333 | K62: 45.720615 | L62: 71.69756 | M62: 123.93333
A63: 2002 | B63: Jan to Mar | C63: =SUM('4.1.1'!C167:C169)/3 -> 75.923333 | D63: =SUM('4.1.1'!D167:D169)/3 -> 78.723333 | E63: =SUM('4.1.1'!E167:E169)/3 -> 70.466667 | F63: =SUM('4.1.1'!F167:F169)/3 -> 74.626667 | G63: =SUM('4.1.1'!G167:G169)/3 -> 14.616667 | H63: =SUM('4.1.1'!H167:H169)/3 -> 14.706667 | I63: =SUM('4.1.1'!I167:I169)/3 -> 27.806822 | J63: =F63-E63 -> 4.16 | K63: 48.730652 | L63: 76.4178 | M63: 131.8
A64: 2002 | B64: Apr to Jun | C64: =SUM('4.1.1'!C170:C172)/3 -> 77.643333 | D64: =SUM('4.1.1'!D170:D172)/3 -> 80.446667 | E64: =SUM('4.1.1'!E170:E172)/3 -> 74.566667 | F64: =SUM('4.1.1'!F170:F172)/3 -> 76.296667 | G64: =SUM('4.1.1'!G170:G172)/3 -> 15.86 | H64: =SUM('4.1.1'!H170:H172)/3 -> 15.83 | I64: =SUM('4.1.1'!I170:I172)/3 -> 32.429236 | J64: =F64-E64 -> 1.73 | K64: 56.780321 | L64: 89.041026 | M64: 153.83333
A65: 2002 | B65: Jul to Sep | C65: =SUM('4.1.1'!C173:C175)/3 -> 77.143333 | D65: =SUM('4.1.1'!D173:D175)/3 -> 80.033333 | E65: =SUM('4.1.1'!E173:E175)/3 -> 73.846667 | F65: =SUM('4.1.1'!F173:F175)/3 -> 75.41 | G65: =SUM('4.1.1'!G173:G175)/3 -> 15.906667 | H65: =SUM('4.1.1'!H173:H175)/3 -> 16.3 | I65: =SUM('4.1.1'!I173:I175)/3 -> 33.47173 | J65: =F65-E65 -> 1.5633333 | K65: 58.594646 | L65: 91.88619 | M65: 158.73333
A66: 2002 | B66: Oct to Dec | C66: =SUM('4.1.1'!C176:C178)/3 -> 77.426667 | D66: =SUM('4.1.1'!D176:D178)/3 -> 79.95 | E66: =SUM('4.1.1'!E176:E178)/3 -> 74.066667 | F66: =SUM('4.1.1'!F176:F178)/3 -> 75.503333 | G66: =SUM('4.1.1'!G176:G178)/3 -> 16.243333 | H66: =SUM('4.1.1'!H176:H178)/3 -> 16.886667 | I66: =SUM('4.1.1'!I176:I178)/3 -> 32.748189 | J66: =F66-E66 -> 1.4366667 | K66: 57.302649 | L66: 89.860123 | M66: 155.2
A67: 2003 | B67: Jan to Mar | C67: =SUM('4.1.1'!C179:C181)/3 -> 79.606667 | D67: =SUM('4.1.1'!D179:D181)/3 -> 81.566667 | E67: =SUM('4.1.1'!E179:E181)/3 -> 76.72 | F67: =SUM('4.1.1'!F179:F181)/3 -> 78.496667 | G67: =SUM('4.1.1'!G179:G181)/3 -> 20.186667 | H67: =SUM('4.1.1'!H179:H181)/3 -> 20.666667 | I67: =SUM('4.1.1'!I179:I181)/3 -> 38.641499 | J67: =F67-E67 -> 1.7766667 | K67: 67.631337 | L67: 105.92463 | M67: 183.26667
A68: 2003 | B68: Apr to Jun | C68: =SUM('4.1.1'!C182:C184)/3 -> 80.273333 | D68: =SUM('4.1.1'!D182:D184)/3 -> 81.566667 | E68: =SUM('4.1.1'!E182:E184)/3 -> 76.143333 | F68: =SUM('4.1.1'!F182:F184)/3 -> 78.57 | G68: =SUM('4.1.1'!G182:G184)/3 -> 15.68 | H68: =SUM('4.1.1'!H182:H184)/3 -> 17.05 | I68: =SUM('4.1.1'!I182:I184)/3 -> 31.162709 | J68: =F68-E68 -> 2.4266667 | K68: 54.503529 | L68: 85.576573 | M68: 147.8
A69: 2003 | B69: Jul to Sep | C69: =SUM('4.1.1'!C185:C187)/3 -> 79.723333 | D69: =SUM('4.1.1'!D185:D187)/3 -> 80.98 | E69: =SUM('4.1.1'!E185:E187)/3 -> 75.433333 | F69: =SUM('4.1.1'!F185:F187)/3 -> 77.146667 | G69: =SUM('4.1.1'!G185:G187)/3 -> 16.81 | H69: =SUM('4.1.1'!H185:H187)/3 -> 18.006667 | I69: =SUM('4.1.1'!I185:I187)/3 -> 33.872742 | J69: =F69-E69 -> 1.7133333 | K69: 59.280597 | L69: 92.923986 | M69: 109.93333
A70: 2003 | B70: Oct to Dec | C70: =SUM('4.1.1'!C188:C190)/3 -> 80.163333 | D70: =SUM('4.1.1'!D188:D190)/3 -> 81.343333 | E70: =SUM('4.1.1'!E188:E190)/3 -> 75.86 | F70: =SUM('4.1.1'!F188:F190)/3 -> 77.463333 | G70: =SUM('4.1.1'!G188:G190)/3 -> 17.606667 | H70: =SUM('4.1.1'!H188:H190)/3 -> 18.603333 | I70: =SUM('4.1.1'!I188:I190)/3 -> 33.367322 | J70: =F70-E70 -> 1.6033333 | K70: 58.404719 | L70: 91.629299
A71: 2004 | B71: Jan to Mar | C71: =SUM('4.1.1'!C191:C193)/3 -> 80.296667 | D71: =SUM('4.1.1'!D191:D193)/3 -> 81.756667 | E71: =SUM('4.1.1'!E191:E193)/3 -> 76.57 | F71: =SUM('4.1.1'!F191:F193)/3 -> 78.15 | G71: =SUM('4.1.1'!G191:G193)/3 -> 18.01 | H71: =SUM('4.1.1'!H191:H193)/3 -> 18.413333 | I71: =SUM('4.1.1'!I191:I193)/3 -> 33.092391 | J71: =F71-E71 -> 1.58 | K71: 57.943952 | L71: 90.866667
A72: 2004 | B72: Apr to Jun | C72: =SUM('4.1.1'!C194:C196)/3 -> 83.526667 | D72: =SUM('4.1.1'!D194:D196)/3 -> 85.276667 | E72: =SUM('4.1.1'!E194:E196)/3 -> 80.176667 | F72: =SUM('4.1.1'!F194:F196)/3 -> 81.463333 | G72: =SUM('4.1.1'!G194:G196)/3 -> 19.733333 | H72: =SUM('4.1.1'!H194:H196)/3 -> 20.316667 | I72: =SUM('4.1.1'!I194:I196)/3 -> 37.50861 | J72: =F72-E72 -> 1.2866667 | K72: 65.649642 | L72: 102.96667
A73: 2004 | B73: Jul to Sep | C73: =SUM('4.1.1'!C197:C199)/3 -> 85.403333 | D73: =SUM('4.1.1'!D197:D199)/3 -> 86.536667 | E73: =SUM('4.1.1'!E197:E199)/3 -> 80.913333 | F73: =SUM('4.1.1'!F197:F199)/3 -> 82.13 | G73: =SUM('4.1.1'!G197:G199)/3 -> 22.37 | H73: =SUM('4.1.1'!H197:H199)/3 -> 22.986667 | I73: =SUM('4.1.1'!I197:I199)/3 -> 43.57582 | J73: =F73-E73 -> 1.2166667 | K73: 76.315329 | L73: 119.66667
A74: 2004 | B74: Oct to Dec | C74: =SUM('4.1.1'!C200:C202)/3 -> 88.446667 | D74: =SUM('4.1.1'!D200:D202)/3 -> 89.43 | E74: =SUM('4.1.1'!E200:E202)/3 -> 83.236667 | F74: =SUM('4.1.1'!F200:F202)/3 -> 85.906667 | G74: =SUM('4.1.1'!G200:G202)/3 -> 24.943333 | H74: =SUM('4.1.1'!H200:H202)/3 -> 26.123333 | I74: =SUM('4.1.1'!I200:I202)/3 -> 44.750715 | J74: =F74-E74 -> 2.67 | K74: 78.379488 | L74: 122.9
A75: 2005 | B75: Jan to Mar | C75: =SUM('4.1.1'!C203:C205)/3 -> 87.553333 | D75: =SUM('4.1.1'!D203:D205)/3 -> 87.616667 | E75: =SUM('4.1.1'!E203:E205)/3 -> 80.126667 | F75: =SUM('4.1.1'!F203:F205)/3 -> 84.84 | G75: =SUM('4.1.1'!G203:G205)/3 -> 23.49 | H75: =SUM('4.1.1'!H203:H205)/3 -> 25.166667 | I75: =SUM('4.1.1'!I203:I205)/3 -> 47.490692 | J75: =F75-E75 -> 4.7133333 | K75: 83.127551 | L75: 130.4
A76: 2005 | B76: Apr to Jun | C76: =SUM('4.1.1'!C206:C208)/3 -> 88.406667 | D76: =SUM('4.1.1'!D206:D208)/3 -> 91.46 | E76: =SUM('4.1.1'!E206:E208)/3 -> 85.126667 | F76: =SUM('4.1.1'!F206:F208)/3 -> 89.353333 | G76: =SUM('4.1.1'!G206:G208)/3 -> 28.03 | H76: =SUM('4.1.1'!H206:H208)/3 -> 28.723333 | I76: =SUM('4.1.1'!I206:I208)/3 -> 52.248788 | J76: =F76-E76 -> 4.2266667 | K76: 91.566733 | L76: 143.46667
A77: 2005 | B77: Jul to Sep | D77: =SUM('4.1.1'!D209:D211)/3 -> 96.96 | E77: =SUM('4.1.1'!E209:E211)/3 -> 91.143333 | F77: =SUM('4.1.1'!F209:F211)/3 -> 94.78 | G77: =SUM('4.1.1'!G209:G211)/3 -> 32.413333 | H77: =SUM('4.1.1'!H209:H211)/3 -> 33.983333 | I77: =SUM('4.1.1'!I209:I211)/3 -> 65.880352 | J77: =F77-E77 -> 3.6366667 | K77: 115.31787 | L77: 180.9
A78: 2005 | B78: Oct to Dec | D78: =SUM('4.1.1'!D212:D214)/3 -> 97.58 | E78: =SUM('4.1.1'!E212:E214)/3 -> 90.583333 | F78: =SUM('4.1.1'!F212:F214)/3 -> 94.466667 | G78: =SUM('4.1.1'!G212:G214)/3 -> 32.193333 | H78: =SUM('4.1.1'!H212:H214)/3 -> 34.243333 | I78: =SUM('4.1.1'!I212:I214)/3 -> 62.834387 | J78: =F78-E78 -> 3.8833333 | K78: 109.98813 | L78: 172.5
A79: 2006 | B79: Jan to Mar | D79: =SUM('4.1.1'!D215:D217)/3 -> 96.046667 | E79: =SUM('4.1.1'!E215:E217)/3 -> 89.243333 | F79: =SUM('4.1.1'!F215:F217)/3 -> 93.493333 | G79: =SUM('4.1.1'!G215:G217)/3 -> 31.953333 | H79: =SUM('4.1.1'!H215:H217)/3 -> 33.823333 | I79: =SUM('4.1.1'!I215:I217)/3 -> 67.259741 | J79: =F79-E79 -> 4.25 | K79: 117.78075 | L79: 184.66667
A80: 2006 | B80: Apr to Jun | D80: =SUM('4.1.1'!D218:D220)/3 -> 101.04667 | E80: =SUM('4.1.1'!E218:E220)/3 -> 95.186667 | F80: =SUM('4.1.1'!F218:F220)/3 -> 97.906667 | G80: =SUM('4.1.1'!G218:G220)/3 -> 33.66 | H80: =SUM('4.1.1'!H218:H220)/3 -> 35.866667 | I80: =SUM('4.1.1'!I218:I220)/3 -> 72.453617 | J80: =F80-E80 -> 2.72 | K80: 126.85932 | L80: 198.93333
A81: 2006 | B81: Jul to Sep | D81: =SUM('4.1.1'!D221:D223)/3 -> 100.78333 | E81: =SUM('4.1.1'!E221:E223)/3 -> 94.6 | F81: =SUM('4.1.1'!F221:F223)/3 -> 97.496667 | G81: =SUM('4.1.1'!G221:G223)/3 -> 36.84 | H81: =SUM('4.1.1'!H221:H223)/3 -> 40.423333 | I81: =SUM('4.1.1'!I221:I223)/3 -> 71.25825 | J81: =F81-E81 -> 2.8966667 | K81: 124.68677 | L81: 195.66667
A82: 2006 | B82: Oct to Dec | D82: =SUM('4.1.1'!D224:D226)/3 -> 94.316667 | E82: =SUM('4.1.1'!E224:E226)/3 -> 86.246667 | F82: =SUM('4.1.1'!F224:F226)/3 -> 91.94 | G82: =SUM('4.1.1'!G224:G226)/3 -> 32.183333 | H82: =SUM('4.1.1'!H224:H226)/3 -> 36.203333 | I82: =SUM('4.1.1'!I224:I226)/3 -> 59.669411 | J82: =F82-E82 -> 5.6933333 | K82: 104.44011 | L82: 163.82598
A83: 2007 | B83: Jan to Mar | D83: =SUM('4.1.1'!D227:D229)/3 -> 94.94 | E83: =SUM('4.1.1'!E227:E229)/3 -> 87.156667 | F83: =SUM('4.1.1'!F227:F229)/3 -> 91.26 | G83: =SUM('4.1.1'!G227:G229)/3 -> 31.053333 | H83: =SUM('4.1.1'!H227:H229)/3 -> 34.756667 | I83: =SUM('4.1.1'!I227:I229)/3 -> 57.057024 | J83: =F83-E83 -> 4.1033333 | K83: 99.94069 | L83: 156.65909
A84: 2007 | B84: Apr to Jun | D84: =SUM('4.1.1'!D230:D232)/3 -> 100.34333 | E84: =SUM('4.1.1'!E230:E232)/3 -> 94.47 | F84: =SUM('4.1.1'!F230:F232)/3 -> 96.053333 | G84: =SUM('4.1.1'!G230:G232)/3 -> 33.786667 | H84: =SUM('4.1.1'!H230:H232)/3 -> 38.36 | I84: =SUM('4.1.1'!I230:I232)/3 -> 66.9043 | J84: =F84-E84 -> 1.5833333 | K84: 117.07986 | L84: 183.68836
A85: 2007 | B85: Jul to Sep | D85: =SUM('4.1.1'!D233:D235)/3 -> 101.34667 | E85: =SUM('4.1.1'!E233:E235)/3 -> 95.4 | F85: =SUM('4.1.1'!F233:F235)/3 -> 96.496667 | G85: =SUM('4.1.1'!G233:G235)/3 -> 34.91 | H85: =SUM('4.1.1'!H233:H235)/3 -> 40 | I85: =SUM('4.1.1'!I233:I235)/3 -> 72.210328 | J85: =F85-E85 -> 1.0966667 | K85: 126.23628 | L85: 198.23333
A86: 2007 | B86: Oct to Dec | D86: =SUM('4.1.1'!D236:D238)/3 -> 104.95667 | E86: =SUM('4.1.1'!E236:E238)/3 -> 99.95 | F86: =SUM('4.1.1'!F236:F238)/3 -> 103.58333 | G86: =SUM('4.1.1'!G236:G238)/3 -> 40.383333 | H86: =SUM('4.1.1'!H236:H238)/3 -> 46.983333 | I86: =SUM('4.1.1'!I236:I238)/3 -> 84.189511 | J86: =F86-E86 -> 3.6333333 | K86: 147.1496 | L86: 231.16667
A87: 2008 | B87: Jan to Mar | D87: =SUM('4.1.1'!D239:D241)/3 -> 111.30667 | E87: =SUM('4.1.1'!E239:E241)/3 -> 104.52333 | F87: =SUM('4.1.1'!F239:F241)/3 -> 110.23333 | G87: =SUM('4.1.1'!G239:G241)/3 -> 45.256667 | H87: =SUM('4.1.1'!H239:H241)/3 -> 52.86 | I87: =SUM('4.1.1'!I239:I241)/3 -> 94.901923 | J87: =F87-E87 -> 5.71 | K87: 166.0632 | L87: 260.2
A88: 2008 | B88: Apr to Jun | D88: =SUM('4.1.1'!D242:D244)/3 -> 118.29667 | E88: =SUM('4.1.1'!E242:E244)/3 -> 112.58 | F88: =SUM('4.1.1'!F242:F244)/3 -> 123.78 | G88: =SUM('4.1.1'!G242:G244)/3 -> 58.423333 | H88: =SUM('4.1.1'!H242:H244)/3 -> 65.346667 | I88: =SUM('4.1.1'!I242:I244)/3 -> 119.39314 | J88: =F88-E88 -> 11.2 | K88: 208.85818 | L88: 327.43333
A89: 2008 | B89: Jul to Sep | D89: =SUM('4.1.1'!D245:D247)/3 -> 120.96667 | E89: =SUM('4.1.1'!E245:E247)/3 -> 114.66 | F89: =SUM('4.1.1'!F245:F247)/3 -> 126.95 | G89: =SUM('4.1.1'!G245:G247)/3 -> 57.91 | H89: =SUM('4.1.1'!H245:H247)/3 -> 64.716667 | I89: =SUM('4.1.1'!I245:I247)/3 -> 118.2575 | J89: =F89-E89 -> 12.29 | K89: 206.47337 | L89: 323.05259
A90: 2008 | B90: Oct to Dec | D90: =SUM('4.1.1'!D248:D250)/3 -> 103.30667 | E90: =SUM('4.1.1'!E248:E250)/3 -> 96.54 | F90: =SUM('4.1.1'!F248:F250)/3 -> 109.08 | G90: =SUM('4.1.1'!G248:G250)/3 -> 42.596667 | H90: =SUM('4.1.1'!H248:H250)/3 -> 50.743333 | I90: =SUM('4.1.1'!I248:I250)/3 -> 69.085618 | J90: =F90-E90 -> 12.54 | K90: 120.74025 | L90: 188.59028
A91: 2009 | B91: Jan to Mar | D91: =SUM('4.1.1'!D251:D253)/3 -> 95.37 | E91: =SUM('4.1.1'!E251:E253)/3 -> 88.59 | F91: =SUM('4.1.1'!F251:F253)/3 -> 99.626667 | G91: =SUM('4.1.1'!G251:G253)/3 -> 33.9 | H91: =SUM('4.1.1'!H251:H253)/3 -> 41.77 | I91: =SUM('4.1.1'!I251:I253)/3 -> 59.18269 | J91: =F91-E91 -> 11.036667 | K91: 103.59095 | L91: 162.20458
A92: 2009 | B92: Apr to Jun | D92: =SUM('4.1.1'!D254:D256)/3 -> 103.54 | E92: =SUM('4.1.1'!E254:E256)/3 -> 97.466667 | F92: =SUM('4.1.1'!F254:F256)/3 -> 103.08 | G92: =SUM('4.1.1'!G254:G256)/3 -> 34.603333 | H92: =SUM('4.1.1'!H254:H256)/3 -> 42.283333 | I92: =SUM('4.1.1'!I254:I256)/3 -> 72.565495 | J92: =F92-E92 -> 5.6133333 | K92: 127.0517 | L92: 199.29593
A93: 2009 | B93: Jul to Sep | D93: =SUM('4.1.1'!D257:D259)/3 -> 110.43667 | E93: =SUM('4.1.1'!E257:E259)/3 -> 104.10667 | F93: =SUM('4.1.1'!F257:F259)/3 -> 104.9 | G93: =SUM('4.1.1'!G257:G259)/3 -> 36.816667 | H93: =SUM('4.1.1'!H257:H259)/3 -> 44.33 | I93: =SUM('4.1.1'!I257:I259)/3 -> 81.146495 | J93: =F93-E93 -> 0.79333333 | K93: 141.96232 | L93: 222.42876
A94: 2009 | B94: Quarter 4 | D94: =SUM('4.1.1'!D260:D262)/3 -> 113.49984 | E94: =SUM('4.1.1'!E260:E262)/3 -> 106.99501 | F94: =SUM('4.1.1'!F260:F262)/3 -> 108.11305 | G94: =SUM('4.1.1'!G260:G262)/3 -> 39.260866 | H94: =SUM('4.1.1'!H260:H262)/3 -> 47.598764 | I94: =SUM('4.1.1'!I260:I262)/3 -> 88.699348 | J94: =F94-E94 -> 1.1180379 | K94: 155.18502 | L94: 242.28748
A95: 2010 | B95: Jan to Mar | D95: =SUM('4.1.1'!D263:D265)/3 -> 119.64287 | E95: =SUM('4.1.1'!E263:E265)/3 -> 112.86785 | F95: =SUM('4.1.1'!F263:F265)/3 -> 114.30019 | G95: =SUM('4.1.1'!G263:G265)/3 -> 43.602052 | H95: =SUM('4.1.1'!H263:H265)/3 -> 51.062124 | I95: =SUM('4.1.1'!I263:I265)/3 -> 95.43048 | J95: =F95-E95 -> 1.4323422 | K95: 167.06305
A96: 2010 | B96: Apr to Jun | D96: =SUM('4.1.1'!D266:D268)/3 -> 126.0103 | E96: =SUM('4.1.1'!E266:E268)/3 -> 119.56102 | F96: =SUM('4.1.1'!F266:F268)/3 -> 121.28531 | G96: =SUM('4.1.1'!G266:G268)/3 -> 46.94942 | H96: =SUM('4.1.1'!H266:H268)/3 -> 55.631368 | I96: =SUM('4.1.1'!I266:I268)/3 -> 101.44342 | J96: =F96-E96 -> 1.7242942 | K96: 177.45749
A97: 2010 | B97: Jul to Sep | D97: =SUM('4.1.1'!D269:D271)/3 -> 123.18837 | E97: =SUM('4.1.1'!E269:E271)/3 -> 116.01119 | F97: =SUM('4.1.1'!F269:F271)/3 -> 118.50924 | G97: =SUM('4.1.1'!G269:G271)/3 -> 43.855028 | H97: =SUM('4.1.1'!H269:H271)/3 -> 53.067317 | I97: =SUM('4.1.1'!I269:I271)/3 -> 96.884591 | J97: =F97-E97 -> 2.4980524 | K97: 169.49923
A98: 2010 | B98: Quarter 4 | D98: =SUM('4.1.1'!D272:D274)/3 -> 126.49258 | E98: =SUM('4.1.1'!E272:E274)/3 -> 119.17023 | F98: =SUM('4.1.1'!F272:F274)/3 -> 122.93977 | G98: =SUM('4.1.1'!G272:G274)/3 -> 47.398617 | H98: =SUM('4.1.1'!H272:H274)/3 -> 56.810859 | I98: =SUM('4.1.1'!I272:I274)/3 -> 106.24151 | J98: =F98-E98 -> 3.7695372 | K98: 185.85643
A99: 2011 | B99: Jan to Mar | D99: =SUM('4.1.1'!D275:D277)/3 -> 136.03843 | E99: =SUM('4.1.1'!E275:E277)/3 -> 129.2614 | F99: =SUM('4.1.1'!F275:F277)/3 -> 134.54995 | G99: =SUM('4.1.1'!G275:G277)/3 -> 56.110502 | H99: =SUM('4.1.1'!H275:H277)/3 -> 64.398639 | I99: =SUM('4.1.1'!I275:I277)/3 -> 127.25946 | J99: =F99-E99 -> 5.2885539 | K99: 222.58227
A100: 2011 | B100: Apr to Jun | D100: =SUM('4.1.1'!D278:D280)/3 -> 142.98884 | E100: =SUM('4.1.1'!E278:E280)/3 -> 135.67101 | F100: =SUM('4.1.1'!F278:F280)/3 -> 140.75747 | G100: =SUM('4.1.1'!G278:G280)/3 -> 60.15228 | H100: =SUM('4.1.1'!H278:H280)/3 -> 69.530992 | I100: =SUM('4.1.1'!I278:I280)/3 -> 140.96789 | J100: =F100-E100 -> 5.0864629 | K100: 246.6704
...

Sheet 4.1.2
A1: Table 4.1.2 Typical retail prices of petroleum products and a crude oil price index (annual)
A2: Note 1. Estimates are based on information provided by oil marketing companies until December 1994. From January 1995, data from super/hypermarket chains have been included.
A3: Note 2. From October 1999, Four Star prices represent 'Lead Replacement Petrol' (LRP). Pump prices for both petrols are broadly the same.
A4: Note 3. The LRP series has been discontinued from September 2005 due to the low volume of sales.
A5: Note 4. From April 2001, Premium unleaded prices represent Ultra Low Sulphur Petrol (ULSP), which now accounts for virtually all Premium unleaded sold. The pump prices for both fuels were broadly the same.
A6: Note 5. From July 1999, diesel prices represent average prices for Ultra Low Sulphur Diesel which now accounts for virtually all diesel sold. Prices for the period March - June 1999 represent a mixture of both types of diesel as companies switched to only selling ULSD. Pump prices for both diesels are broadly the same.
A7: Note 6. These estimates are for deliveries of up to 1,000 litres; such deliveries attract 8 per cent VAT from 1 April 1994. With effect from 1 September 1997 the rate of VAT has been reduced to 5 per cent.
A8: Note 7. These estimates are for deliveries of 2,000 to 5,000 litres; such deliveries attract 8 per cent VAT from 1 April 1994. With effect from 1 September 1997 the rate of VAT has been reduced to 5 per cent.
A9: Note 8. Price index for supplies received by refineries in the UK from both indigenous and imported sources. It represents the average for the month calculated in sterling on a cif basis.
A10: Blank cells represent quarters where data was not reported in this table.
A11: Freeze panes are turned on. To turn off freeze panes select the 'View' ribbon then 'Freeze Panes' then 'Unfreeze Panes' or use [Alt,W,F]
A12: Source: Department for Energy Security and Net Zero
A13: Year | B13: Motor spirit: 4 star / LRP (Pence per litre) [Note 1, 2, 3] | C13: Motor spirit: Super unleaded (Pence per litre) [Note 1] | D13: Motor spirit: Premium unleaded / ULSP (Pence per litre) [Note 1, 4] | E13: Derv: Diesel / ULSD (Pence per litre) [Note 1, 5] | F13: Standard grade burning oil (Pence per litre) [Note 1, 6] | G13: Gas oil (Pence per litre) [Note 1, 7] | H13: Crude oil acquired by refineries 2010 = 100 [Note 8] [r] | I13: ULSP to ULSD Differential (Pence per litre) | J13: Historic Indices: Crude oil acquired by refineries 2005 = 100 | K13: Historic Indices: Crude oil acquired by refineries 2000 = 100 | L13: Historic Indices: Crude oil acquired by refineries 1995 = 100
A14: 1977 | B14: 17.64 | C14: .. | D14: .. | E14: 18.21 | F14: 8.4 | G14: 8.37 | H14: ..
A15: 1978 | B15: 16.77 | C15: .. | D15: .. | E15: 18.46 | F15: 8.39 | G15: 8.42 | H15: ..
A16: 1979 | B16: 22.66 | C16: .. | D16: .. | E16: 23.65 | F16: 10.89 | G16: 10.9 | H16: ..
A17: 1980 | B17: 28.32 | C17: .. | D17: .. | E17: 29.67 | F17: 14.78 | G17: 14.77 | H17: ..
A18: 1981 | B18: 34.29 | C18: .. | D18: .. | E18: 34.01 | F18: 18.01 | G18: 17.51 | H18: ..
A19: 1982 | B19: 36.62 | C19: .. | D19: .. | E19: 35.86 | F19: 20.75 | G19: 20.11 | H19: ..
A20: 1983 | B20: 39.28 | C20: .. | D20: .. | E20: 37.3 | F20: 21.19 | G20: 20.71 | H20: ..
A21: 1984 | B21: 40.62 | C21: .. | D21: .. | E21: 38.33 | F21: 19.67 | G21: 20.44 | H21: ..
A22: 1985 | B22: 43.14 | C22: .. | D22: .. | E22: 41.94 | F22: 21.12 | G22: 21.58 | H22: ..
A23: 1986 | B23: 37.35 | C23: .. | D23: .. | E23: 35.6 | F23: 13.95 | G23: 13.77 | H23: ..
A24: 1987 | B24: 37.9 | C24: .. | D24: .. | E24: 34.58 | F24: 12.55 | G24: 13.16 | H24: ..
A25: 1988 | B25: 37.38 | C25: .. | D25: .. | E25: 34 | F25: 10.65 | G25: 10.88 | H25: ..
A26: 1989 | B26: 40.39 | C26: .. | D26: =SUM('4.1.1'!E11:E22)/12 -> 38.2875 | E26: 36.18 | F26: 12.04 | G26: 11.64 | H26: ..
A27: 1990 | B27: =SUM('4.1.1'!C23:C34)/12 -> 44.874167 | C27: .. | D27: =SUM('4.1.1'!E23:E34)/12 -> 42.031667 | E27: =SUM('4.1.1'!F23:F34)/12 -> 40.481667 | F27: =SUM('4.1.1'!G23:G34)/12 -> 15.56 | G27: =SUM('4.1.1'!H23:H34)/12 -> 14.639167 | H27: .. | I27: =E27-D27 -> -1.55
A28: 1991 | B28: =SUM('4.1.1'!C35:C46)/12 -> 48.481667 | C28: =SUM('4.1.1'!D35:D46)/12 -> 47.305833 | D28: =SUM('4.1.1'!E35:E46)/12 -> 45.073333 | E28: =SUM('4.1.1'!F35:F46)/12 -> 43.818333 | F28: =SUM('4.1.1'!G35:G46)/12 -> 14.111667 | G28: =SUM('4.1.1'!H35:H46)/12 -> 13.65 | H28: .. | I28: =E28-D28 -> -1.255 | J28: 38.922892 | K28: 61.037595 | L28: =SUM(chart_data!Q30:Q41)/12 -> 105.43583
A29: 1992 | B29: =SUM('4.1.1'!C47:C58)/12 -> 50.28 | C29: =SUM('4.1.1'!D47:D58)/12 -> 48.375833 | D29: =SUM('4.1.1'!E47:E58)/12 -> 46.070833 | E29: =SUM('4.1.1'!F47:F58)/12 -> 45.010833 | F29: =SUM('4.1.1'!G47:G58)/12 -> 13.055 | G29: =SUM('4.1.1'!H47:H58)/12 -> 12.4925 | H29: .. | I29: =E29-D29 -> -1.06 | J29: 36.736839 | K29: 57.609498 | L29: =SUM(chart_data!Q42:Q53)/12 -> 99.514167
A30: 1993 | B30: =SUM('4.1.1'!C59:C70)/12 -> 54.120833 | C30: =SUM('4.1.1'!D59:D70)/12 -> 52.905833 | D30: =SUM('4.1.1'!E59:E70)/12 -> 49.443333 | E30: =SUM('4.1.1'!F59:F70)/12 -> 49.195 | F30: =SUM('4.1.1'!G59:G70)/12 -> 13.6375 | G30: =SUM('4.1.1'!H59:H70)/12 -> 13.419167 | H30: .. | I30: =E30-D30 -> -0.24833333 | J30: 38.256247 | K30: 59.992185 | L30: =SUM(chart_data!Q54:Q65)/12 -> 103.63
A31: 1994 | B31: =SUM('4.1.1'!C71:C82)/12 -> 56.874167 | C31: =SUM('4.1.1'!D71:D82)/12 -> 55.979167 | D31: =SUM('4.1.1'!E71:E82)/12 -> 51.5775 | E31: =SUM('4.1.1'!F71:F82)/12 -> 51.530833 | F31: =SUM('4.1.1'!G71:G82)/12 -> 13.365 | G31: =SUM('4.1.1'!H71:H82)/12 -> 13.265 | H31: .. | I31: =E31-D31 -> -0.046666667 | J31: 35.104835 | K31: 55.050244 | L31: =SUM(chart_data!Q66:Q77)/12 -> 95.093333
A32: =+chart_data!B78 -> 1995 | B32: =SUM('4.1.1'!C83:C94)/12 -> 59.698333 | C32: =SUM('4.1.1'!D83:D94)/12 -> 58.5525 | D32: =SUM('4.1.1'!E83:E94)/12 -> 53.769167 | E32: =SUM('4.1.1'!F83:F94)/12 -> 54.240833 | F32: =SUM('4.1.1'!G83:G94)/12 -> 13.8 | G32: =SUM('4.1.1'!H83:H94)/12 -> 13.870833 | H32: .. | I32: =E32-D32 -> 0.47166667 | J32: 36.91619 | K32: 57.890751 | L32: =SUM(chart_data!Q78:Q89)/12 -> 100
A33: =+chart_data!B90 -> 1996 | B33: =SUM('4.1.1'!C95:C106)/12 -> 61.631667 | C33: =SUM('4.1.1'!D95:D106)/12 -> 63.674167 | D33: =SUM('4.1.1'!E95:E106)/12 -> 56.520833 | E33: =SUM('4.1.1'!F95:F106)/12 -> 57.705833 | F33: =SUM('4.1.1'!G95:G106)/12 -> 15.931667 | G33: =SUM('4.1.1'!H95:H106)/12 -> 16.529167 | H33: =SUM('4.1.1'!I95:I106)/12 -> 25.877915 | I33: =E33-D33 -> 1.185 | J33: 45.258664 | K33: 70.973144 | L33: =SUM(chart_data!Q90:Q101)/12 -> 122.4575
A34: =+chart_data!B102 -> 1997 | B34: =SUM('4.1.1'!C107:C118)/12 -> 67.2175 | C34: =SUM('4.1.1'!D107:D118)/12 -> 71.306667 | D34: =SUM('4.1.1'!E107:E118)/12 -> 61.82 | E34: =SUM('4.1.1'!F107:F118)/12 -> 62.471667 | F34: =SUM('4.1.1'!G107:G118)/12 -> 14.355833 | G34: =SUM('4.1.1'!H107:H118)/12 -> 15.450833 | H34: =SUM('4.1.1'!I107:I118)/12 -> 22.722815 | I34: =E34-D34 -> 0.65166667 | J34: 39.799141 | K34: 62.411699 | L34: =SUM(chart_data!Q102:Q113)/12 -> 107.8625
A35: =+chart_data!B114 -> 1998 | B35: =SUM('4.1.1'!C119:C130)/12 -> 71.106667 | C35: =SUM('4.1.1'!D119:D130)/12 -> 77.796667 | D35: =SUM('4.1.1'!E119:E130)/12 -> 64.795833 | E35: =SUM('4.1.1'!F119:F130)/12 -> 65.503333 | F35: =SUM('4.1.1'!G119:G130)/12 -> 11.2475 | G35: =SUM('4.1.1'!H119:H130)/12 -> 12.468333 | H35: =SUM('4.1.1'!I119:I130)/12 -> 14.797875 | I35: =E35-D35 -> 0.7075 | J35: 25.966926 | K35: 40.720477 | L35: =SUM(chart_data!Q114:Q125)/12 -> 70.483333
A36: =+chart_data!B126 -> 1999 | B36: =SUM('4.1.1'!C131:C142)/12 -> 77.2025 | C36: =SUM('4.1.1'!D131:D142)/12 -> 82.9225 | D36: =SUM('4.1.1'!E131:E142)/12 -> 70.161667 | E36: =SUM('4.1.1'!F131:F142)/12 -> 72.485833 | F36: =SUM('4.1.1'!G131:G142)/12 -> 12.729167 | G36: =SUM('4.1.1'!H131:H142)/12 -> 13.8925 | H36: =SUM('4.1.1'!I131:I142)/12 -> 21.306581 | I36: =E36-D36 -> 2.3241667 | J36: 37.266103 | K36: 58.439473 | L36: =SUM(chart_data!Q126:Q137)/12 -> 100.77417
A37: 2000 | B37: =SUM('4.1.1'!C143:C154)/12 -> 84.8925 | C37: =SUM('4.1.1'!D143:D154)/12 -> 87.315833 | D37: =SUM('4.1.1'!E143:E154)/12 -> 79.926667 | E37: =SUM('4.1.1'!F143:F154)/12 -> 81.343333 | F37: =SUM('4.1.1'!G143:G154)/12 -> 20.5725 | G37: =SUM('4.1.1'!H143:H154)/12 -> 21.510833 | H37: =SUM('4.1.1'!I143:I154)/12 -> 36.453614 | I37: =E37-D37 -> 1.4166667 | J37: 63.767439 | K37: 99.997994 | L37: =SUM(chart_data!Q138:Q149)/12 -> 172.73917
A38: 2001 | B38: =SUM('4.1.1'!C155:C166)/12 -> 79.714167 | C38: =SUM('4.1.1'!D155:D166)/12 -> 82.741667 | D38: =SUM('4.1.1'!E155:E166)/12 -> 75.716667 | E38: =SUM('4.1.1'!F155:F166)/12 -> 77.835833 | F38: =SUM('4.1.1'!G155:G166)/12 -> 18.1275 | G38: =SUM('4.1.1'!H155:H166)/12 -> 19.115 | H38: =SUM('4.1.1'!I155:I166)/12 -> 32.791852 | I38: =E38-D38 -> 2.1191667 | J38: 57.352717 | K38: 89.938638 | L38: =SUM(chart_data!Q150:Q161)/12 -> 155.45167
A39: 2002 | B39: =SUM('4.1.1'!C167:C178)/12 -> 77.034167 | C39: =SUM('4.1.1'!D167:D178)/12 -> 79.788333 | D39: =SUM('4.1.1'!E167:E178)/12 -> 73.236667 | E39: =SUM('4.1.1'!F167:F178)/12 -> 75.459167 | F39: =SUM('4.1.1'!G167:G178)/12 -> 15.656667 | G39: =SUM('4.1.1'!H167:H178)/12 -> 15.930833 | H39: =SUM('4.1.1'!I167:I178)/12 -> 31.613995 | I39: =E39-D39 -> 2.2225 | J39: 55.352067 | K39: 86.801285 | L39: =SUM(chart_data!Q162:Q173)/12 -> 149.89167
A40: 2003 | B40: =SUM('4.1.1'!C179:C190)/12 -> 79.941667 | C40: =SUM('4.1.1'!D179:D190)/12 -> 81.364167 | D40: =SUM('4.1.1'!E179:E190)/12 -> 76.039167 | E40: =SUM('4.1.1'!F179:F190)/12 -> 77.919167 | F40: =SUM('4.1.1'!G179:G190)/12 -> 17.570833 | G40: =SUM('4.1.1'!H179:H190)/12 -> 18.581667 | H40: =SUM('4.1.1'!I179:I190)/12 -> 34.261068 | I40: =E40-D40 -> 1.88 | J40: 59.955046 | K40: 94.013622
A41: 2004 | B41: =SUM('4.1.1'!C191:C202)/12 -> 84.418333 | C41: =SUM('4.1.1'!D191:D202)/12 -> 85.75 | D41: =SUM('4.1.1'!E191:E202)/12 -> 80.224167 | E41: =SUM('4.1.1'!F191:F202)/12 -> 81.9125 | F41: =SUM('4.1.1'!G191:G202)/12 -> 21.264167 | G41: =SUM('4.1.1'!H191:H202)/12 -> 21.96 | H41: =SUM('4.1.1'!I191:I202)/12 -> 39.731884 | I41: =E41-D41 -> 1.6883333 | J41: 69.572103 | K41: 109.1
A42: 2005 | C42: =SUM('4.1.1'!D203:D214)/12 -> 93.404167 | D42: =SUM('4.1.1'!E203:E214)/12 -> 86.745 | E42: =SUM('4.1.1'!F203:F214)/12 -> 90.86 | F42: =SUM('4.1.1'!G203:G214)/12 -> 29.031667 | G42: =SUM('4.1.1'!H203:H214)/12 -> 30.529167 | H42: =SUM('4.1.1'!I203:I214)/12 -> 57.113555 | I42: =E42-D42 -> 4.115 | J42: 100.00007 | K42: 156.81667
A43: 2006 | C43: =SUM('4.1.1'!D215:D226)/12 -> 98.048333 | D43: =SUM('4.1.1'!E215:E226)/12 -> 91.319167 | E43: =SUM('4.1.1'!F215:F226)/12 -> 95.209167 | F43: =SUM('4.1.1'!G215:G226)/12 -> 33.659167 | G43: =SUM('4.1.1'!H215:H226)/12 -> 36.579167 | H43: =SUM('4.1.1'!I215:I226)/12 -> 67.660255 | I43: =E43-D43 -> 3.89 | J43: 118.44174 | K43: 185.77316
A44: 2007 | C44: =SUM('4.1.1'!D227:D238)/12 -> 100.39667 | D44: =SUM('4.1.1'!E227:E238)/12 -> 94.244167 | E44: =SUM('4.1.1'!F227:F238)/12 -> 96.848333 | F44: =SUM('4.1.1'!G227:G238)/12 -> 35.033333 | G44: =SUM('4.1.1'!H227:H238)/12 -> 40.025 | H44: =SUM('4.1.1'!I227:I238)/12 -> 70.090291 | I44: =E44-D44 -> 2.6041667 | J44: 122.60161 | K44: 192.43686
A45: 2008 | C45: =SUM('4.1.1'!D239:D250)/12 -> 113.46917 | D45: =SUM('4.1.1'!E239:E250)/12 -> 107.07583 | E45: =SUM('4.1.1'!F239:F250)/12 -> 117.51083 | F45: =SUM('4.1.1'!G239:G250)/12 -> 51.046667 | G45: =SUM('4.1.1'!H239:H250)/12 -> 58.416667 | H45: =SUM('4.1.1'!I239:I250)/12 -> 100.40955 | I45: =E45-D45 -> 10.435 | J45: 175.53375 | K45: 274.81905
A46: 2009 | C46: =SUM('4.1.1'!D251:D262)/12 -> 105.71163 | D46: =SUM('4.1.1'!E251:E262)/12 -> 99.289585 | E46: =SUM('4.1.1'!F251:F262)/12 -> 103.92993 | F46: =SUM('4.1.1'!G251:G262)/12 -> 36.145217 | G46: =SUM('4.1.1'!H251:H262)/12 -> 43.995524 | H46: =SUM('4.1.1'!I251:I262)/12 -> 75.398507 | I46: =E46-D46 -> 4.6403428 | J46: 131.9475 | K46: 206.55419
A47: 2010 | C47: =SUM('4.1.1'!D263:D274)/12 -> 123.83353 | D47: =SUM('4.1.1'!E263:E274)/12 -> 116.90257 | E47: =SUM('4.1.1'!F263:F274)/12 -> 119.25863 | F47: =SUM('4.1.1'!G263:G274)/12 -> 45.451279 | G47: =SUM('4.1.1'!H263:H274)/12 -> 54.142917 | H47: =SUM('4.1.1'!I263:I274)/12 -> 100 | I47: =E47-D47 -> 2.3560565 | J47: 174.96905
A48: 2011 | C48: =SUM('4.1.1'!D275:D286)/12 -> 140.57395 | D48: =SUM('4.1.1'!E275:E286)/12 -> 133.26879 | E48: =SUM('4.1.1'!F275:F286)/12 -> 138.71613 | F48: =SUM('4.1.1'!G275:G286)/12 -> 58.177498 | G48: =SUM('4.1.1'!H275:H286)/12 -> 68.104193 | H48: =SUM('4.1.1'!I275:I286)/12 -> 135.7312 | I48: =E48-D48 -> 5.4473369 | J48: 237.51179
A49: 2012 | C49: =SUM('4.1.1'!D287:D298)/12 -> 142.86882 | D49: =SUM('4.1.1'!E287:E298)/12 -> 135.39055 | E49: =SUM('4.1.1'!F287:F298)/12 -> 141.82826 | F49: =SUM('4.1.1'!G287:G298)/12 -> 59.287908 | G49: =SUM('4.1.1'!H287:H298)/12 -> 70.760918 | H49: =SUM('4.1.1'!I287:I298)/12 -> 136.79698 | I49: =E49-D49 -> 6.4377125 | J49: 239.28562
A50: 2013 | C50: =SUM('4.1.1'!D299:D310)/12 -> 141.74901 | D50: =SUM('4.1.1'!E299:E310)/12 -> 134.14528 | E50: =SUM('4.1.1'!F299:F310)/12 -> 140.40519 | F50: =SUM('4.1.1'!G299:G310)/12 -> 57.144056 | G50: =SUM('4.1.1'!H299:H310)/12 -> 69.78322 | H50: =SUM('4.1.1'!I299:I310)/12 -> 135.31978 | I50: =E50-D50 -> 6.2599111 | J50: 236.39468
A51: 2014 | C51: =SUM('4.1.1'!D311:D322)/12 -> 135.06874 | D51: =SUM('4.1.1'!E311:E322)/12 -> 127.49585 | E51: =SUM('4.1.1'!F311:F322)/12 -> 133.458 | F51: =SUM('4.1.1'!G311:G322)/12 -> 50.144982 | G51: =SUM('4.1.1'!H311:H322)/12 -> 62.281867 | H51: =SUM('4.1.1'!I311:I322)/12 -> 117.62357 | I51: =E51-D51 -> 5.9621459
A52: 2015 | C52: =SUM('4.1.1'!D323:D334)/12 -> 118.97426 | D52: =SUM('4.1.1'!E323:E334)/12 -> 111.13076 | E52: =SUM('4.1.1'!F323:F334)/12 -> 114.89846 | F52: =SUM('4.1.1'!G323:G334)/12 -> 34.07159 | G52: =SUM('4.1.1'!H323:H334)/12 -> 45.79804 | H52: =SUM('4.1.1'!I323:I334)/12 -> 67.054799 | I52: =E52-D52 -> 3.7676957
A53: 2016 | C53: =SUM('4.1.1'!D335:D346)/12 -> 117.83008 | D53: =SUM('4.1.1'!E335:E346)/12 -> 108.84564 | E53: =SUM('4.1.1'!F335:F346)/12 -> 110.12863 | F53: =SUM('4.1.1'!G335:G346)/12 -> 30.48125 | G53: =SUM('4.1.1'!H335:H346)/12 -> 42.596509 | H53: =SUM('4.1.1'!I335:I346)/12 -> 63.026327 | I53: =E53-D53 -> 1.28299
A54: 2017 | C54: =SUM('4.1.1'!D347:D358)/12 -> 126.95402 | D54: =SUM('4.1.1'!E347:E358)/12 -> 117.58888 | E54: =SUM('4.1.1'!F347:F358)/12 -> 120.14924 | F54: =SUM('4.1.1'!G347:G358)/12 -> 39.168833 | G54: =SUM('4.1.1'!H347:H358)/12 -> 50.460858 | H54: =SUM('4.1.1'!I347:I358)/12 -> 81.613553 | I54: =E54-D54 -> 2.5603547
A55: 2018 | C55: =SUM('4.1.1'!D359:D370)/12 -> 135.1862 | D55: =SUM('4.1.1'!E359:E370)/12 -> 125.19597 | E55: =SUM('4.1.1'!F359:F370)/12 -> 129.98217 | F55: =SUM('4.1.1'!G359:G370)/12 -> 48.193917 | G55: =SUM('4.1.1'!H359:H370)/12 -> 59.388476 | H55: =SUM('4.1.1'!I359:I370)/12 -> 104.21642 | I55: =E55-D55 -> 4.7861952
A56: 2019 | C56: =SUM('4.1.1'!D371:D382)/12 -> 136.18089 | D56: =SUM('4.1.1'!E371:E382)/12 -> 124.878 | E56: =SUM('4.1.1'!F371:F382)/12 -> 131.47546 | F56: =SUM('4.1.1'!G371:G382)/12 -> 46.926333 | G56: =SUM('4.1.1'!H371:H382)/12 -> 58.848569 | H56: =SUM('4.1.1'!I371:I382)/12 -> 99.023666 | I56: =E56-D56 -> 6.5974644
A57: 2020 | C57: =SUM('4.1.1'!D383:D394)/12 -> 127.27902 | D57: =SUM('4.1.1'!E383:E394)/12 -> 113.94729 | E57: =SUM('4.1.1'!F383:F394)/12 -> 119.13522 | F57: =SUM('4.1.1'!G383:G394)/12 -> 29.588917 | G57: =SUM('4.1.1'!H383:H394)/12 -> 46.099946 | H57: =SUM('4.1.1'!I383:I394)/12 -> 65.066174 | I57: =E57-D57 -> 5.1879305
A58: 2021 | C58: =SUM('4.1.1'!D395:D406)/12 -> 144.86708 | D58: =SUM('4.1.1'!E395:E406)/12 -> 131.26958 | E58: =SUM('4.1.1'!F395:F406)/12 -> 134.93701 | F58: =SUM('4.1.1'!G395:G406)/12 -> 42.774667 | G58: =SUM('4.1.1'!H395:H406)/12 -> 59.904396 | H58: =SUM('4.1.1'!I395:I406)/12 -> 98.988776 | I58: =E58-D58 -> 3.6674284
A59: 2022 | C59: =SUM('4.1.1'!D407:D418)/12 -> 176.38956 | D59: =SUM('4.1.1'!E407:E418)/12 -> 164.73227 | E59: =SUM('4.1.1'!F407:F418)/12 -> 177.65813 | F59: =SUM('4.1.1'!G407:G418)/12 -> 80.498417 | G59: =SUM('4.1.1'!H407:H418)/12 -> 104.39323 | H59: =SUM('4.1.1'!I407:I418)/12 -> 163.18159 | I59: =E59-D59 -> 12.925857
A60: 2023 | C60: =SUM('4.1.1'!D419:D430)/12 -> 160.84343 | D60: =SUM('4.1.1'!E419:E430)/12 -> 147.74633 | E60: =SUM('4.1.1'!F419:F430)/12 -> 158.18871 | F60: =SUM('4.1.1'!G419:G430)/12 -> 65.4035 | G60: =SUM('4.1.1'!H419:H430)/12 -> 83.417171 | H60: =SUM('4.1.1'!I419:I430)/12 -> 131.60797 | I60: =E60-D60 -> 10.442378
A61: 2024 | C61: =SUM('4.1.1'!D431:D442)/12 -> 154.68838 | D61: =SUM('4.1.1'!E431:E442)/12 -> 141.47767 | E61: =SUM('4.1.1'!F431:F442)/12 -> 148.32888 | F61: =SUM('4.1.1'!G431:G442)/12 -> 58.243667 | G61: =SUM('4.1.1'!H431:H442)/12 -> 72.319082 | H61: =SUM('4.1.1'!I431:I442)/12 -> 124.84775 | I61: =E61-D61 -> 6.8512194
A62: 2025 | C62: =SUM('4.1.1'!D443:D454)/12 -> 149.57538 | D62: =SUM('4.1.1'!E443:E454)/12 -> 135.07221 | E62: =SUM('4.1.1'!F443:F454)/12 -> 142.54858 | F62: =SUM('4.1.1'!G443:G454)/12 -> 52.14425 | G62: =SUM('4.1.1'!H443:H454)/12 -> 67.626351 | H62: =SUM('4.1.1'!I443:I454)/12 -> 103.92923 | I62: =E62-D62 -> 7.4763647

Sheet 4.1.2 (excl VAT)
A1: Typical retail prices of petroleum products excluding VAT and duty
A2: Blank cells represent either times when there was no change in VAT or duty or are periods between time aggregations. The aggregation is recorded in the final month of the period. 4 star/LRP time series ended in August 2005, ULSP to ULSD differential started in February 2008.
A3: An r indicates revised data. An r in the date column indicates all data in the row has been revised. An r in a cell indicates that just that cell has been revised.
A4: Freeze panes are turned on. To turn off freeze panes select the 'View' ribbon then 'Freeze Panes' then 'Unfreeze Panes' or use [Alt,W,F]
A5: Source: Department for Energy Security and Net Zero
A6: Year | B6: Month | C6: VAT or duty change note | D6: 4 Star/LRP: Ex VAT (Monthly) (Pence per litre) | E6: 4 Star/LRP: Ex VAT & Duty (Monthly) (Pence per litre) | F6: 4 Star/LRP: Ex VAT & Duty (Quarterly Average) (Pence per litre) | G6: Derv (Diesel / ULSD): Diesel / ULSD Ex VAT (Monthly) (Pence per litre) | H6: Derv (Diesel / ULSD): Ex VAT & Duty (Monthly) (Pence per litre) | I6: Derv (Diesel / ULSD): Ex VAT & Duty (Quarterly Average) (Pence per litre) | J6: ULSP (Premium Unleaded): Ex VAT (Monthly) (Pence per litre) | K6: ULSP (Premium Unleaded): Ex VAT & Duty (Monthly) (Pence per litre) | L6: ULSP (Premium Unleaded): Ex VAT & Duty (Quarterly Average) (Pence per litre) | M6: Standard grade burning oil (kerosene): Ex VAT (Monthly) (Pence per litre) | N6: Standard grade burning oil (kerosene): Ex VAT & Duty (Monthly) (Pence per litre) | O6: Standard grade burning oil (kerosene): Ex VAT & Duty (Quarterly Average) (Pence per litre) | P6: Gas oil: Ex VAT (Monthly) (Pence per litre) | Q6: Gas oil: Ex VAT & Duty (Monthly) (Pence per litre) | R6: Gas oil: Ex VAT & Duty (Quarterly Average) (Pence per litre) | S6: ULSP to ULSD Differential (Pence per litre) | T6: Annual Average Derv: Ex VAT (Pence per litre) | U6: Annual Average Derv: Ex VAT & Duty (Pence per litre) | V6: Annual Average ULSP: Ex VAT (Pence per litre) | W6: Annual Average ULSP: Ex VAT & Duty (Pence per litre)
A7: 1990 | B7: 32874 | D7: 35.58 | E7: 15.14 | G7: 34.1 | H7: 16.81 | J7: 33.37 | K7: 15.65 | M7: ='4.1.1'!G23 -> 15.45 | N7: =M7-0 -> 15.45 | P7: ='4.1.1'!H23 -> 15.46 | Q7: =P7-1.1 -> 14.36
A8: 1990 | B8: 32905 | D8: 35.52 | E8: 15.08 | G8: 32.71 | H8: 15.42 | J8: 33.27 | K8: 15.55 | M8: ='4.1.1'!G24 -> 13.64 | N8: =M8-0 -> 13.64 | P8: ='4.1.1'!H24 -> 12.96 | Q8: =P8-1.1 -> 11.86
A9: 1990 | B9: 32933 | D9: 35.56 | E9: 15.13 | F9: =SUM(E7:E9)/3 -> 15.116667 | G9: 32.5 | H9: 15.21 | I9: =SUM(H7:H9)/3 -> 15.813333 | J9: 33.29 | K9: 15.57 | L9: =SUM(K7:K9)/3 -> 15.59 | M9: ='4.1.1'!G25 -> 13.04 | N9: =M9-0 -> 13.04 | O9: =SUM(N7:N9)/3 -> 14.043333 | P9: ='4.1.1'!H25 -> 12.56 | Q9: =P9-1.1 -> 11.46 | R9: =SUM(Q7:Q9)/3 -> 12.56
A10: 1990 | B10: 32964 | D10: 38.5 | E10: 16.02 | G10: 34.08 | H10: 12.21 | J10: 35.97 | K10: 16.48 | M10: ='4.1.1'!G26 -> 12.47 | N10: =M10-0 -> 12.47 | P10: ='4.1.1'!H26 -> 12.37 | Q10: =P10-1.8 -> 10.57
A11: 1990 | B11: 32994 | D11: 38.12 | E11: 15.64 | G11: 34.5 | H11: 12.63 | J11: 35.63 | K11: 16.15 | M11: ='4.1.1'!G27 -> 12.19 | N11: =M11-0 -> 12.19 | P11: ='4.1.1'!H27 -> 11.92 | Q11: =P11-1.8 -> 10.12
A12: 1990 | B12: 33025 | D12: 38.03 | E12: 15.55 | F12: =SUM(E10:E12)/3 -> 15.736667 | G12: 33.16 | H12: 11.29 | I12: =SUM(H10:H12)/3 -> 12.043333 | J12: 35.5 | K12: 16.01 | L12: =SUM(K10:K12)/3 -> 16.213333 | M12: ='4.1.1'!G28 -> 11.84 | N12: =M12-0 -> 11.84 | O12: =SUM(N10:N12)/3 -> 12.166667 | P12: ='4.1.1'!H28 -> 11.51 | Q12: =P12-1.8 -> 9.71 | R12: =SUM(Q10:Q12)/3 -> 10.133333
A13: 1990 | B13: 33055 | D13: 37.62 | E13: 15.14 | G13: 32.68 | H13: 10.81 | J13: 35.07 | K13: 15.58 | M13: ='4.1.1'!G29 -> 12.17 | N13: =M13-0 -> 12.17 | P13: ='4.1.1'!H29 -> 11.9 | Q13: =P13-1.8 -> 10.1
A14: 1990 | B14: 33086 | D14: 40.71 | E14: 18.23 | G14: 35.01 | H14: 13.14 | J14: 38.17 | K14: 18.67 | M14: ='4.1.1'!G30 -> 15.39 | N14: =M14-0 -> 15.39 | P14: ='4.1.1'!H30 -> 14.93 | Q14: =P14-1.8 -> 13.13
A15: 1990 | B15: 33117 | D15: 44.03 | E15: 21.56 | F15: =SUM(E13:E15)/3 -> 18.31 | G15: 37.1 | H15: 15.23 | I15: =SUM(H13:H15)/3 -> 13.06 | J15: 41.49 | K15: 22 | L15: =SUM(K13:K15)/3 -> 18.75 | M15: ='4.1.1'!G31 -> 18.31 | N15: =M15-0 -> 18.31 | O15: =SUM(N13:N15)/3 -> 15.29 | P15: ='4.1.1'!H31 -> 16.94 | Q15: =P15-1.8 -> 15.14 | R15: =SUM(Q13:Q15)/3 -> 12.79
A16: 1990 | B16: 33147 | D16: 44.74 | E16: 22.26 | G16: 39.87 | H16: 18 | J16: 42.19 | K16: 22.7 | M16: ='4.1.1'!G32 -> 23.91 | N16: =M16-0 -> 23.91 | P16: ='4.1.1'!H32 -> 19.66 | Q16: =P16-1.8 -> 17.86
A17: 1990 | B17: 33178 | D17: 41.33 | E17: 18.85 | G17: 38.71 | H17: 16.84 | J17: 38.74 | K17: 19.25 | M17: ='4.1.1'!G33 -> 20.64 | N17: =M17-0 -> 20.64 | P17: ='4.1.1'!H33 -> 18.11 | Q17: =P17-1.8 -> 16.31
A18: 1990 | B18: 33208 | D18: 38.5 | E18: 16.02 | F18: =SUM(E16:E18)/3 -> 19.043333 | G18: 38 | H18: 16.13 | I18: =SUM(H16:H18)/3 -> 16.99 | J18: 35.9 | K18: 16.41 | L18: =SUM(K16:K18)/3 -> 19.453333 | M18: ='4.1.1'!G34 -> 17.67 | N18: =M18-0 -> 17.67 | O18: =SUM(N16:N18)/3 -> 20.74 | P18: ='4.1.1'!H34 -> 17.35 | Q18: =P18-1.8 -> 15.55 | R18: =SUM(Q16:Q18)/3 -> 16.573333
A19: 1991 | B19: 33239 | D19: 39.24 | E19: 16.76 | G19: 37.66 | H19: 15.79 | J19: 36.64 | K19: 17.15 | M19: ='4.1.1'!G35 -> 17.52 | N19: =M19-0 -> 17.52 | P19: ='4.1.1'!H35 -> 17.13 | Q19: =P19-1.8 -> 15.33
A20: 1991 | B20: 33270 | D20: 37.93 | E20: 15.45 | G20: 37.56 | H20: 15.69 | J20: 35.31 | K20: 15.82 | M20: ='4.1.1'!G36 -> 16.68 | N20: =M20-0 -> 16.68 | P20: ='4.1.1'!H36 -> 15.39 | Q20: =P20-1.8 -> 13.59
A21: 1991 | B21: 33298 | D21: 38.9 | E21: 16.42 | F21: =SUM(E19:E21)/3 -> 16.21 | G21: 35.05 | H21: 13.18 | I21: =SUM(H19:H21)/3 -> 14.886667 | J21: 36.23 | K21: 16.74 | L21: =SUM(K19:K21)/3 -> 16.57 | M21: ='4.1.1'!G37 -> 13.54 | N21: =M21-0 -> 13.54 | O21: =SUM(N19:N21)/3 -> 15.913333 | P21: ='4.1.1'!H37 -> 13.4 | Q21: =P21-1.8 -> 11.6 | R21: =SUM(Q19:Q21)/3 -> 13.506667
A22: 1991 | B22: 33329 | D22: 41.73 | E22: 15.88 | G22: 36.94 | H22: 15.07 | J22: 38.65 | K22: 16.24 | M22: ='4.1.1'!G38 -> 12.49 | N22: =M22-0 -> 12.49 | P22: ='4.1.1'!H38 -> 12.16 | Q22: =P22-1.29 -> 10.87
A23: 1991 | B23: 33359 | D23: 42.69 | E23: 16.84 | G23: 37.14 | H23: 15.27 | J23: 39.69 | K23: 17.28 | M23: ='4.1.1'!G39 -> 13.15 | N23: =M23-0 -> 13.15 | P23: ='4.1.1'!H39 -> 12.91 | Q23: =P23-1.29 -> 11.62
A24: 1991 | B24: 33390 | D24: 42.59 | E24: 16.74 | F24: =SUM(E22:E24)/3 -> 16.486667 | G24: 37.14 | H24: 15.27 | I24: =SUM(H22:H24)/3 -> 15.203333 | J24: 39.6 | K24: 17.19 | L24: =SUM(K22:K24)/3 -> 16.903333 | M24: ='4.1.1'!G40 -> 13.38 | N24: =M24-0 -> 13.38 | O24: =SUM(N22:N24)/3 -> 13.006667 | P24: ='4.1.1'!H40 -> 13.05 | Q24: =P24-1.29 -> 11.76 | R24: =SUM(Q22:Q24)/3 -> 11.416667
A25: 1991 | B25: 33420 | D25: 43.11 | E25: 17.26 | G25: 37.67 | H25: 15.8 | J25: 40.07 | K25: 17.66 | M25: ='4.1.1'!G41 -> 13.67 | N25: =M25-0 -> 13.67 | P25: ='4.1.1'!H41 -> 12.97 | Q25: =P25-1.29 -> 11.68
A26: 1991 | B26: 33451 | D26: 42.75 | E26: 16.9 | G26: 37.59 | H26: 15.72 | J26: 39.75 | K26: 17.34 | M26: ='4.1.1'!G42 -> 13.33 | N26: =M26-0 -> 13.33 | P26: ='4.1.1'!H42 -> 12.71 | Q26: =P26-1.29 -> 11.42
A27: 1991 | B27: 33482 | D27: 42.65 | E27: 16.8 | F27: =SUM(E25:E27)/3 -> 16.986667 | G27: 37.65 | H27: 15.78 | I27: =SUM(H25:H27)/3 -> 15.766667 | J27: 39.64 | K27: 17.23 | L27: =SUM(K25:K27)/3 -> 17.41 | M27: ='4.1.1'!G43 -> 13.64 | N27: =M27-0 -> 13.64 | O27: =SUM(N25:N27)/3 -> 13.546667 | P27: ='4.1.1'!H43 -> 13.01 | Q27: =P27-1.29 -> 11.72 | R27: =SUM(Q25:Q27)/3 -> 11.606667
A28: 1991 | B28: 33512 | D28: 42.54 | E28: 16.69 | G28: 38.38 | H28: 16.51 | J28: 39.56 | K28: 17.15 | M28: ='4.1.1'!G44 -> 14.18 | N28: =M28-0 -> 14.18 | P28: ='4.1.1'!H44 -> 13.66 | Q28: =P28-1.29 -> 12.37
A29: 1991 | B29: 33543 | D29: 42.29 | E29: 16.44 | G29: 39.19 | H29: 17.32 | J29: 39.3 | K29: 16.89 | M29: ='4.1.1'!G45 -> 14.33 | N29: =M29-0 -> 14.33 | P29: ='4.1.1'!H45 -> 14.25 | Q29: =P29-1.29 -> 12.96
A30: 1991 | B30: 33573 | D30: 41.18 | E30: 15.33 | F30: =SUM(E28:E30)/3 -> 16.153333 | G30: 37.87 | H30: 16 | I30: =SUM(H28:H30)/3 -> 16.61 | J30: 38.18 | K30: 15.77 | L30: =SUM(K28:K30)/3 -> 16.603333 | M30: ='4.1.1'!G46 -> 13.43 | N30: =M30-0 -> 13.43 | O30: =SUM(N28:N30)/3 -> 13.98 | P30: ='4.1.1'!H46 -> 13.16 | Q30: =P30-1.29 -> 11.87 | R30: =SUM(Q28:Q30)/3 -> 12.4
A31: 1992 | B31: 33604 | D31: 39.94 | E31: 14.09 | G31: 36.76 | H31: 14.89 | J31: 36.96 | K31: 14.55 | M31: ='4.1.1'!G47 -> 12.47 | N31: =M31-0 -> 12.47 | P31: ='4.1.1'!H47 -> 12.02 | Q31: =P31-1.29 -> 10.73
A32: 1992 | B32: 33635 | D32: 40.65 | E32: 14.8 | G32: 37.18 | H32: 15.31 | J32: 37.64 | K32: 15.23 | M32: ='4.1.1'!G48 -> 12.88 | N32: =M32-0 -> 12.88 | P32: ='4.1.1'!H48 -> 12.31 | Q32: =P32-1.29 -> 11.02
A33: 1992 | B33: 33664 | D33: 42.87 | E33: 15.08 | F33: =SUM(E31:E33)/3 -> 14.656667 | G33: 37.77 | H33: 14.92 | I33: =SUM(H31:H33)/3 -> 15.04 | J33: 39.17 | K33: 15.75 | L33: =SUM(K31:K33)/3 -> 15.176667 | M33: ='4.1.1'!G49 -> 14.4 | N33: =M33-0 -> 14.4 | O33: =SUM(N31:N33)/3 -> 13.25 | P33: ='4.1.1'!H49 -> 11.98 | Q33: =P33-1.35 -> 10.63 | R33: =SUM(Q31:Q33)/3 -> 10.793333
A34: 1992 | B34: 33695 | D34: 43.07 | E34: 15.28 | G34: 37.95 | H34: 15.1 | J34: 39.21 | K34: 15.79 | M34: ='4.1.1'!G50 -> 12.64 | N34: =M34-0 -> 12.64 | P34: ='4.1.1'!H50 -> 12.16 | Q34: =P34-1.35 -> 10.81
A35: 1992 | B35: 33725 | D35: 43.71 | E35: 15.92 | G35: 38.61 | H35: 15.76 | J35: 40.04 | K35: 16.62 | M35: ='4.1.1'!G51 -> 12.62 | N35: =M35-0 -> 12.62 | P35: ='4.1.1'!H51 -> 12.34 | Q35: =P35-1.35 -> 10.99
A36: 1992 | B36: 33756 | D36: 44.33 | E36: 16.54 | F36: =SUM(E34:E36)/3 -> 15.913333 | G36: 38.51 | H36: 15.66 | I36: =SUM(H34:H36)/3 -> 15.506667 | J36: 40.41 | K36: 16.99 | L36: =SUM(K34:K36)/3 -> 16.466667 | M36: ='4.1.1'!G52 -> 12.66 | N36: =M36-0 -> 12.66 | O36: =SUM(N34:N36)/3 -> 12.64 | P36: ='4.1.1'!H52 -> 12.33 | Q36: =P36-1.35 -> 10.98 | R36: =SUM(Q34:Q36)/3 -> 10.926667
A37: 1992 | B37: 33786 | D37: 43.12 | E37: 15.32 | G37: 38.26 | H37: 15.4 | J37: 39.46 | K37: 16.03 | M37: ='4.1.1'!G53 -> 12.41 | N37: =M37-0 -> 12.41 | P37: ='4.1.1'!H53 -> 11.98 | Q37: =P37-1.35 -> 10.63
A38: 1992 | B38: 33817 | D38: 42.33 | E38: 14.54 | G38: 37.87 | H38: 15.02 | J38: 38.67 | K38: 15.25 | M38: ='4.1.1'!G54 -> 12.04 | N38: =M38-0 -> 12.04 | P38: ='4.1.1'!H54 -> 11.6 | Q38: =P38-1.35 -> 10.25
A39: 1992 | B39: 33848 | D39: 42.15 | E39: 14.36 | F39: =SUM(E37:E39)/3 -> 14.74 | G39: 37.68 | H39: 14.83 | I39: =SUM(H37:H39)/3 -> 15.083333 | J39: 38.43 | K39: 15.01 | L39: =SUM(K37:K39)/3 -> 15.43 | M39: ='4.1.1'!G55 -> 12.44 | N39: =M39-0 -> 12.44 | O39: =SUM(N37:N39)/3 -> 12.296667 | P39: ='4.1.1'!H55 -> 12.23 | Q39: =P39-1.35 -> 10.88 | R39: =SUM(Q37:Q39)/3 -> 10.586667
A40: 1992 | B40: 33878 | D40: 43.7 | E40: 15.91 | G40: 39.37 | H40: 16.52 | J40: 40.03 | K40: 16.61 | M40: ='4.1.1'!G56 -> 13.75 | N40: =M40-0 -> 13.75 | P40: ='4.1.1'!H56 -> 13.35 | Q40: =P40-1.35 -> 12
A41: 1992 | B41: 33909 | D41: 44.01 | E41: 16.22 | G41: 40.18 | H41: 17.33 | J41: 40.54 | K41: 17.12 | M41: ='4.1.1'!G57 -> 14.46 | N41: =M41-0 -> 14.46 | P41: ='4.1.1'!H57 -> 14.09 | Q41: =P41-1.35 -> 12.74
A42: 1992 | B42: 33939 | D42: 43.62 | E42: 15.83 | F42: =SUM(E40:E42)/3 -> 15.986667 | G42: 39.55 | H42: 16.7 | I42: =SUM(H40:H42)/3 -> 16.85 | J42: 39.96 | K42: 16.54 | L42: =SUM(K40:K42)/3 -> 16.756667 | M42: ='4.1.1'!G58 -> 13.89 | N42: =M42-0 -> 13.89 | O42: =SUM(N40:N42)/3 -> 14.033333 | P42: ='4.1.1'!H58 -> 13.52 | Q42: =P42-1.35 -> 12.17 | R42: =SUM(Q40:Q42)/3 -> 12.303333
A43: 1993 | B43: 33970 | D43: 43.63 | E43: 15.84 | G43: 40.04 | H43: 17.19 | J43: 40.11 | K43: 16.69 | M43: ='4.1.1'!G59 -> 14.1 | N43: =M43-0 -> 14.1 | P43: ='4.1.1'!H59 -> 13.52 | Q43: =P43-1.35 -> 12.17
A44: 1993 | B44: 34001 | D44: 44.22 | E44: 16.43 | G44: 40.69 | H44: 17.84 | J44: 40.57 | K44: 17.15 | M44: ='4.1.1'!G60 -> 14.41 | N44: =M44-0 -> 14.41 | P44: ='4.1.1'!H60 -> 13.81 | Q44: =P44-1.35 -> 12.46
A45: 1993 | B45: 34029 | D45: 44.87 | E45: 14.29 | F45: =SUM(E43:E45)/3 -> 15.52 | G45: 41.16 | H45: 18.31 | I45: =SUM(H43:H45)/3 -> 17.78 | J45: 41.23 | K45: 17.81 | L45: =SUM(K43:K45)/3 -> 17.216667 | M45: ='4.1.1'!G61 -> 14.53 | N45: =M45-0 -> 14.53 | O45: =SUM(N43:N45)/3 -> 14.346667 | P45: ='4.1.1'!H61 -> 14.04 | Q45: =P45-1.35 -> 12.69 | R45: =SUM(Q43:Q45)/3 -> 12.44
A46: 1993 | B46: 34060 | D46: 46.67 | E46: 16.09 | G46: 41.94 | H46: 16.8 | J46: 42.6 | K46: 16.84 | M46: ='4.1.1'!G62 -> 14.07 | N46: =M46-0 -> 14.07 | P46: ='4.1.1'!H62 -> 14.34 | Q46: =P46-1.49 -> 12.85
A47: 1993 | B47: 34090 | D47: 46.84 | E47: 16.26 | G47: 42.03 | H47: 16.89 | J47: 42.75 | K47: 16.99 | M47: ='4.1.1'!G63 -> 13.73 | N47: =M47-0 -> 13.73 | P47: ='4.1.1'!H63 -> 13.73 | Q47: =P47-1.49 -> 12.24
A48: 1993 | B48: 34121 | D48: 47.35 | E48: 16.77 | F48: =SUM(E46:E48)/3 -> 16.373333 | G48: 42.29 | H48: 17.15 | I48: =SUM(H46:H48)/3 -> 16.946667 | J48: 43.12 | K48: 17.35 | L48: =SUM(K46:K48)/3 -> 17.06 | M48: ='4.1.1'!G64 -> 13.33 | N48: =M48-0 -> 13.33 | O48: =SUM(N46:N48)/3 -> 13.71 | P48: ='4.1.1'!H64 -> 13.26 | Q48: =P48-1.49 -> 11.77 | R48: =SUM(Q46:Q48)/3 -> 12.286667
A49: 1993 | B49: 34151 | D49: 46.69 | E49: 16.11 | G49: 42.07 | H49: 16.93 | J49: 42.58 | K49: 16.82 | M49: ='4.1.1'!G65 -> 13.1 | N49: =M49-0 -> 13.1 | P49: ='4.1.1'!H65 -> 12.88 | Q49: =P49-1.49 -> 11.39
A50: 1993 | B50: 34182 | D50: 46.35 | E50: 15.77 | G50: 41.77 | H50: 16.63 | J50: 42.26 | K50: 16.5 | M50: ='4.1.1'!G66 -> 12.87 | N50: =M50-0 -> 12.87 | P50: ='4.1.1'!H66 -> 12.66 | Q50: =P50-1.49 -> 11.17
A51: 1993 | B51: 34213 | D51: 46.5 | E51: 15.92 | F51: =SUM(E49:E51)/3 -> 15.933333 | G51: 42.03 | H51: 16.89 | I51: =SUM(H49:H51)/3 -> 16.816667 | J51: 42.54 | K51: 16.78 | L51: =SUM(K49:K51)/3 -> 16.7 | M51: ='4.1.1'!G67 -> 12.84 | N51: =M51-0 -> 12.84 | O51: =SUM(N49:N51)/3 -> 12.936667 | P51: ='4.1.1'!H67 -> 12.72 | Q51: =P51-1.49 -> 11.23 | R51: =SUM(Q49:Q51)/3 -> 11.263333
A52: 1993 | B52: 34243 | D52: 46.03 | E52: 15.45 | G52: 41.92 | H52: 16.78 | J52: 41.95 | K52: 16.19 | M52: ='4.1.1'!G68 -> 13.64 | N52: =M52-0 -> 13.64 | P52: ='4.1.1'!H68 -> 13.51 | Q52: =P52-1.49 -> 12.02
A53: 1993 | B53: 34274 | D53: 46.08 | E53: 15.51 | G53: 42.56 | H53: 17.42 | J53: 42.03 | K53: 16.27 | M53: ='4.1.1'!G69 -> 13.68 | N53: =M53-0 -> 13.68 | P53: ='4.1.1'!H69 -> 13.42 | Q53: =P53-1.49 -> 11.93
A54: 1993 | B54: 34304 | D54: 47.47 | E54: 14.33 | F54: =SUM(E52:E54)/3 -> 15.096667 | G54: 43.92 | H54: 16.22 | I54: =SUM(H52:H54)/3 -> 16.806667 | J54: 43.23 | K54: 14.91 | L54: =SUM(K52:K54)/3 -> 15.79 | M54: ='4.1.1'!G70 -> 13.35 | N54: =M54-0 -> 13.35 | O54: =SUM(N52:N54)/3 -> 13.556667 | P54: ='4.1.1'!H70 -> 13.14 | Q54: =P54-1.64 -> 11.5 | R54: =SUM(Q52:Q54)/3 -> 11.816667
A55: 1994 | B55: 34335 | D55: 47.23 | E55: 14.09 | G55: 44.02 | H55: 16.32 | J55: 43.26 | K55: 14.94 | M55: ='4.1.1'!G71 -> 12.94 | N55: =M55-0 -> 12.94 | P55: ='4.1.1'!H71 -> 12.72 | Q55: =P55-1.64 -> 11.08
A56: 1994 | B56: 34366 | D56: 47.58 | E56: 14.44 | G56: 43.43 | H56: 15.73 | J56: 43 | K56: 14.68 | M56: ='4.1.1'!G72 -> 12.87 | N56: =M56-0 -> 12.87 | P56: ='4.1.1'!H72 -> 12.65 | Q56: =P56-1.64 -> 11.01
A57: 1994 | B57: 34394 | D57: 47.43 | E57: 14.29 | F57: =SUM(E55:E57)/3 -> 14.273333 | G57: 43.08 | H57: 15.38 | I57: =SUM(H55:H57)/3 -> 15.81 | J57: 42.85 | K57: 14.53 | L57: =SUM(K55:K57)/3 -> 14.716667 | M57: ='4.1.1'!G73 -> 12.63 | N57: =M57-0 -> 12.63 | O57: =SUM(N55:N57)/3 -> 12.813333 | P57: ='4.1.1'!H73 -> 12.37 | Q57: =P57-1.64 -> 10.73 | R57: =SUM(Q55:Q57)/3 -> 10.94
A58: 1994 | B58: 34425 | D58: 48 | E58: 14.86 | G58: 43.73 | H58: 16.03 | J58: 43.58 | K58: 15.26 | M58: ='4.1.1'!G74/1.08 -> 12.62963 | N58: =M58-0 -> 12.62963 | P58: ='4.1.1'!H74/1.08 -> 12.62037 | Q58: =P58-1.64 -> 10.98037
A59: 1994 | B59: 34455 | D59: 48.27 | E59: 15.13 | G59: 43.84 | H59: 16.14 | J59: 43.68 | K59: 15.36 | M59: ='4.1.1'!G75/1.08 -> 12.611111 | N59: =M59-0 -> 12.611111 | P59: ='4.1.1'!H75/1.08 -> 12.703704 | Q59: =P59-1.64 -> 11.063704
A60: 1994 | B60: 34486 | D60: 48.66 | E60: 15.52 | F60: =SUM(E58:E60)/3 -> 15.17 | G60: 43.86 | H60: 16.16 | I60: =SUM(H58:H60)/3 -> 16.11 | J60: 44.12 | K60: 15.8 | L60: =SUM(K58:K60)/3 -> 15.473333 | M60: ='4.1.1'!G76/1.08 -> 12.212963 | N60: =M60-0 -> 12.212963 | O60: =SUM(N58:N60)/3 -> 12.484568 | P60: ='4.1.1'!H76/1.08 -> 12.314815 | Q60: =P60-1.64 -> 10.674815 | R60: =SUM(Q58:Q60)/3 -> 10.906296
A61: 1994 | B61: 34516 | D61: 48.46 | E61: 15.32 | G61: 43.73 | H61: 16.03 | J61: 43.76 | K61: 15.44 | M61: ='4.1.1'!G77/1.08 -> 12.416667 | N61: =M61-0 -> 12.416667 | P61: ='4.1.1'!H77/1.08 -> 12.268519 | Q61: =P61-1.64 -> 10.628519
A62: 1994 | B62: 34547 | D62: 49.66 | E62: 16.52 | G62: 44.34 | H62: 16.64 | J62: 45.06 | K62: 16.74 | M62: ='4.1.1'!G78/1.08 -> 12.509259 | N62: =M62-0 -> 12.509259 | P62: ='4.1.1'!H78/1.08 -> 12.333333 | Q62: =P62-1.64 -> 10.693333
A63: 1994 | B63: 34578 | D63: 49.09 | E63: 15.95 | F63: =SUM(E61:E63)/3 -> 15.93 | G63: 44.15 | H63: 16.45 | I63: =SUM(H61:H63)/3 -> 16.373333 | J63: 44.83 | K63: 16.51 | L63: =SUM(K61:K63)/3 -> 16.23 | M63: ='4.1.1'!G79/1.08 -> 12.527778 | N63: =M63-0 -> 12.527778 | O63: =SUM(N61:N63)/3 -> 12.484568 | P63: ='4.1.1'!H79/1.08 -> 12.166667 | Q63: =P63-1.64 -> 10.526667 | R63: =SUM(Q61:Q63)/3 -> 10.616173
A64: 1994 | B64: 34608 | D64: 48.81 | E64: 15.67 | G64: 43.69 | H64: 15.98 | J64: 44.19 | K64: 15.87 | M64: ='4.1.1'!G80/1.08 -> 12.62037 | N64: =M64-0 -> 12.62037 | P64: ='4.1.1'!H80/1.08 -> 12.287037 | Q64: =P64-1.64 -> 10.647037
A65: 1994 | B65: 34639 | D65: 48.01 | E65: 14.87 | G65: 43.27 | H65: 15.57 | J65: 43.5 | K65: 15.18 | M65: ='4.1.1'!G81/1.08 -> 12.712963 | N65: =M65-0 -> 12.712963 | P65: ='4.1.1'!H81/1.08 -> 12.694444 | Q65: =P65-1.64 -> 11.054444
A66: 1994 | B66: 34669 | D66: 49.63 | E66: 14.37 | F66: =SUM(E64:E66)/3 -> 14.97 | G66: 45.14 | H66: 14.7 | I66: =SUM(H64:H66)/3 -> 15.416667 | J66: 44.91 | K66: 14.47 | L66: =SUM(K64:K66)/3 -> 15.173333 | M66: ='4.1.1'!G82/1.08 -> 12.666667 | N66: =M66-0 -> 12.666667 | O66: =SUM(N64:N66)/3 -> 12.666667 | P66: ='4.1.1'!H82/1.08 -> 13.055556 | Q66: =P66-2.14 -> 10.915556 | R66: =SUM(Q64:Q66)/3 -> 10.872346
A67: 1995 | B67: 34700 | D67: 50.31 | E67: 14.17 | G67: 46.07 | H67: 14.75 | J67: 45.48 | K67: 14.16 | M67: ='4.1.1'!G83/1.08 -> 12.333333 | N67: =M67-0 -> 12.333333 | P67: ='4.1.1'!H83/1.08 -> 12.898148 | Q67: =P67-2.14 -> 10.758148
A68: 1995 | B68: 34731 | D68: 49.87 | E68: 13.73 | G68: 45.57 | H68: 14.25 | J68: 44.95 | K68: 13.63 | M68: ='4.1.1'!G84/1.08 -> 12.592593 | N68: =M68-0 -> 12.592593 | P68: ='4.1.1'!H84/1.08 -> 12.777778 | Q68: =P68-2.14 -> 10.637778
A69: 1995 | B69: 34759 | D69: 50.2 | E69: 14.06 | F69: =SUM(E67:E69)/3 -> 13.986667 | G69: 45.85 | H69: 14.53 | I69: =SUM(H67:H69)/3 -> 14.51 | J69: 45.28 | K69: 13.96 | L69: =SUM(K67:K69)/3 -> 13.916667 | M69: ='4.1.1'!G85/1.08 -> 12.685185 | N69: =M69-0 -> 12.685185 | O69: =SUM(N67:N69)/3 -> 12.537037 | P69: ='4.1.1'!H85/1.08 -> 12.75 | Q69: =P69-2.14 -> 10.61 | R69: =SUM(Q67:Q69)/3 -> 10.668642
A70: 1995 | B70: 34790 | D70: 51.14 | E70: 15 | G70: 46.58 | H70: 15.26 | J70: 46.03 | K70: 14.71 | M70: ='4.1.1'!G86/1.08 -> 12.861111 | N70: =M70-0 -> 12.861111 | P70: ='4.1.1'!H86/1.08 -> 13.092593 | Q70: =P70-2.14 -> 10.952593
A71: 1995 | B71: 34820 | D71: 51.42 | E71: 15.28 | G71: 46.72 | H71: 15.4 | J71: 46.48 | K71: 15.16 | M71: ='4.1.1'!G87/1.08 -> 12.759259 | N71: =M71-0 -> 12.759259 | P71: ='4.1.1'!H87/1.08 -> 12.888889 | Q71: =P71-2.14 -> 10.748889
A72: 1995 | B72: 34851 | D72: 51.38 | E72: 15.24 | F72: =SUM(E70:E72)/3 -> 15.173333 | G72: 46.55 | H72: 15.23 | I72: =SUM(H70:H72)/3 -> 15.296667 | J72: 46.43 | K72: 15.11 | L72: =SUM(K70:K72)/3 -> 14.993333 | M72: ='4.1.1'!G88/1.08 -> 12.314815 | N72: =M72-0 -> 12.314815 | O72: =SUM(N70:N72)/3 -> 12.645062 | P72: ='4.1.1'!H88/1.08 -> 12.62963 | Q72: =P72-2.14 -> 10.48963 | R72: =SUM(Q70:Q72)/3 -> 10.73037
A73: 1995 | B73: 34881 | D73: 51.5 | E73: 15.36 | G73: 46.61 | H73: 15.29 | J73: 46.38 | K73: 15.06 | M73: ='4.1.1'!G89/1.08 -> 12.537037 | N73: =M73-0 -> 12.537037 | P73: ='4.1.1'!H89/1.08 -> 12.240741 | Q73: =P73-2.14 -> 10.100741
A74: 1995 | B74: 34912 | D74: 51.18 | E74: 15.04 | G74: 46.23 | H74: 14.91 | J74: 46.12 | K74: 14.8 | M74: ='4.1.1'!G90/1.08 -> 12.796296 | N74: =M74-0 -> 12.796296 | P74: ='4.1.1'!H90/1.08 -> 12.648148 | Q74: =P74-2.14 -> 10.508148
A75: 1995 | B75: 34943 | D75: 50.47 | E75: 14.33 | F75: =SUM(E73:E75)/3 -> 14.91 | G75: 45.53 | H75: 14.21 | I75: =SUM(H73:H75)/3 -> 14.803333 | J75: 45.43 | K75: 14.11 | L75: =SUM(K73:K75)/3 -> 14.656667 | M75: ='4.1.1'!G91/1.08 -> 13.074074 | N75: =M75-0 -> 13.074074 | O75: =SUM(N73:N75)/3 -> 12.802469 | P75: ='4.1.1'!H91/1.08 -> 12.888889 | Q75: =P75-2.14 -> 10.748889 | R75: =SUM(Q73:Q75)/3 -> 10.452593
A76: 1995 | B76: 34973 | D76: 50.05 | E76: 13.91 | G76: 45.19 | H76: 13.87 | J76: 44.92 | K76: 13.6 | M76: ='4.1.1'!G92/1.08 -> 12.87963 | N76: =M76-0 -> 12.87963 | P76: ='4.1.1'!H92/1.08 -> 12.657407 | Q76: =P76-2.14 -> 10.517407
A77: 1995 | B77: 35004 | D77: 49.55 | E77: 13.41 | G77: 44.71 | H77: 13.39 | J77: 44.23 | K77: 12.91 | M77: ='4.1.1'!G93/1.08 -> 12.898148 | N77: =M77-0 -> 12.898148 | P77: ='4.1.1'!H93/1.08 -> 12.833333 | Q77: =P77-2.14 -> 10.693333
A78: 1995 | B78: 35034 | D78: 52.62 | E78: 13.5 | F78: =SUM(E76:E78)/3 -> 13.606667 | G78: 48.34 | H78: 14.04 | I78: =SUM(H76:H78)/3 -> 13.766667 | J78: 47.4 | K78: 13.1 | L78: =SUM(K76:K78)/3 -> 13.203333 | M78: ='4.1.1'!G94/1.08 -> 13.601852 | N78: =M78-0 -> 13.601852 | O78: =SUM(N76:N78)/3 -> 13.126543 | P78: ='4.1.1'!H94/1.08 -> 13.814815 | Q78: =P78-2.33 -> 11.484815 | R78: =SUM(Q76:Q78)/3 -> 10.898519
A79: 1996 | B79: 35065 | D79: 52.74 | E79: 13.62 | G79: 48.88 | H79: 14.58 | J79: 47.6 | K79: 13.3 | M79: ='4.1.1'!G95/1.08 -> 14.240741 | N79: =M79-0 -> 14.240741 | P79: ='4.1.1'!H95/1.08 -> 14.685185 | Q79: =P79-2.33 -> 12.355185
A80: 1996 | B80: 35096 | D80: 50.83 | E80: 11.71 | G80: 47.36 | H80: 13.06 | J80: 46.34 | K80: 12.04 | M80: ='4.1.1'!G96/1.08 -> 13.962963 | N80: =M80-0 -> 13.962963 | P80: ='4.1.1'!H96/1.08 -> 14.453704 | Q80: =P80-2.33 -> 12.123704
A81: 1996 | B81: 35125 | D81: 50.45 | E81: 11.33 | F81: =SUM(E79:E81)/3 -> 12.22 | G81: 47.15 | H81: 12.85 | I81: =SUM(H79:H81)/3 -> 13.496667 | J81: 46.13 | K81: 11.83 | L81: =SUM(K79:K81)/3 -> 12.39 | M81: ='4.1.1'!G97/1.08 -> 14.842593 | N81: =M81-0 -> 14.842593 | O81: =SUM(N79:N81)/3 -> 14.348765 | P81: ='4.1.1'!H97/1.08 -> 15.12037 | Q81: =P81-2.33 -> 12.79037 | R81: =SUM(Q79:Q81)/3 -> 12.423086
A82: 1996 | B82: 35156 | D82: 51.36 | E82: 12.24 | G82: 48.02 | H82: 13.72 | J82: 47.01 | K82: 12.71 | M82: ='4.1.1'!G98/1.08 -> 15.342593 | N82: =M82-0 -> 15.342593 | P82: ='4.1.1'!H98/1.08 -> 15.787037 | Q82: =P82-2.33 -> 13.457037
A83: 1996 | B83: 35186 | D83: 51.3 | E83: 12.18 | G83: 47.85 | H83: 13.56 | J83: 46.92 | K83: 12.62 | M83: ='4.1.1'!G99/1.08 -> 14.12963 | N83: =M83-0 -> 14.12963 | P83: ='4.1.1'!H99/1.08 -> 14.611111 | Q83: =P83-2.33 -> 12.281111
A84: 1996 | B84: 35217 | D84: 50.76 | E84: 11.64 | F84: =SUM(E82:E84)/3 -> 12.02 | G84: 47.32 | H84: 13.02 | I84: =SUM(H82:H84)/3 -> 13.433333 | J84: 46.53 | K84: 12.23 | L84: =SUM(K82:K84)/3 -> 12.52 | M84: ='4.1.1'!G100/1.08 -> 13.37963 | N84: =M84-0 -> 13.37963 | O84: =SUM(N82:N84)/3 -> 14.283951 | P84: ='4.1.1'!H100/1.08 -> 13.935185 | Q84: =P84-2.33 -> 11.605185 | R84: =SUM(Q82:Q84)/3 -> 12.447778
A85: 1996 | B85: 35247 | D85: 50.63 | E85: 11.51 | G85: 47 | H85: 12.7 | J85: 46.25 | K85: 11.95 | M85: ='4.1.1'!G101/1.08 -> 13.546296 | N85: =M85-0 -> 13.546296 | P85: ='4.1.1'!H101/1.08 -> 14.287037 | Q85: =P85-2.33 -> 11.957037
A86: 1996 | B86: 35278 | D86: 52.35 | E86: 13.23 | G86: 49.04 | H86: 14.74 | J86: 48.31 | K86: 14.02 | M86: ='4.1.1'!G102/1.08 -> 13.824074 | N86: =M86-0 -> 13.824074 | P86: ='4.1.1'!H102/1.08 -> 14.37037 | Q86: =P86-2.33 -> 12.04037
A87: 1996 | B87: 35309 | D87: 53.65 | E87: 14.53 | F87: =SUM(E85:E87)/3 -> 13.09 | G87: 50.03 | H87: 15.73 | I87: =SUM(H85:H87)/3 -> 14.39 | J87: 49.57 | K87: 15.27 | L87: =SUM(K85:K87)/3 -> 13.746667 | M87: ='4.1.1'!G103/1.08 -> 15.787037 | N87: =M87-0 -> 15.787037 | O87: =SUM(N85:N87)/3 -> 14.385802 | P87: ='4.1.1'!H103/1.08 -> 16.212963 | Q87: =P87-2.33 -> 13.882963 | R87: =SUM(Q85:Q87)/3 -> 12.62679
A88: 1996 | B88: 35339 | D88: 54.22 | E88: 15.1 | G88: 51.63 | H88: 17.33 | J88: 50.03 | K88: 15.73 | M88: ='4.1.1'!G104/1.08 -> 16.657407 | N88: =M88-0 -> 16.657407 | P88: ='4.1.1'!H104/1.08 -> 17.324074 | Q88: =P88-2.33 -> 14.994074
A89: 1996 | B89: 35370 | D89: 54.69 | E89: 15.57 | G89: 51.79 | H89: 17.49 | J89: 50.43 | K89: 16.13 | M89: ='4.1.1'!G105/1.08 -> 15.546296 | N89: =M89-0 -> 15.546296 | P89: ='4.1.1'!H105/1.08 -> 16.314815 | Q89: =P89-2.33 -> 13.984815
A90: 1996 | B90: 35400 | D90: 56.45 | E90: 14.77 | F90: =SUM(E88:E90)/3 -> 15.146667 | G90: 53.27 | H90: 16.41 | I90: =SUM(H88:H90)/3 -> 17.076667 | J90: 52.13 | K90: 15.27 | L90: =SUM(K88:K90)/3 -> 15.71 | M90: ='4.1.1'!G106/1.08 -> 15.759259 | N90: =M90-0 -> 15.759259 | O90: =SUM(N88:N90)/3 -> 15.987654 | P90: ='4.1.1'!H106/1.08 -> 16.555556 | Q90: =P90-2.5 -> 14.055556 | R90: =SUM(Q88:Q90)/3 -> 14.344815
A91: 1997 | B91: 35431 | D91: 55.71 | E91: 14.03 | G91: 52.78 | H91: 15.92 | J91: 51.99 | K91: 15.13 | M91: ='4.1.1'!G107/1.08 -> 15.861111 | N91: =M91-0 -> 15.861111 | P91: ='4.1.1'!H107/1.08 -> 16.796296 | Q91: =P91-2.5 -> 14.296296
A92: 1997 | B92: 35462 | D92: 55.69 | E92: 14.01 | G92: 52.24 | H92: 15.38 | J92: 51.2 | K92: 14.34 | M92: ='4.1.1'!G108/1.08 -> 14.777778 | N92: =M92-0 -> 14.777778 | P92: ='4.1.1'!H108/1.08 -> 15.75 | Q92: =P92-2.5 -> 13.25
A93: 1997 | B93: 35490 | D93: 54.67 | E93: 12.99 | F93: =SUM(E91:E93)/3 -> 13.676667 | G93: 51.35 | H93: 14.48 | I93: =SUM(H91:H93)/3 -> 15.26 | J93: 50.19 | K93: 13.33 | L93: =SUM(K91:K93)/3 -> 14.266667 | M93: ='4.1.1'!G109/1.08 -> 13.537037 | N93: =M93-0 -> 13.537037 | O93: =SUM(N91:N93)/3 -> 14.725309 | P93: ='4.1.1'!H109/1.08 -> 14.259259 | Q93: =P93-2.5 -> 11.759259 | R93: =SUM(Q91:Q93)/3 -> 13.101852
A94: 1997 | B94: 35521 | D94: 54.97 | E94: 13.29 | G94: 51.25 | H94: 14.39 | J94: 50.42 | K94: 13.56 | M94: ='4.1.1'!G110/1.08 -> 13.157407 | N94: =M94-0 -> 13.157407 | P94: ='4.1.1'!H110/1.08 -> 14.055556 | Q94: =P94-2.5 -> 11.555556
A95: 1997 | B95: 35551 | D95: 55.24 | E95: 13.56 | G95: 51.32 | H95: 14.46 | J95: 50.56 | K95: 13.7 | M95: ='4.1.1'!G111/1.08 -> 12.907407 | N95: =M95-0 -> 12.907407 | P95: ='4.1.1'!H111/1.08 -> 14.296296 | Q95: =P95-2.5 -> 11.796296
A96: 1997 | B96: 35582 | D96: 55.65 | E96: 13.97 | F96: =SUM(E94:E96)/3 -> 13.606667 | G96: 51.57 | H96: 14.71 | I96: =SUM(H94:H96)/3 -> 14.52 | J96: 50.94 | K96: 14.09 | L96: =SUM(K94:K96)/3 -> 13.783333 | M96: ='4.1.1'!G112/1.08 -> 12.75 | N96: =M96-0 -> 12.75 | O96: =SUM(N94:N96)/3 -> 12.938272 | P96: ='4.1.1'!H112/1.08 -> 13.777778 | Q96: =P96-2.5 -> 11.277778 | R96: =SUM(Q94:Q96)/3 -> 11.54321
A97: 1997 | B97: 35612 | D97: 58.04 | E97: 12.94 | G97: 53.99 | H97: 13.71 | J97: 53.35 | K97: 13.07 | M97: ='4.1.1'!G113/1.08 -> 12.268519 | N97: =M97-0 -> 12.268519 | P97: ='4.1.1'!H113/1.08 -> 13.527778 | Q97: =P97-2.58 -> 10.947778
A98: 1997 | B98: 35643 | D98: 59.16 | E98: 14.06 | G98: 54.88 | H98: 14.59 | J98: 54.53 | K98: 14.25 | M98: ='4.1.1'!G114/1.08 -> 12.833333 | N98: =M98-0 -> 12.833333 | P98: ='4.1.1'!H114/1.08 -> 14.074074 | Q98: =P98-2.58 -> 11.494074
A99: 1997 | B99: 35674 | D99: 59.81 | E99: 14.71 | F99: =SUM(E97:E99)/3 -> 13.903333 | G99: 55.12 | H99: 14.83 | I99: =SUM(H97:H99)/3 -> 14.376667 | J99: 55.08 | K99: 14.8 | L99: =SUM(K97:K99)/3 -> 14.04 | M99: ='4.1.1'!G115/1.05 -> 12.838095 | N99: =M99-0 -> 12.838095 | O99: =SUM(N97:N99)/3 -> 12.646649 | P99: ='4.1.1'!H115/1.05 -> 13.990476 | Q99: =P99-2.58 -> 11.410476 | R99: =SUM(Q97:Q99)/3 -> 11.284109
A100: 1997 | B100: 35704 | D100: 59.36 | E100: 14.26 | G100: 54.73 | H100: 14.45 | J100: 54.65 | K100: 14.37 | M100: ='4.1.1'!G116/1.05 -> 13.590476 | N100: =M100-0 -> 13.590476 | P100: ='4.1.1'!H116/1.05 -> 14.380952 | Q100: =P100-2.58 -> 11.800952
...

Sheet 4.1.3
A1: Table 4.1.3 Typical retail prices of petroleum products from 1954, United Kingdom
A2: The estimates are generally representative of prices paid (inclusive of taxes) at the pump on or about the 15th of the month. Estimates are based on information provided by oil companies from 1977 until the 15th of the month.
A3: Estimates are based on information provided by oil companies from 1977 until 1994. From January 1995 data from super/hypermarket chains have been included.
A4: For rates of duty and VAT see Annex C.
A5: Note 1. From October 1999 Four Star prices represent ‘Lead Replacement Petrol’ (LRP) which had replaced Four Star at 95 per cent of outlets at that time. Leaded petrol has now been phased out.
A6: Note 1. Pump prices for both petrols are broadly the same. The LRP series has been discontinued from September 2005 due to the low volume of sales.
A7: Note 2. From April 2001, Premium unleaded prices represent Ultra Low Sulphur Petrol (ULSP), which now accounts for virtually all Premium unleaded sold. The pump prices for both fuels were broadly the same.
A8: Note 3. From July 1999 diesel prices represent average prices for Ultra Low Sulphur Diesel which now accounts for virtually all diesel sold. Pump prices for both diesels are broadly the same.
A9: Note 4. Typical prices for deliveries of up to 1,000 litres of standard grade burning oil and between 2,000 and 5,000 litres of gas oil.
A10: Note 4. Prior to 1977, prices were for deliveries of 900 litres of standard grade burning oil and 2,275 litres of gas oil. Since April 1994 prices include VAT at a rate of 8% until September 1997 when the applicable rate was reduced to 5%.
A11: In the table r indicates revised data. An r in the date column indicates all data in the row has been revised.
A12: Freeze panes are turned on. To turn off freeze panes select the 'View' ribbon then 'Freeze Panes' then 'Unfreeze Panes' or use [Alt,W,F]
A13: Source: Department for Energy Security and Net Zero
A14: Year | B14: Month | C14: Motor spirit: 2 star (Pence per litre) | D14: Motor spirit: 4 star/LRP (Pence per litre) [Note 1] | E14: Motor spirit: Super unleaded (Pence per litre) | F14: Motor spirit: Premium unleaded / ULSP (Pence per litre) [Note 2] | G14: Derv: Diesel / ULSD (Pence per litre) [Note 3] | H14: Standard grade burning oil (Pence per litre) [Note 4] | I14: Gas oil (Pence per litre) [Note 4]
A15: 1954 | B15: January | C15: 4.47 | D15: 4.9 | E15: .. | F15: .. | G15: .. | H15: .. | I15: ..
A16: 1955 | B16: January | C16: 4.49 | D16: 4.9 | E16: .. | F16: .. | G16: 4.38 | H16: .. | I16: ..
A17: 1956 | B17: January | C17: 4.49 | D17: 5.04 | E17: .. | F17: .. | G17: 4.47 | H17: .. | I17: ..
A18: 1957 | B18: January | C18: 6.09 | D18: 6.64 | E18: .. | F18: .. | G18: 6.07 | H18: .. | I18: ..
A19: 1958 | B19: January | C19: 4.65 | D19: 5.13 | E19: .. | F19: .. | G19: 4.69 | H19: .. | I19: ..
A20: 1959 | B20: January | C20: 4.67 | D20: 5.13 | E20: .. | F20: .. | G20: 4.7 | H20: .. | I20: ..
A21: 1960 | B21: January | C21: 4.67 | D21: 5.18 | E21: .. | F21: .. | G21: 4.79 | H21: 1.55 | I21: 1.55
A22: 1961 | B22: January | C22: 4.58 | D22: 5.09 | E22: .. | F22: .. | G22: 4.65 | H22: 1.65 | I22: 1.52
A23: 1962 | B23: January | C23: 4.86 | D23: 5.36 | E23: .. | F23: .. | G23: 4.93 | H23: 1.89 | I23: 1.73
A24: 1963 | B24: January | C24: 4.77 | D24: 5.36 | E24: .. | F24: .. | G24: 4.93 | H24: 1.86 | I24: 1.73
A25: 1964 | B25: January | C25: 4.77 | D25: 5.22 | E25: .. | F25: .. | G25: 4.97 | H25: 1.86 | I25: 1.73
A26: 1965 | B26: January | C26: 5.36 | D26: 5.82 | E26: .. | F26: .. | G26: 5.52 | H26: 1.86 | I26: 1.73
A27: 1966 | B27: January | C27: 5.36 | D27: 5.68 | E27: .. | F27: .. | G27: 5.52 | H27: 1.86 | I27: 1.73
A28: 1967 | B28: January | C28: 5.73 | D28: 6.05 | E28: .. | F28: .. | G28: 5.89 | H28: 1.86 | I28: 1.73
A29: 1968 | B29: January | C29: 5.77 | D29: 6.14 | E29: .. | F29: .. | G29: 6.07 | H29: 2.06 | I29: 1.95
A30: 1969 | B30: January | C30: 6.57 | D30: 6.94 | E30: .. | F30: .. | G30: 6.92 | H30: 2.09 | I30: 1.95
A31: 1970 | B31: January | C31: 6.78 | D31: 7.15 | E31: .. | F31: .. | G31: 6.99 | H31: 2.17 | I31: 2.02
A32: 1971 | B32: January | C32: 7.06 | D32: 7.42 | E32: .. | F32: .. | G32: 7.22 | H32: 2.34 | I32: 2.14
... A49: 1988 | B49: January | C49: 35.98 | D49: 36.79 | E49: .. | F49: .. | G49: 33.94 | H49: 11.97 | I49: 12.29
A50: 1989 | B50: January | C50: 36.36 | D50: 37.14 | E50: .. | F50: 36.02 | G50: 34.17 | H50: 11.41 | I50: 11.15
A51: 1990 | B51: January | C51: .. | D51: 40.92 | E51: .. | F51: 38.37 | G51: 39.21 | H51: 15.45 | I51: 15.46
A52: 1991 | B52: January | C52: .. | D52: 45.13 | E52: 44.38 | F52: 42.14 | G52: 43.31 | H52: 17.52 | I52: 17.13
A53: 1992 | B53: January | C53: .. | D53: 46.93 | E53: 45.57 | F53: 43.43 | G53: 43.19 | H53: 12.47 | I53: 12.02
A54: 1993 | B54: January | C54: .. | D54: 51.27 | E54: 49.76 | F54: 47.13 | G54: 47.05 | H54: 14.1 | I54: 13.52
A55: 1994 | B55: January | C55: .. | D55: 55.5 | E55: 54.48 | F55: 50.83 | G55: 51.72 | H55: 12.94 | I55: 12.72
A56: 1995 | B56: January | C56: .. | D56: 59.11 | E56: 58 | F56: 53.44 | G56: 54.13 | H56: 13.32 | I56: 13.93
A57: 1996 | B57: January | C57: .. | D57: 61.97 | E57: 61.26 | F57: 55.93 | G57: 57.43 | H57: 15.38 | I57: 15.86
A58: 1997 | B58: January | C58: .. | D58: 65.46 | E58: 69.24 | F58: 61.09 | G58: 62.02 | H58: 17.13 | I58: 18.14
A59: 1998 | B59: January | C59: .. | D59: 69.03 | E59: 73.96 | F59: 63.13 | G59: 63.34 | H59: 12.92 | I59: 13.67
A60: 1999 | B60: January | C60: .. | D60: 69.61 | E60: 79.23 | F60: 62.87 | G60: 63.95 | H60: 9.89 | I60: 11.36
A61: 2000 | B61: January | C61: .. | D61: 80.84 | E61: 84.15 | F61: 75.38 | G61: 77.75 | H61: 17.84 | I61: 18.15
A62: 2001 | B62: January | C62: .. | D62: 82.19 | E62: 85.06 | F62: 76.85 | G62: 81.63 | H62: 19.86 | I62: 20.46
A63: 2002 | B63: January | C63: .. | D63: 75.94 | E63: 78.48 | F63: 69.9 | G63: 74.65 | H63: 14.61 | I63: 14.71
A64: 2003 | B64: =B63 -> January | C64: .. | D64: 78.15 | E64: 80.47 | F64: 74.95 | G64: 76.38 | H64: 17.83 | I64: 18.63
A65: 2004 | B65: =B64 -> January | C65: .. | D65: 80.04 | E65: 81.49 | F65: 76.2 | G65: 77.92 | H65: 18.33 | I65: 18.95
A66: 2005 | B66: =B65 -> January | C66: .. | D66: 87.16 | E66: 87.43 | F66: 78.99 | G66: 84.15 | H66: 22.16 | I66: 23.99
A67: 2006 | B67: =B66 -> January | C67: .. | D67: .. | E67: 94.73 | F67: 88.84 | G67: 93.07 | H67: 31.58 | I67: 33.6
A68: 2007 | B68: =B67 -> January | C68: .. | D68: .. | E68: 94.8 | F68: 86.91 | G68: 91.44 | H68: 30.88 | I68: 34.03
A69: 2008 | B69: =B67 -> January | C69: .. | D69: .. | E69: 110.59 | F69: 103.71 | G69: 108.7 | H69: 43.9 | I69: 51.01
A70: 2009 | B70: =B68 -> January | C70: .. | D70: .. | E70: 93.3 | F70: 86.33 | G70: 98.74 | H70: 36.01 | I70: 43.83
A71: 2010 | B71: =B69 -> January | C71: .. | D71: .. | E71: 118.52927 | F71: 111.48884 | G71: 113.311 | H71: 42.490196 | I71: 50.639435
A72: 2011 | B72: =B70 -> January | C72: .. | D72: .. | E72: 134.83284 | F72: 127.52572 | G72: 132.07785 | H72: 55.136714 | I72: 61.901548
A73: 2012 | B73: January | C73: .. | D73: .. | E73: 140.39533 | F73: 132.88734 | G73: 141.3445 | H73: 61.037362 | I73: 70.744632
A74: 2013 | B74: January | C74: .. | D74: .. | E74: 139.35155 | F74: 131.70958 | G74: 139.45832 | H74: 57.852491 | I74: 68.986218
A75: 2014 | B75: January | C75: .. | D75: .. | E75: 137.77165 | F75: 130.1638 | G75: 138.10669 | H75: 55.668188 | I75: 66.675702
A76: 2015 | B76: January | C76: .. | D76: .. | E76: 116.22432 | F76: 108.44509 | G76: 115.84513 | H76: 36.432617 | I76: 46.331203
A77: 2016 | B77: January | C77: .. | D77: .. | E77: 110.24386 | F77: 101.74239 | G77: 102.5226 | H77: 22.813 | I77: 35.185763
A78: 2017 | B78: January | C78: .. | D78: .. | E78: 127.85469 | F78: 118.69498 | G78: 121.99151 | H78: 40.68 | I78: 51.987027
A79: 2018 | B79: January | C79: .. | D79: .. | E79: 130.51236 | F79: 121.16115 | G79: 124.55389 | H79: 45.919 | I79: 55.511189
A80: 2019 | B80: January | C80: .. | D80: .. | E80: 129.55495 | F80: 119.45654 | G80: 129.26834 | H80: 46.587 | I80: 56.722092
A81: 2020 | B81: January | C81: .. | D81: .. | E81: 139.21163 | F81: 127.14053 | G81: 132.63435 | H81: 48.197 | I81: 59.820065
A82: 2021 | B82: January | C82: .. | D82: .. | E82: 130.1747 | F82: 117.2518 | G82: 121.73464 | H82: 34.624 | I82: 49.851804
A83: 2022 | B83: January | C83: .. | D83: .. | E83: 156.9926 | F83: 144.9245 | G83: 148.7429 | H83: 53.925 | I83: 71.8762
A84: 2023 | B84: January | C84: .. | D84: .. | E84: 162.02353 | F84: 148.45071 | G84: 171.27094 | H84: 74.788 | I84: 92.105607
... A86: 2025 | B86: January | C86: .. | D86: .. | E86: 149.32678 | F86: 136.7574 | G86: 143.41604 | H86: 56.644 | I86: 74.680828
A87: 2026 | B87: January | E87: 149.00372 | F87: 133.19472 | G87: 142.41128 | H87: 51.843 | I87: 64.43028

Sheet Charts
A1: Charts 4.1.1 to 4.1.4 Typical Prices of Petroleum Products and 4.2.1 Index of Crude Oil Prices
A4: Chart 4.1.1 | K4: Chart 4.1.3 | U4: Chart 4.2.1
A25: Chart 4.1.2 | K25: Chart 4.1.4
A45: Return to Contents Page

Sheet Methodology
A1: Notes for Tables 4.1.1 to 4.1.3
A2: The data published in these tables are national average prices calculated from prices supplied by a sample of motor fuel companies and supermarkets.
A3: Notes
A4: Because of the different pricing policies companies in the road fuels market have, average prices presented here will differ to what companies may charge and prices can differ dependant on the area of the country they are charged in.
A5: Since 1 September 2021, the Unleaded figure reported inlcudes the new standard "E10" grade. This was implemented in Great Britain by companies as soon as the legislation was in place.
A6: On 1 November 2022 "E10" was also rolled out in Northern Ireland. Therefore, between 1 September 2021 and 31 October 2022 the unleaded average included differing grades under the umbrella of “unleaded” in our releases.
A7: Crude oil prices are shown in Table 4.1.1 as an index based on a “basket” of both indigenous and imported crude oil prices that are used as an input, along with other fuel prices, for the Producer Prices Index (produced by ONS).
A8: Link to Producer Prices Index
A9: The index represents the average price paid by refineries for the month and is calculated in sterling on a Cost, Insurance and Freight (CIF) basis.
A10: Link to Asymmetries in Trade Data - A UK Perspective report
A11: Provisional monthly crude oil prices are usually revised in the month following their original publication, with revisions being marked with an “r”.
A12: Historic Data
... A15: Return to Contents Page

Sheet chart_data
A1: Table 4.1.1 Typical retail prices of petroleum products and a crude oil price index (monthly) | S1: Change p/litre | T1: % Change | U1: Change p/litre | V1: % Change | X1: Change p/litre | Y1: % Change | Z1: Change p/litre | AA1: % Change | AC1: Change p/litre | AD1: % Change | AE1: Change p/litre | AF1: % Change | AH1: Change p/litre | AI1: % Change | AJ1: Change p/litre | AK1: % Change | AN1: Change p/litre | AO1: % Change | AP1: Change p/litre | AQ1: % Change | AS1: Change p/litre | AT1: % Change | AU1: Change p/litre | AV1: % Change | AX1: Change p/litre | AY1: % Change | AZ1: Change p/litre | BA1: % Change | BC1: Change p/litre | BD1: % Change | BE1: Change p/litre | BF1: % Change | BH1: Change p/litre | BI1: % Change | BJ1: Change p/litre | BK1: % Change | BM1: Change p/litre | BN1: % Change | BO1: Change p/litre | BP1: % Change
D2: Motor spirit1 | G2: Derv1 | H2: Standard grade | I2: Gas oil1,3 | K2: Crude oil acquired | Q2: Crude oil acquired | S2: MTH | T2: MTH | U2: YR | V2: YR | X2: MTH | Y2: MTH | Z2: YR | AA2: YR | AC2: MTH | AD2: MTH | AE2: YR | AF2: YR | AH2: MTH | AI2: MTH | AJ2: YR | AK2: MTH | AN2: MTH | AO2: MTH | AP2: YR | AQ2: YR | AS2: MTH | AT2: MTH | AU2: YR | AV2: YR | AX2: MTH | AY2: MTH | AZ2: YR | BA2: YR | BC2: MTH | BD2: MTH | BE2: YR | BF2: YR | BH2: MTH | BI2: MTH | BJ2: YR | BK2: YR | BM2: MTH | BN2: MTH | BO2: YR | BP2: YR
D3: 4 star / LRP | E3: Super | F3: Premium | H3: burning oil1,2 | K3: by refineries | M3: ULSP to ULSD | Q3: by refineries | S3: Premium | T3: Premium | U3: Premium | V3: Premium | W3: Premium | X3: Premium | Y3: Premium | Z3: Premium | AA3: Premium | AN3: Super | AO3: Super | AP3: Super | AQ3: Super | AR3: Super | AS3: Super | AT3: Super | AU3: Super | AV3: Super | AX3: SGBO | AY3: SGBO | AZ3: SGBO | BA3: SGBO | BB3: SGBO | BC3: SGBO | BD3: SGBO | BE3: SGBO | BF3: SGBO | BH3: GAS Oil | BI3: GAS Oil | BJ3: GAS Oil | BK3: GAS Oil | BL3: GAS Oil | BM3: GAS Oil | BN3: GAS Oil | BO3: GAS Oil | BP3: GAS Oil
E4: unleaded | F4: unleaded | M4: Differential | Q4: Historic Indices | S4: unleaded | T4: unleaded | U4: unleaded | V4: unleaded | W4: unleaded | X4: unleaded | Y4: unleaded | Z4: unleaded | AA4: unleaded | AC4: Derv1 | AD4: Derv1 | AE4: Derv2 | AF4: Derv1 | AG4: Derv1 | AH4: Derv1 | AI4: Derv1 | AJ4: Derv1 | AK4: Derv1 | AN4: unleaded | AO4: unleaded | AP4: unleaded | AQ4: unleaded | AR4: unleaded | AS4: unleaded | AT4: unleaded | AU4: unleaded | AV4: unleaded | BV4: Price | BW4: MTH | BX4: MTH | BY4: YR | BZ4: YR
D5: Pence per litre | K5: 2010 = 100 | O5: 2005 = 100 | P5: 2000 = 100 | Q5: 1995 = 100 | W5: Excluding VAT and Duty | X5: Excluding VAT and Duty | Y5: Excluding VAT and Duty | Z5: Excluding VAT and Duty | AA5: Excluding VAT and Duty | AG5: Excluding VAT and Duty | AH5: Excluding VAT and Duty | AI5: Excluding VAT and Duty | AJ5: Excluding VAT and Duty | AK5: Excluding VAT and Duty | AR5: Excluding VAT and Duty | AS5: Excluding VAT and Duty | AT5: Excluding VAT and Duty | AU5: Excluding VAT and Duty | AV5: Excluding VAT and Duty | BB5: Excluding VAT and Duty | BC5: Excluding VAT and Duty | BD5: Excluding VAT and Duty | BE5: Excluding VAT and Duty | BF5: Excluding VAT and Duty | BL5: Excluding VAT and Duty | BM5: Excluding VAT and Duty | BN5: Excluding VAT and Duty | BO5: Excluding VAT and Duty | BP5: Excluding VAT and Duty | BV5: p/litre | BW5: p/litre | BX5: % | BY5: p/litre | BZ5: %
A6: 32509 | B6: 1989 | C6: January | D6: 37.14 | E6: .. | F6: 36.02 | G6: 34.17 | H6: 11.41 | I6: 11.15 | BU6: ULSP Pump price | BV6: =INDEX(chart_data!F:F,MATCH(MAX(chart_data!$A:$A),chart_data!$A:$A,0)) -> 161.85764 | BW6: =INDEX(chart_data!S:S,MATCH(MAX(chart_data!$A:$A),chart_data!$A:$A,0)) -> 14.85303 | BX6: =INDEX(chart_data!T:T,MATCH(MAX(chart_data!$A:$A),chart_data!$A:$A,0)) -> 0.13446298 | BY6: =INDEX(chart_data!U:U,MATCH(MAX(chart_data!$A:$A),chart_data!$A:$A,0)) -> 37.815014 | BZ6: =INDEX(chart_data!V:V,MATCH(MAX(chart_data!$A:$A),chart_data!$A:$A,0)) -> 0.30485499
A7: 32540 | B7: 1989 | C7: February | D7: 38.3 | E7: .. | F7: 36.88 | G7: 35.03 | H7: 10.83 | I7: 10.49 | BU7: Excluding vat and duty | BV7: =INDEX(chart_data!W:W,MATCH(MAX(chart_data!$A:$A),chart_data!$A:$A,0)) -> 76.931367 | BW7: =INDEX(chart_data!X:X,MATCH(MAX(chart_data!$A:$A),chart_data!$A:$A,0)) -> 12.377525 | BX7: =INDEX(chart_data!Y:Y,MATCH(MAX(chart_data!$A:$A),chart_data!$A:$A,0)) -> 0.19173956 | BY7: =INDEX(chart_data!Z:Z,MATCH(MAX(chart_data!$A:$A),chart_data!$A:$A,0)) -> 31.512511 | BZ7: =INDEX(chart_data!AA:AA,MATCH(MAX(chart_data!$A:$A),chart_data!$A:$A,0)) -> 0.69382002
A8: 32568 | B8: 1989 | C8: March | D8: 38.85 | E8: .. | F8: 37.3 | G8: 35.09 | H8: 11.4 | I8: 10.9
A9: 32599 | B9: 1989 | C9: April | D9: 41.14 | E9: .. | F9: 39.09 | G9: 36.08 | H9: 11.45 | I9: 10.83 | BU9: DERV Pump price | BV9: =INDEX(chart_data!G:G,MATCH(MAX(chart_data!$A:$A),chart_data!$A:$A,0)) -> 171.39069 | BW9: =INDEX(chart_data!AC:AC,MATCH(MAX(chart_data!$A:$A),chart_data!$A:$A,0)) -> 20.314196 | BX9: =INDEX(chart_data!AD:AD,MATCH(MAX(chart_data!$A:$A),chart_data!$A:$A,0)) -> 0.13446298 | BY9: =INDEX(chart_data!AE:AE,MATCH(MAX(chart_data!$A:$A),chart_data!$A:$A,0)) -> 43.282151 | BZ9: =INDEX(chart_data!AF:AF,MATCH(MAX(chart_data!$A:$A),chart_data!$A:$A,0)) -> 0.33785531
A10: 32629 | B10: 1989 | C10: May | D10: 42.83 | E10: .. | F10: 40.81 | G10: 36.06 | H10: 11.41 | I10: 10.81 | BU10: Excluding vat and duty | BV10: =INDEX(chart_data!AG:AG,MATCH(MAX(chart_data!$A:$A),chart_data!$A:$A,0)) -> 84.875577 | BW10: =INDEX(chart_data!AH:AH,MATCH(MAX(chart_data!$A:$A),chart_data!$A:$A,0)) -> 16.928497 | BX10: =INDEX(chart_data!AI:AI,MATCH(MAX(chart_data!$A:$A),chart_data!$A:$A,0)) -> 0.24914237 | BY10: =INDEX(chart_data!AJ:AJ,MATCH(MAX(chart_data!$A:$A),chart_data!$A:$A,0)) -> 36.068459 | BZ10: =INDEX(chart_data!AK:AK,MATCH(MAX(chart_data!$A:$A),chart_data!$A:$A,0)) -> 0.73899999
A11: 32660 | B11: 1989 | C11: June | D11: 42.7 | E11: .. | F11: 40.74 | G11: 35.93 | H11: 11.48 | I11: 11.26
A12: 32690 | B12: 1989 | C12: July | D12: 41.49 | E12: .. | F12: 39.26 | G12: 35.87 | H12: 11 | I12: 10.91 | BU12: SUPERUNLEADED Pump price | BV12: =INDEX(chart_data!E:E,MATCH(MAX(chart_data!$AM:$AM),chart_data!$AM:$AM,0)) -> 173.88733 | BW12: =INDEX(chart_data!AN:AN,MATCH(MAX(chart_data!$AM:$AM),chart_data!$AM:$AM,0)) -> 14.830537 | BX12: =INDEX(chart_data!AO:AO,MATCH(MAX(chart_data!$AM:$AM),chart_data!$AM:$AM,0)) -> 0.093240514 | BY12: =INDEX(chart_data!AP:AP,MATCH(MAX(chart_data!$AM:$AM),chart_data!$AM:$AM,0)) -> 36.791918 | BZ12: =INDEX(chart_data!AQ:AQ,MATCH(MAX(chart_data!$AM:$AM),chart_data!$AM:$AM,0)) -> 0.26836725
A13: 32721 | B13: 1989 | C13: August | D13: 39.92 | E13: .. | F13: 37.4 | G13: 35.7 | H13: 11.48 | I13: 11.19 | BU13: Excluding vat and duty | BV13: =INDEX(chart_data!AR:AR,MATCH(MAX(chart_data!$AM:$AM),chart_data!$AM:$AM,0)) -> 86.956107 | BW13: =INDEX(chart_data!AS:AS,MATCH(MAX(chart_data!$AM:$AM),chart_data!$AM:$AM,0)) -> 12.358781 | BX13: =INDEX(chart_data!AT:AT,MATCH(MAX(chart_data!$AM:$AM),chart_data!$AM:$AM,0)) -> 0.16567324 | BY13: =INDEX(chart_data!AU:AU,MATCH(MAX(chart_data!$AM:$AM),chart_data!$AM:$AM,0)) -> 30.659932 | BZ13: =INDEX(chart_data!AV:AV,MATCH(MAX(chart_data!$AM:$AM),chart_data!$AM:$AM,0)) -> 0.54461838
A14: 32752 | B14: 1989 | C14: September | D14: 40.79 | E14: .. | F14: 38.19 | G14: 36 | H14: 12.33 | I14: 11.89
A15: 32782 | B15: 1989 | C15: October | D15: 40.89 | E15: .. | F15: 38.3 | G15: 37.33 | H15: 13.13 | I15: 12.5 | BU15: SGBO Including VAT (no duty) | BV15: =INDEX(chart_data!H:H,MATCH(MAX(chart_data!$AM:$AM),chart_data!$AM:$AM,0)) -> 84.861 | BW15: =INDEX(chart_data!AX:AX,MATCH(MAX(chart_data!$AM:$AM),chart_data!$AM:$AM,0)) -> 25.746 | BX15: =INDEX(chart_data!AY:AY,MATCH(MAX(chart_data!$AM:$AM),chart_data!$AM:$AM,0)) -> 0.43552398 | BY15: =INDEX(chart_data!AZ:AZ,MATCH(MAX(chart_data!$AM:$AM),chart_data!$AM:$AM,0)) -> 45.855 | BZ15: =INDEX(chart_data!BA:BA,MATCH(MAX(chart_data!$AM:$AM),chart_data!$AM:$AM,0)) -> 1.1755884
A16: 32813 | B16: 1989 | C16: November | D16: 40.68 | E16: .. | F16: 38.08 | G16: 37.76 | H16: 13.79 | I16: 13.28 | BU16: Excluding vat and duty | BV16: =INDEX(chart_data!BB:BB,MATCH(MAX(chart_data!$AM:$AM),chart_data!$AM:$AM,0)) -> 80.82 | BW16: =INDEX(chart_data!BC:BC,MATCH(MAX(chart_data!$AM:$AM),chart_data!$AM:$AM,0)) -> 24.52 | BX16: =INDEX(chart_data!BD:BD,MATCH(MAX(chart_data!$AM:$AM),chart_data!$AM:$AM,0)) -> 0.43552398 | BY16: =INDEX(chart_data!BE:BE,MATCH(MAX(chart_data!$AM:$AM),chart_data!$AM:$AM,0)) -> 43.671429 | BZ16: =INDEX(chart_data!BF:BF,MATCH(MAX(chart_data!$AM:$AM),chart_data!$AM:$AM,0)) -> 1.1755884
A17: 32843 | B17: 1989 | C17: December | D17: 39.97 | E17: .. | F17: 37.38 | G17: 39.16 | H17: 14.71 | I17: 14.44
A18: 32874 | B18: 1990 | C18: January | D18: 40.92 | E18: .. | F18: 38.37 | G18: 39.21 | H18: 15.45 | I18: 15.46 | BU18: GAS OIL including VAT and duty | BV18: =INDEX(chart_data!I:I,MATCH(MAX(chart_data!$AM:$AM),chart_data!$AM:$AM,0)) -> 121.69098 | BW18: =INDEX(chart_data!BH:BH,MATCH(MAX(chart_data!$AM:$AM),chart_data!$AM:$AM,0)) -> 44.386963 | BX18: =INDEX(chart_data!BI:BI,MATCH(MAX(chart_data!$AM:$AM),chart_data!$AM:$AM,0)) -> 0.57418698 | BY18: =INDEX(chart_data!BJ:BJ,MATCH(MAX(chart_data!$AM:$AM),chart_data!$AM:$AM,0)) -> 65.95178 | BZ18: =INDEX(chart_data!BK:BK,MATCH(MAX(chart_data!$AM:$AM),chart_data!$AM:$AM,0)) -> 1.1832207
A19: 32905 | B19: 1990 | C19: February | D19: 40.85 | E19: .. | F19: 38.26 | G19: 37.62 | H19: 13.64 | I19: 12.96 | BU19: Excluding vat and duty | BV19: =INDEX(chart_data!BL:BL,MATCH(MAX(chart_data!$AM:$AM),chart_data!$AM:$AM,0)) -> 104.75618 | BW19: =INDEX(chart_data!BM:BM,MATCH(MAX(chart_data!$AM:$AM),chart_data!$AM:$AM,0)) -> 42.273298 | BX19: =INDEX(chart_data!BN:BN,MATCH(MAX(chart_data!$AM:$AM),chart_data!$AM:$AM,0)) -> 0.67655811 | BY19: =INDEX(chart_data!BO:BO,MATCH(MAX(chart_data!$AM:$AM),chart_data!$AM:$AM,0)) -> 62.811219 | BZ19: =INDEX(chart_data!BP:BP,MATCH(MAX(chart_data!$AM:$AM),chart_data!$AM:$AM,0)) -> 1.4974677
A20: 32933 | B20: 1990 | C20: March | D20: 40.9 | E20: .. | F20: 38.28 | G20: 37.37 | H20: 13.04 | I20: 12.56
A21: 32964 | B21: 1990 | C21: April | D21: 44.27 | E21: .. | F21: 41.37 | G21: 39.19 | H21: 12.47 | I21: 12.37
A22: 32994 | B22: 1990 | C22: May | D22: 43.84 | E22: .. | F22: 40.98 | G22: 39.68 | H22: 12.19 | I22: 11.92
A23: 33025 | B23: 1990 | C23: June | D23: 43.73 | E23: .. | F23: 40.83 | G23: 38.13 | H23: 11.84 | I23: 11.51
A24: 33055 | B24: 1990 | C24: July | D24: 43.26 | E24: .. | F24: 40.33 | G24: 37.58 | H24: 12.17 | I24: 11.9
A25: 33086 | B25: 1990 | C25: August | D25: 46.82 | E25: .. | F25: 43.89 | G25: 40.26 | H25: 15.39 | I25: 14.93
A26: 33117 | B26: 1990 | C26: September | D26: 50.64 | E26: .. | F26: 47.71 | G26: 42.67 | H26: 18.31 | I26: 16.94
A27: 33147 | B27: 1990 | C27: October | D27: 51.45 | E27: .. | F27: 48.52 | G27: 45.85 | H27: 23.91 | I27: 19.66
A28: 33178 | B28: 1990 | C28: November | D28: 47.53 | E28: .. | F28: 44.55 | G28: 44.52 | H28: 20.64 | I28: 18.11
A29: 33208 | B29: 1990 | C29: December | D29: 44.28 | E29: .. | F29: 41.29 | G29: 43.7 | H29: 17.67 | I29: 17.35
A30: 33239 | B30: 1991 | C30: January | D30: 45.13 | E30: 44.38 | F30: 42.14 | G30: 43.31 | H30: 17.52 | I30: 17.13 | M30: =G30-F30 -> 1.17 | O30: 44.816254 | P30: 70.279371 | Q30: 121.4
A31: 33270 | B31: 1991 | C31: February | D31: 43.62 | E31: 42.91 | F31: 40.61 | G31: 43.19 | H31: 16.68 | I31: 15.39 | M31: =G31-F31 -> 2.58 | O31: 35.712722 | P31: 56.003512 | Q31: 96.74
A32: 33298 | B32: 1991 | C32: March | D32: 44.74 | E32: 43.8 | F32: 41.66 | G32: 40.31 | H32: 13.54 | I32: 13.4 | M32: =G32-F32 -> -1.35 | O32: 35.465383 | P32: 55.615644 | Q32: 96.07
A33: 33329 | B33: 1991 | C33: April | D33: 49.03 | E33: 47.52 | F33: 45.41 | G33: 43.41 | H33: 12.49 | I33: 12.16 | M33: =G33-F33 -> -2 | O33: 36.993714 | P33: 58.012321 | Q33: 100.21
A34: 33359 | B34: 1991 | C34: May | D34: 50.16 | E34: 48.94 | F34: 46.64 | G34: 43.64 | H34: 13.15 | I34: 12.91 | M34: =G34-F34 -> -3 | O34: 37.444091 | P34: 58.718588 | Q34: 101.43
A35: 33390 | B35: 1991 | C35: June | D35: 50.04 | E35: 48.76 | F35: 46.53 | G35: 43.64 | H35: 13.38 | I35: 13.05 | M35: =G35-F35 -> -2.89 | O35: 37.421942 | P35: 58.683854 | Q35: 101.37
A36: 33420 | B36: 1991 | C36: July | D36: 50.65 | E36: 49.35 | F36: 47.08 | G36: 44.26 | H36: 13.67 | I36: 12.97 | M36: =G36-F36 -> -2.82 | O36: 38.776766 | P36: 60.808444 | Q36: 105.04
A37: 33451 | B37: 1991 | C37: August | D37: 50.23 | E37: 48.9 | F37: 46.71 | G37: 44.17 | H37: 13.33 | I37: 12.71 | M37: =G37-F37 -> -2.54 | O37: 39.415416 | P37: 61.809954 | Q37: 106.77
A38: 33482 | B38: 1991 | C38: September | D38: 50.11 | E38: 48.85 | F38: 46.58 | G38: 44.24 | H38: 13.64 | I38: 13.01 | M38: =G38-F38 -> -2.34 | O38: 40.039299 | P38: 62.788308 | Q38: 108.46
A39: 33512 | B39: 1991 | C39: October | D39: 49.99 | E39: 48.7 | F39: 46.48 | G39: 45.1 | H39: 14.18 | I39: 13.66 | M39: =G39-F39 -> -1.38 | O39: 42.029082 | P39: 65.908619 | Q39: 113.85
A40: 33543 | B40: 1991 | C40: November | D40: 49.69 | E40: 48.44 | F40: 46.18 | G40: 46.05 | H40: 14.33 | I40: 14.25 | M40: =G40-F40 -> -0.13 | O40: 42.442543 | P40: 66.556996 | Q40: 114.97
A41: 33573 | B41: 1991 | C41: December | D41: 48.39 | E41: 47.12 | F41: 44.86 | G41: 44.5 | H41: 13.43 | I41: 13.16 | M41: =G41-F41 -> -0.36 | O41: 36.517495 | P41: 57.26553 | Q41: 98.92
... A89: 35034 | B89: 1995 | C89: December | D89: 61.83 | E89: 60.74 | F89: 55.7 | G89: 56.8 | H89: 14.69 | I89: 14.92 | M89: =G89-F89 -> 1.1 | O89: 39.463407 | P89: 61.885212 | Q89: 106.9
A90: 35065 | B90: 1996 | C90: January | D90: 61.97 | E90: 61.26 | F90: 55.93 | G90: 57.43 | H90: 15.38 | I90: 15.86 | K90: 23.342423 | M90: =G90-F90 -> 1.5 | O90: 40.904203 | P90: 64.144621 | Q90: 110.9
A91: 35096 | B91: 1996 | C91: February | D91: 59.72 | E91: 59.22 | F91: 54.45 | G91: 55.65 | H91: 15.08 | I91: 15.61 | K91: 22.889426 | M91: =G91-F91 -> 1.2 | O91: 40.074773 | P91: 62.843936 | Q91: 108.54
A92: 35125 | B92: 1996 | C92: March | D92: 59.28 | E92: 59.12 | F92: 54.2 | G92: 55.4 | H92: 16.03 | I92: 16.33 | K92: 25.607715 | M92: =G92-F92 -> 1.2 | O92: 44.652326 | P92: 70.022305 | Q92: 120.58
A93: 35156 | B93: 1996 | C93: April | D93: 60.35 | E93: 60.19 | F93: 55.24 | G93: 56.42 | H93: 16.57 | I93: 17.05 | K93: 27.415084 | M93: =G93-F93 -> 1.18 | O93: 47.905135 | P93: 75.123252 | Q93: 129.58
A94: 35186 | B94: 1996 | C94: May | D94: 60.28 | E94: 62.92 | F94: 55.13 | G94: 56.23 | H94: 15.26 | I94: 15.78 | K94: 25.160352 | M94: =G94-F94 -> 1.1 | O94: 44.164004 | P94: 69.256534 | Q94: 119.69
A95: 35217 | B95: 1996 | C95: June | D95: 59.64 | E95: 62.89 | F95: 54.67 | G95: 55.6 | H95: 14.45 | I95: 15.05 | K95: 23.659403 | M95: =G95-F95 -> 0.93 | O95: 41.461884 | P95: 65.019158 | Q95: 112.37
A96: 35247 | B96: 1996 | C96: July | D96: 59.49 | E96: 62.89 | F96: 54.34 | G96: 55.22 | H96: 14.63 | I96: 15.43 | K96: 24.776133 | M96: =G96-F96 -> 0.88 | O96: 43.221876 | P96: 67.77912 | Q96: 116.81
A97: 35278 | B97: 1996 | C97: August | D97: 61.51 | E97: 65.26 | F97: 56.77 | G97: 57.62 | H97: 14.93 | I97: 15.52 | K97: 25.756688 | M97: =G97-F97 -> 0.85 | O97: 45.056649 | P97: 70.65635 | Q97: 121.96
A98: 35309 | B98: 1996 | C98: September | D98: 63.04 | E98: 66.64 | F98: 58.24 | G98: 58.79 | H98: 17.05 | I98: 17.51 | K98: 27.738946 | M98: =G98-F98 -> 0.55 | O98: 48.486942 | P98: 76.035622 | Q98: 131.07
A99: 35339 | B99: 1996 | C99: October | D99: 63.71 | E99: 66.78 | F99: 58.78 | G99: 60.67 | H99: 17.99 | I99: 18.71 | K99: 29.481854 | M99: =G99-F99 -> 1.89 | O99: 51.454781 | P99: 80.68969 | Q99: 138.84
A100: 35370 | B100: 1996 | C100: November | D100: 64.26 | E100: 67.34 | F100: 59.25 | G100: 60.85 | H100: 16.79 | I100: 17.62 | K100: 26.72295 | M100: =G100-F100 -> 1.6 | O100: 46.818255 | P100: 73.418842 | Q100: 126.89
A101: 35400 | B101: 1996 | C101: December | D101: 66.33 | E101: 69.58 | F101: 61.25 | G101: 62.59 | H101: 17.02 | I101: 17.88 | K101: 27.984003 | M101: =G101-F101 -> 1.34 | O101: 48.903144 | P101: 76.688297 | Q101: 132.26
... A137: 36495 | B137: 1999 | C137: December | D137: 81.02 | E137: 83.54 | F137: 75.42 | G137: 77.65 | H137: 17.11 | I137: 17.73 | K137: 31.032309 | M137: =G137-F137 -> 2.23 | O137: 54.226503 | P137: 85.036212 | Q137: 146.54
A138: 36526 | B138: 2000 | C138: January | D138: 80.84 | E138: 84.15 | F138: 75.38 | G138: 77.75 | H138: 17.84 | I138: 18.15 | K138: 30.421232 | M138: =G138-F138 -> 2.37 | O138: 53.24892 | P138: 83.5032 | Q138: 144.23 | AN138: =IF(ABS(E138-E137)<0.05,0,E138-E137) -> 0.61 | AO138: =IF((E138/E137-1)<0.05,0,(E138/E137-1)) -> 0 | AP138: =IF(ABS(E138-E126)<0.05,0,E138-E126) -> 4.92 | AQ138: =IF(ABS(E138/E126-1)<0.05,0,(E138/E126-1)) -> 0.06209769 | AR138: =(E138/1.2)-57.95 -> 12.175
A139: 36557 | B139: 2000 | C139: February | D139: 80.75 | E139: 83.42 | F139: 75.14 | G139: 77.68 | H139: 17.92 | I139: 18.5 | K139: 33.867543 | M139: =G139-F139 -> 2.54 | O139: 59.257314 | P139: 92.925365 | Q139: 160.44 | AN139: =IF(ABS(E139-E138)<0.05,0,E139-E138) -> -0.73 | AO139: =IF((E139/E138-1)<0.05,0,(E139/E138-1)) -> 0 | AP139: =IF(ABS(E139-E127)<0.05,0,E139-E127) -> 5.16 | AQ139: =IF(ABS(E139/E127-1)<0.05,0,(E139/E127-1)) -> 0.065934066 | AR139: =(E139/1.2)-57.95 -> 11.566667
A140: 36586 | B140: 2000 | C140: March | D140: 82.99 | E140: 85.24 | F140: 78.32 | G140: 79.82 | H140: 18.63 | I140: 19.06 | K140: 33.62982 | M140: =G140-F140 -> 1.5 | O140: 58.858002 | P140: 92.299177 | Q140: 159.39 | AN140: =IF(ABS(E140-E139)<0.05,0,E140-E139) -> 1.82 | AO140: =IF((E140/E139-1)<0.05,0,(E140/E139-1)) -> 0 | AP140: =IF(ABS(E140-E128)<0.05,0,E140-E128) -> 3 | AQ140: =IF(ABS(E140/E128-1)<0.05,0,(E140/E128-1)) -> 0 | AR140: =(E140/1.2)-57.95 -> 13.083333
A141: 36617 | B141: 2000 | C141: April | D141: 84.45 | E141: 87.18 | F141: 79.96 | G141: 81.07 | H141: 18.33 | I141: 18.61 | K141: 28.377269 | M141: =G141-F141 -> 1.11 | O141: 49.671013 | P141: 77.892444 | Q141: 134.56 | AN141: =IF(ABS(E141-E140)<0.05,0,E141-E140) -> 1.94 | AO141: =IF((E141/E140-1)<0.05,0,(E141/E140-1)) -> 0 | AP141: =IF(ABS(E141-E129)<0.05,0,E141-E129) -> 3.79 | AQ141: =IF(ABS(E141/E129-1)<0.05,0,(E141/E129-1)) -> 0 | AR141: =(E141/1.2)-57.95 -> 14.7
A142: 36647 | B142: 2000 | C142: May | D142: 84.04 | E142: 86.93 | F142: 79.54 | G142: 80.56 | H142: 17.8 | I142: 19.17 | K142: 35.2387 | M142: =G142-F142 -> 1.02 | O142: 61.538554 | P142: 96.502729 | Q142: 166.83 | AN142: =IF(ABS(E142-E141)<0.05,0,E142-E141) -> -0.25 | AO142: =IF((E142/E141-1)<0.05,0,(E142/E141-1)) -> 0 | AP142: =IF(ABS(E142-E130)<0.05,0,E142-E130) -> 3.11 | AQ142: =IF(ABS(E142/E130-1)<0.05,0,(E142/E130-1)) -> 0 | AR142: =(E142/1.2)-57.95 -> 14.491667
A143: 36678 | B143: 2000 | C143: June | D143: 88.34 | E143: 89.86 | F143: 84.28 | G143: 82.92 | H143: 18.96 | I143: 19.99 | K143: 38.408884 | M143: =G143-F143 -> -1.36 | O143: 67.200174 | P143: 105.38109 | Q143: 181.95 | AN143: =IF(ABS(E143-E142)<0.05,0,E143-E142) -> 2.93 | AO143: =IF((E143/E142-1)<0.05,0,(E143/E142-1)) -> 0 | AP143: =IF(ABS(E143-E131)<0.05,0,E143-E131) -> 6.12 | AQ143: =IF(ABS(E143/E131-1)<0.05,0,(E143/E131-1)) -> 0.073083353 | AR143: =(E143/1.2)-57.95 -> 16.933333
A144: 36708 | B144: 2000 | C144: July | D144: 88.76 | E144: 89.94 | F144: 84.65 | G144: 83.18 | H144: 19.86 | I144: 20.81 | K144: 36.38745 | M144: =G144-F144 -> -1.47 | O144: 63.559414 | P144: 99.671776 | Q144: 172.28 | AN144: =IF(ABS(E144-E143)<0.05,0,E144-E143) -> 0.08 | AO144: =IF((E144/E143-1)<0.05,0,(E144/E143-1)) -> 0 | AP144: =IF(ABS(E144-E132)<0.05,0,E144-E132) -> 6.07 | AQ144: =IF(ABS(E144/E132-1)<0.05,0,(E144/E132-1)) -> 0.072373912 | AR144: =(E144/1.2)-57.95 -> 17
A145: 36739 | B145: 2000 | C145: August | D145: 85.86 | E145: 87.87 | F145: 80.34 | G145: 80.7 | H145: 20.83 | I145: 21.77 | K145: 38.422416 | M145: =G145-F145 -> 0.36 | O145: 67.148223 | P145: 105.29963 | Q145: 181.83 | AN145: =IF(ABS(E145-E144)<0.05,0,E145-E144) -> -2.07 | AO145: =IF((E145/E144-1)<0.05,0,(E145/E144-1)) -> 0 | AP145: =IF(ABS(E145-E133)<0.05,0,E145-E133) -> 3.3 | AQ145: =IF(ABS(E145/E133-1)<0.05,0,(E145/E133-1)) -> 0 | AR145: =(E145/1.2)-57.95 -> 15.275
A146: 36770 | B146: 2000 | C146: September | D146: 85.7 | E146: 88.39 | F146: 80.17 | G146: 82.31 | H146: 24.77 | I146: 26.4 | K146: 42.991465 | M146: =G146-F146 -> 2.14 | O146: 75.260328 | P146: 118.02076 | Q146: 203.84 | AN146: =IF(ABS(E146-E145)<0.05,0,E146-E145) -> 0.52 | AO146: =IF((E146/E145-1)<0.05,0,(E146/E145-1)) -> 0 | AP146: =IF(ABS(E146-E134)<0.05,0,E146-E134) -> 3.28 | AQ146: =IF(ABS(E146/E134-1)<0.05,0,(E146/E134-1)) -> 0 | AR146: =(E146/1.2)-57.95 -> 15.708333
A147: 36800 | B147: 2000 | C147: October | D147: 85.07 | E147: 87.82 | F147: 79.46 | G147: 81.35 | H147: 24.99 | I147: 26.13 | K147: 41.181236 | M147: =G147-F147 -> 1.89 | O147: 72.138497 | P147: 113.12521 | Q147: 195.44 | AN147: =IF(ABS(E147-E146)<0.05,0,E147-E146) -> -0.57 | AO147: =IF((E147/E146-1)<0.05,0,(E147/E146-1)) -> 0 | AP147: =IF(ABS(E147-E135)<0.05,0,E147-E135) -> 3.92 | AQ147: =IF(ABS(E147/E135-1)<0.05,0,(E147/E135-1)) -> 0 | AR147: =(E147/1.2)-57.95 -> 15.233333
A148: 36831 | B148: 2000 | C148: November | D148: 86.92 | E148: 88.83 | F148: 82.05 | G148: 84.22 | H148: 24.54 | I148: 25.73 | K148: 43.964481 | M148: =G148-F148 -> 2.17 | O148: 76.936335 | P148: 120.64902 | Q148: 208.4 | AN148: =IF(ABS(E148-E147)<0.05,0,E148-E147) -> 1.01 | AO148: =IF((E148/E147-1)<0.05,0,(E148/E147-1)) -> 0 | AP148: =IF(ABS(E148-E136)<0.05,0,E148-E136) -> 5.43 | AQ148: =IF(ABS(E148/E136-1)<0.05,0,(E148/E136-1)) -> 0.065107914 | AR148: =(E148/1.2)-57.95 -> 16.075
A149: 36861 | B149: 2000 | C149: December | D149: 84.99 | E149: 88.16 | F149: 79.83 | G149: 84.56 | H149: 22.4 | I149: 23.81 | K149: 34.552874 | M149: =G149-F149 -> 4.73 | O149: 60.392499 | P149: 94.705524 | Q149: 163.68 | AN149: =IF(ABS(E149-E148)<0.05,0,E149-E148) -> -0.67 | AO149: =IF((E149/E148-1)<0.05,0,(E149/E148-1)) -> 0 | AP149: =IF(ABS(E149-E137)<0.05,0,E149-E137) -> 4.62 | AQ149: =IF(ABS(E149/E137-1)<0.05,0,(E149/E137-1)) -> 0.055302849 | AR149: =(E149/1.2)-57.95 -> 15.516667
... A181: 37834 | B181: 2003 | C181: August | D181: 79.77 | E181: 81.26 | F181: 75.73 | G181: 77.32 | H181: 17.32 | I181: 18.51 | K181: 35.757177 | M181: =G181-F181 -> 1.59 | O181: 62.576832 | P181: 98.14808 | Q181: 170.3 | AN181: =IF(ABS(E181-E180)<0.05,0,E181-E180) -> 0.75 | AO181: =IF((E181/E180-1)<0.05,0,(E181/E180-1)) -> 0 | AP181: =IF(ABS(E181-E169)<0.05,0,E181-E169) -> 1.26 | AQ181: =IF(ABS(E181/E169-1)<0.05,0,(E181/E169-1)) -> 0 | AR181: =(E181/1.2)-57.95 -> 9.7666667
A182: 37865 | B182: 2003 | C182: September | D182: 79.81 | E182: 81.17 | F182: 76.1 | G182: 77.55 | H182: 16.81 | I182: 17.94 | K182: 32.181095 | M182: =G182-F182 -> 1.45 | O182: 56.280487 | P182: 88.07219 | Q182: .. | AN182: =IF(ABS(E182-E181)<0.05,0,E182-E181) -> -0.09 | AO182: =IF((E182/E181-1)<0.05,0,(E182/E181-1)) -> 0 | AP182: =IF(ABS(E182-E170)<0.05,0,E182-E170) -> 1.15 | AQ182: =IF(ABS(E182/E170-1)<0.05,0,(E182/E170-1)) -> 0 | AR182: =(E182/1.2)-57.95 -> 9.6916667
A183: 37895 | B183: 2003 | C183: October | D183: 80.05 | E183: 81.31 | F183: 75.84 | G183: 77.38 | H183: 17.07 | I183: 18.6 | K183: 33.971066 | M183: =G183-F183 -> 1.54 | O183: 59.465651 | P183: 93.345352 | AN183: =IF(ABS(E183-E182)<0.05,0,E183-E182) -> 0.14 | AO183: =IF((E183/E182-1)<0.05,0,(E183/E182-1)) -> 0 | AP183: =IF(ABS(E183-E171)<0.05,0,E183-E171) -> 1.26 | AQ183: =IF(ABS(E183/E171-1)<0.05,0,(E183/E171-1)) -> 0 | AR183: =(E183/1.2)-57.95 -> 9.8083333
A184: 37926 | B184: 2003 | C184: November | D184: 80.19 | E184: 81.4 | F184: 75.86 | G184: 77.45 | H184: 17.55 | I184: 18.74 | K184: 33.036261 | M184: =G184-F184 -> 1.59 | O184: 57.808322 | P184: 90.633255 | AN184: =IF(ABS(E184-E183)<0.05,0,E184-E183) -> 0.09 | AO184: =IF((E184/E183-1)<0.05,0,(E184/E183-1)) -> 0 | AP184: =IF(ABS(E184-E172)<0.05,0,E184-E172) -> 1.45 | AQ184: =IF(ABS(E184/E172-1)<0.05,0,(E184/E172-1)) -> 0 | AR184: =(E184/1.2)-57.95 -> 9.8833333
A185: 37956 | B185: 2003 | C185: December | D185: 80.25 | E185: 81.32 | F185: 75.88 | G185: 77.56 | H185: 18.2 | I185: 18.47 | K185: 33.104106 | M185: =G185-F185 -> 1.68 | O185: 57.940185 | P185: 90.909291 | AN185: =IF(ABS(E185-E184)<0.05,0,E185-E184) -> -0.08 | AO185: =IF((E185/E184-1)<0.05,0,(E185/E184-1)) -> 0 | AP185: =IF(ABS(E185-E173)<0.05,0,E185-E173) -> 1.47 | AQ185: =IF(ABS(E185/E173-1)<0.05,0,(E185/E173-1)) -> 0 | AR185: =(E185/1.2)-57.95 -> 9.8166667
A186: 37987 | B186: 2004 | C186: January | D186: 80.04 | E186: 81.49 | F186: 76.2 | G186: 77.92 | H186: 18.33 | I186: 18.95 | K186: 32.255457 | M186: =G186-F186 -> 1.72 | O186: 56.391294 | P186: 88.3 | AN186: =IF(ABS(E186-E185)<0.05,0,E186-E185) -> 0.17 | AO186: =IF((E186/E185-1)<0.05,0,(E186/E185-1)) -> 0 | AP186: =IF(ABS(E186-E174)<0.05,0,E186-E174) -> 1.02 | AQ186: =IF(ABS(E186/E174-1)<0.05,0,(E186/E174-1)) -> 0 | AR186: =(E186/1.2)-57.95 -> 9.9583333
A187: 38018 | B187: 2004 | C187: February | D187: 79.89 | E187: 81.42 | F187: 76.36 | G187: 77.93 | H187: 17.73 | I187: 17.58 | K187: 31.821074 | M187: =G187-F187 -> 1.57 | O187: 55.69972 | P187: 87.4 | AN187: =IF(ABS(E187-E186)<0.05,0,E187-E186) -> -0.07 | AO187: =IF((E187/E186-1)<0.05,0,(E187/E186-1)) -> 0 | AP187: =IF(ABS(E187-E175)<0.05,0,E187-E175) -> 0.11 | AQ187: =IF(ABS(E187/E175-1)<0.05,0,(E187/E175-1)) -> 0 | AR187: =(E187/1.2)-57.95 -> 9.9
A188: 38047 | B188: 2004 | C188: March | D188: 80.96 | E188: 82.36 | F188: 77.15 | G188: 78.6 | H188: 17.97 | I188: 18.71 | K188: 35.284164 | M188: =G188-F188 -> 1.45 | O188: 61.740841 | P188: 96.9 | AN188: =IF(ABS(E188-E187)<0.05,0,E188-E187) -> 0.94 | AO188: =IF((E188/E187-1)<0.05,0,(E188/E187-1)) -> 0 | AP188: =IF(ABS(E188-E176)<0.05,0,E188-E176) -> -0.56 | AQ188: =IF(ABS(E188/E176-1)<0.05,0,(E188/E176-1)) -> 0 | AR188: =(E188/1.2)-57.95 -> 10.683333
A189: 38078 | B189: 2004 | C189: April | D189: 81.25 | E189: 82.53 | F189: 77.81 | G189: 79.21 | H189: 18.31 | I189: 19.5 | K189: 35.204451 | M189: =G189-F189 -> 1.4 | O189: 61.600769 | P189: 96.7 | AN189: =IF(ABS(E189-E188)<0.05,0,E189-E188) -> 0.17 | AO189: =IF((E189/E188-1)<0.05,0,(E189/E188-1)) -> 0 | AP189: =IF(ABS(E189-E177)<0.05,0,E189-E177) -> -0.57 | AQ189: =IF(ABS(E189/E177-1)<0.05,0,(E189/E177-1)) -> 0 | AR189: =(E189/1.2)-57.95 -> 10.825
A190: 38108 | B190: 2004 | C190: May | D190: 84.32 | E190: 86.24 | F190: 81.02 | G190: 82.32 | H190: 21.12 | I190: 20.89 | K190: 40.211929 | M190: =G190-F190 -> 1.3 | O190: 70.44249 | P190: 110.5 | AN190: =IF(ABS(E190-E189)<0.05,0,E190-E189) -> 3.71 | AO190: =IF((E190/E189-1)<0.05,0,(E190/E189-1)) -> 0 | AP190: =IF(ABS(E190-E178)<0.05,0,E190-E178) -> 5.03 | AQ190: =IF(ABS(E190/E178-1)<0.05,0,(E190/E178-1)) -> 0.061938185 | AR190: =(E190/1.2)-57.95 -> 13.916667
A191: 38139 | B191: 2004 | C191: June | D191: 85.01 | E191: 87.06 | F191: 81.7 | G191: 82.86 | H191: 19.77 | I191: 20.56 | K191: 37.077416 | M191: =G191-F191 -> 1.16 | O191: 64.905667 | P191: 101.7 | AN191: =IF(ABS(E191-E190)<0.05,0,E191-E190) -> 0.82 | AO191: =IF((E191/E190-1)<0.05,0,(E191/E190-1)) -> 0 | AP191: =IF(ABS(E191-E179)<0.05,0,E191-E179) -> 6.67 | AQ191: =IF(ABS(E191/E179-1)<0.05,0,(E191/E179-1)) -> 0.082970519 | AR191: =(E191/1.2)-57.95 -> 14.6
A192: 38169 | B192: 2004 | C192: July | D192: 84.77 | E192: 86.23 | F192: 80.35 | G192: 81.17 | H192: 20.69 | I192: 21.42 | K192: 38.960001 | M192: =G192-F192 -> 0.82 | O192: 68.252814 | P192: 106.9 | AN192: =IF(ABS(E192-E191)<0.05,0,E192-E191) -> -0.83 | AO192: =IF((E192/E191-1)<0.05,0,(E192/E191-1)) -> 0 | AP192: =IF(ABS(E192-E180)<0.05,0,E192-E180) -> 5.72 | AQ192: =IF(ABS(E192/E180-1)<0.05,0,(E192/E180-1)) -> 0.071047075 | AR192: =(E192/1.2)-57.95 -> 13.908333
A193: 38200 | B193: 2004 | C193: August | D193: 85.29 | E193: 86.64 | F193: 81.14 | G193: 82.28 | H193: 22.84 | I193: 23.58 | K193: 45.504235 | M193: =G193-F193 -> 1.14 | O193: 79.614644 | P193: 124.9 | AN193: =IF(ABS(E193-E192)<0.05,0,E193-E192) -> 0.41 | AO193: =IF((E193/E192-1)<0.05,0,(E193/E192-1)) -> 0 | AP193: =IF(ABS(E193-E181)<0.05,0,E193-E181) -> 5.38 | AQ193: =IF(ABS(E193/E181-1)<0.05,0,(E193/E181-1)) -> 0.066207236 | AR193: =(E193/1.2)-57.95 -> 14.25
A194: 38231 | B194: 2004 | C194: September | D194: 86.15 | E194: 86.74 | F194: 81.25 | G194: 82.94 | H194: 23.58 | I194: 23.96 | K194: 46.31323 | M194: =G194-F194 -> 1.69 | O194: 81.078529 | P194: 127.2 | AN194: =IF(ABS(E194-E193)<0.05,0,E194-E193) -> 0.1 | AO194: =IF((E194/E193-1)<0.05,0,(E194/E193-1)) -> 0 | AP194: =IF(ABS(E194-E182)<0.05,0,E194-E182) -> 5.57 | AQ194: =IF(ABS(E194/E182-1)<0.05,0,(E194/E182-1)) -> 0.068621412 | AR194: =(E194/1.2)-57.95 -> 14.333333
... A205: 38565 | B205: 2005 | C205: August | D205: 91.99 | E205: 96.59 | F205: 90.4 | G205: 94.33 | H205: 32.11 | I205: 33.47 | K205: 68.213591 | M205: =G205-F205 -> 3.93 | O205: 119.39025 | P205: 187.3 | AN205: =IF(ABS(E205-E204)<0.05,0,E205-E204) -> 1.78 | AO205: =IF((E205/E204-1)<0.05,0,(E205/E204-1)) -> 0 | AP205: =IF(ABS(E205-E193)<0.05,0,E205-E193) -> 9.95 | AQ205: =IF(ABS(E205/E193-1)<0.05,0,(E205/E193-1)) -> 0.11484303 | AR205: =(E205/1.2)-57.95 -> 22.541667
A206: 38596 | B206: 2005 | C206: September | E206: 99.48 | F206: 94.77 | G206: 97.58 | H206: 33.57 | I206: 35.54 | K206: 66.236 | M206: =G206-F206 -> 2.81 | O206: 115.99747 | P206: 182 | AN206: =IF(ABS(E206-E205)<0.05,0,E206-E205) -> 2.89 | AO206: =IF((E206/E205-1)<0.05,0,(E206/E205-1)) -> 0 | AP206: =IF(ABS(E206-E194)<0.05,0,E206-E194) -> 12.74 | AQ206: =IF(ABS(E206/E194-1)<0.05,0,(E206/E194-1)) -> 0.14687572 | AR206: =(E206/1.2)-57.95 -> 24.95
A207: 38626 | B207: 2005 | C207: October | E207: 100.3 | F207: 94 | G207: 96.94 | H207: 34.95 | I207: 36.34 | K207: 63.669633 | M207: =G207-F207 -> 2.94 | O207: 111.43426 | P207: 174.8 | AN207: =IF(ABS(E207-E206)<0.05,0,E207-E206) -> 0.82 | AO207: =IF((E207/E206-1)<0.05,0,(E207/E206-1)) -> 0 | AP207: =IF(ABS(E207-E195)<0.05,0,E207-E195) -> 11.18 | AQ207: =IF(ABS(E207/E195-1)<0.05,0,(E207/E195-1)) -> 0.12544883 | AR207: =(E207/1.2)-57.95 -> 25.633333
A208: 38657 | B208: 2005 | C208: November | E208: 97.11 | F208: 90.3 | G208: 94.74 | H208: 31.1 | I208: 33.09 | K208: 62.189706 | M208: =G208-F208 -> 4.44 | O208: 108.80907 | P208: 170.6 | AN208: =IF(ABS(E208-E207)<0.05,0,E208-E207) -> -3.19 | AO208: =IF((E208/E207-1)<0.05,0,(E208/E207-1)) -> 0 | AP208: =IF(ABS(E208-E196)<0.05,0,E208-E196) -> 7.35 | AQ208: =IF(ABS(E208/E196-1)<0.05,0,(E208/E196-1)) -> 0.081885027 | AR208: =(E208/1.2)-57.95 -> 22.975
A209: 38687 | B209: 2005 | C209: December | E209: 95.33 | F209: 87.45 | G209: 91.72 | H209: 30.53 | I209: 33.3 | K209: 62.685426 | M209: =G209-F209 -> 4.27 | O209: 109.72106 | P209: 172.1 | AN209: =IF(ABS(E209-E208)<0.05,0,E209-E208) -> -1.78 | AO209: =IF((E209/E208-1)<0.05,0,(E209/E208-1)) -> 0 | AP209: =IF(ABS(E209-E197)<0.05,0,E209-E197) -> 5.92 | AQ209: =IF(ABS(E209/E197-1)<0.05,0,(E209/E197-1)) -> 0.066211833 | AR209: =(E209/1.2)-57.95 -> 21.491667
A210: 38718 | B210: 2006 | C210: January | E210: 94.73 | F210: 88.84 | G210: 93.07 | H210: 31.58 | I210: 33.6 | K210: 67.80606 | M210: =G210-F210 -> 4.23 | O210: 118.6992 | P210: 186.2 | AN210: =IF(ABS(E210-E209)<0.05,0,E210-E209) -> -0.6 | AO210: =IF((E210/E209-1)<0.05,0,(E210/E209-1)) -> 0 | AP210: =IF(ABS(E210-E198)<0.05,0,E210-E198) -> 7.3 | AQ210: =IF(ABS(E210/E198-1)<0.05,0,(E210/E198-1)) -> 0.083495368 | AR210: =(E210/1.2)-57.95 -> 20.991667
A211: 38749 | B211: 2006 | C211: February | E211: 96.8 | F211: 89.46 | G211: 93.66 | H211: 32.16 | I211: 33.79 | K211: 66.566955 | M211: =G211-F211 -> 4.2 | O211: 116.49436 | P211: 182.7 | AN211: =IF(ABS(E211-E210)<0.05,0,E211-E210) -> 2.07 | AO211: =IF((E211/E210-1)<0.05,0,(E211/E210-1)) -> 0 | AP211: =IF(ABS(E211-E199)<0.05,0,E211-E199) -> 9.36 | AQ211: =IF(ABS(E211/E199-1)<0.05,0,(E211/E199-1)) -> 0.10704483 | AR211: =(E211/1.2)-57.95 -> 22.716667
A212: 38777 | B212: 2006 | C212: March | E212: 96.61 | F212: 89.43 | G212: 93.75 | H212: 32.12 | I212: 34.08 | K212: 67.481056 | M212: =G212-F212 -> 4.32 | O212: 118.14868 | P212: 185.1 | AN212: =IF(ABS(E212-E211)<0.05,0,E212-E211) -> -0.19 | AO212: =IF((E212/E211-1)<0.05,0,(E212/E211-1)) -> 0 | AP212: =IF(ABS(E212-E200)<0.05,0,E212-E200) -> 8.63 | AQ212: =IF(ABS(E212/E200-1)<0.05,0,(E212/E200-1)) -> 0.098090475 | AR212: =(E212/1.2)-57.95 -> 22.558333
A213: 38808 | B213: 2006 | C213: April | E213: 99.42 | F213: 94.14 | G213: 97.59 | H213: 33.16 | I213: 35.31 | K213: 75.312329 | M213: =G213-F213 -> 3.45 | O213: 131.72817 | P213: 206.7 | AN213: =IF(ABS(E213-E212)<0.05,0,E213-E212) -> 2.81 | AO213: =IF((E213/E212-1)<0.05,0,(E213/E212-1)) -> 0 | AP213: =IF(ABS(E213-E201)<0.05,0,E213-E201) -> 8.31 | AQ213: =IF(ABS(E213/E201-1)<0.05,0,(E213/E201-1)) -> 0.091208429 | AR213: =(E213/1.2)-57.95 -> 24.9
A214: 38838 | B214: 2006 | C214: May | E214: 102.35 | F214: 96.12 | G214: 98.47 | H214: 34.07 | I214: 36.12 | K214: 71.391945 | M214: =G214-F214 -> 2.35 | O214: 124.98569 | P214: 195.8 | AN214: =IF(ABS(E214-E213)<0.05,0,E214-E213) -> 2.93 | AO214: =IF((E214/E213-1)<0.05,0,(E214/E213-1)) -> 0 | AP214: =IF(ABS(E214-E202)<0.05,0,E214-E202) -> 10.75 | AQ214: =IF(ABS(E214/E202-1)<0.05,0,(E214/E202-1)) -> 0.11735808 | AR214: =(E214/1.2)-57.95 -> 27.341667
A215: 38869 | B215: 2006 | C215: June | E215: 101.37 | F215: 95.3 | G215: 97.66 | H215: 33.75 | I215: 36.17 | K215: 70.772206 | M215: =G215-F215 -> 2.36 | O215: 123.86411 | P215: 194.3 | AN215: =IF(ABS(E215-E214)<0.05,0,E215-E214) -> -0.98 | AO215: =IF((E215/E214-1)<0.05,0,(E215/E214-1)) -> 0 | AP215: =IF(ABS(E215-E203)<0.05,0,E215-E203) -> 9.7 | AQ215: =IF(ABS(E215/E203-1)<0.05,0,(E215/E203-1)) -> 0.10581433 | AR215: =(E215/1.2)-57.95 -> 26.525
A216: 38899 | B216: 2006 | C216: July | E216: 102.53 | F216: 96.78 | G216: 98.68 | H216: 37.4 | I216: 40.82 | K216: 76.419974 | M216: =G216-F216 -> 1.9 | O216: 133.78262 | P216: 209.7 | AN216: =IF(ABS(E216-E215)<0.05,0,E216-E215) -> 1.16 | AO216: =IF((E216/E215-1)<0.05,0,(E216/E215-1)) -> 0 | AP216: =IF(ABS(E216-E204)<0.05,0,E216-E204) -> 7.72 | AQ216: =IF(ABS(E216/E204-1)<0.05,0,(E216/E204-1)) -> 0.08142601 | AR216: =(E216/1.2)-57.95 -> 27.491667
A217: 38930 | B217: 2006 | C217: August | E217: 103.01 | F217: 97.67 | G217: 99.38 | H217: 37.36 | I217: 41.11 | K217: 74.158043 | M217: =G217-F217 -> 1.71 | O217: 129.76338 | P217: 203.7 | AN217: =IF(ABS(E217-E216)<0.05,0,E217-E216) -> 0.48 | AO217: =IF((E217/E216-1)<0.05,0,(E217/E216-1)) -> 0 | AP217: =IF(ABS(E217-E205)<0.05,0,E217-E205) -> 6.42 | AQ217: =IF(ABS(E217/E205-1)<0.05,0,(E217/E205-1)) -> 0.066466508 | AR217: =(E217/1.2)-57.95 -> 27.891667
... A258: 40179 | B258: 2010 | C258: January | E258: 118.52927 | F258: 111.48884 | G258: 113.311 | H258: 42.490196 | I258: 50.639435 | K258: 91.870437 | M258: =G258-F258 -> 1.8221665 | O258: 160.72709 | P258: 257.45042 | AN258: =IF(ABS(E258-E257)<0.05,0,E258-E257) -> 3.7713136 | AO258: =IF((E258/E257-1)<0.05,0,(E258/E257-1)) -> 0 | AP258: =IF(ABS(E258-E246)<0.05,0,E258-E246) -> 25.229275 | AQ258: =IF(ABS(E258/E246-1)<0.05,0,(E258/E246-1)) -> 0.27041023 | AR258: =(E258/1.2)-57.95 -> 40.824396
A259: 40210 | B259: 2010 | C259: February | E259: 118.52849 | F259: 111.64594 | G259: 113.38498 | H259: 43.198321 | I259: 50.045117 | K259: 92.739631 | M259: =G259-F259 -> 1.739037 | O259: 162.24124 | AN259: =IF(ABS(E259-E258)<0.05,0,E259-E258) -> 0 | AO259: =IF((E259/E258-1)<0.05,0,(E259/E258-1)) -> 0 | AP259: =IF(ABS(E259-E247)<0.05,0,E259-E247) -> 22.178491 | AQ259: =IF(ABS(E259/E247-1)<0.05,0,(E259/E247-1)) -> 0.23018673 | AR259: =(E259/1.2)-57.95 -> 40.823743
A260: 40238 | B260: 2010 | C260: March | E260: 121.87084 | F260: 115.46876 | G260: 116.20458 | H260: 45.11764 | I260: 52.501819 | K260: 101.86678 | M260: =G260-F260 -> 0.73582304 | O260: 178.22082 | AN260: =IF(ABS(E260-E259)<0.05,0,E260-E259) -> 3.3423468 | AO260: =IF((E260/E259-1)<0.05,0,(E260/E259-1)) -> 0 | AP260: =IF(ABS(E260-E248)<0.05,0,E260-E248) -> 25.410838 | AQ260: =IF(ABS(E260/E248-1)<0.05,0,(E260/E248-1)) -> 0.26343394 | AR260: =(E260/1.2)-57.95 -> 43.609032
A261: 40269 | B261: 2010 | C261: April | E261: 126.09781 | F261: 119.80299 | G261: 120.98551 | H261: 46.682493 | I261: 55.155251 | K261: 106.52561 | M261: =G261-F261 -> 1.1825139 | O261: 186.40964 | AN261: =IF(ABS(E261-E260)<0.05,0,E261-E260) -> 4.2269712 | AO261: =IF((E261/E260-1)<0.05,0,(E261/E260-1)) -> 0 | AP261: =IF(ABS(E261-E249)<0.05,0,E261-E249) -> 26.647809 | AQ261: =IF(ABS(E261/E249-1)<0.05,0,(E261/E249-1)) -> 0.26795183 | AR261: =(E261/1.2)-57.95 -> 47.131508
A262: 40299 | B262: 2010 | C262: May | E262: 127.08088 | F262: 121.17919 | G262: 122.75372 | H262: 47.413579 | I262: 56.428913 | K262: 99.584032 | M262: =G262-F262 -> 1.5745338 | O262: 174.20931 | AN262: =IF(ABS(E262-E261)<0.05,0,E262-E261) -> 0.98306993 | AO262: =IF((E262/E261-1)<0.05,0,(E262/E261-1)) -> 0 | AP262: =IF(ABS(E262-E250)<0.05,0,E262-E250) -> 23.880879 | AQ262: =IF(ABS(E262/E250-1)<0.05,0,(E262/E250-1)) -> 0.23140387 | AR262: =(E262/1.2)-57.95 -> 47.950732
A263: 40330 | B263: 2010 | C263: June | E263: 124.85221 | F263: 117.70088 | G263: 120.11671 | H263: 46.752187 | I263: 55.309938 | K263: 98.146187 | M263: =G263-F263 -> 2.4158349 | O263: 171.75354 | AN263: =IF(ABS(E263-E262)<0.05,0,E263-E262) -> -2.2286707 | AO263: =IF((E263/E262-1)<0.05,0,(E263/E262-1)) -> 0 | AP263: =IF(ABS(E263-E251)<0.05,0,E263-E251) -> 16.882208 | AQ263: =IF(ABS(E263/E251-1)<0.05,0,(E263/E251-1)) -> 0.15636018 | AR263: =(E263/1.2)-57.95 -> 46.093507
...
